Workbook

Sheet README
B1: Security Assessment Operating System (SAOS)
B2: Assessment workbook v0.1 (Phase 0 + Server Security pilot) | built 2025-11-28
B4: Purpose
B5: Vendor-neutral, framework-driven assessment toolkit for client engagements. Every control carries a purpose, evidence requirements, test procedure, maturity anchors, risk rating, remediation guidance and framework mappings.
B6: This release contains the Phase 0 foundations (methodology, risk and maturity models, registers, dashboard) and the first completed domain: Server Security (60 controls). See Domain_Registry for build status of all domains.
B8: How to run an engagement
B9: 1. Scope: complete the Scope sheet (client, tier, platforms, domains). Applicable? and target maturity pre-fill from it.
B10: 2. Evidence: send Evidence_Requests to the client; log each received item in Evidence_Register and link its ID back to the request.
B11: 3. Assess: in Assessment score Current Maturity 0-5 for each control using Maturity_Model and the L1/L3/L5 anchors in Control_Library. Record tests performed, evidence IDs and notes.
B12: 4. Findings and risks: raise a finding for each material gap in Findings_Register, a matching entry in Risk_Register, and an action in Remediation_Tracker.
B13: 5. Context: capture Crown_Jewels and Attack_Paths so findings are prioritised by business criticality and realistic attack routes.
B14: 6. Report: read results from Dashboard, then complete the Word executive report template.
... B34: Registers are formatted for 200 rows; Assessment and dashboard formulas read to row 2000 so the library can grow to its full size.

Sheet Scope
A1: Engagement Scope
A2: Blue cells on yellow are inputs. Domain and platform choices pre-fill the "Applicable?" column in the Assessment sheet.
B3: Engagement | E3: Default target by tier
B4: Client name | E4: Org tier | F4: Default target
B5: Engagement reference | E5: SMB | F5: 2
B6: Assessment start date | E6: Mid-size | F6: 3
B7: Assessment end date | E7: Enterprise | F7: 3
B8: Lead assessor | E8: Multinational | F8: 4
B9: Reviewer | E9: Government | F9: 4
B10: Organisation size tier | E10: SAOS defaults - edit to client risk appetite.
B11: Industry
B12: Regulatory and contractual drivers
B13: Default target maturity | C13: =IFERROR(INDEX($F$5:$F$9,MATCH(C10,$E$5:$E$9,0)),3) -> 3
B14: Default comes from the tier table; overtype C13 to set a client-specific target. Individual targets can be overtyped in Assessment column L.
B16: Platform scope
B17: Platform | C17: In scope? | G17: Notes
B18: Windows | C18: Yes | G18: Windows Server
B19: Linux | C19: Yes | G19: Linux servers
B20: Hypervisor | C20: Yes | G20: VMware, Hyper-V, Proxmox
B22: Domain scope
B23: Domain | C23: In scope? | G23: Notes
B24: Governance | C24: Yes
B25: Asset Management | C25: Yes
B26: Identity and Access Management | C26: Yes
B27: Endpoint Security | C27: Yes
B28: Server Security | C28: Yes
B29: Network Security | C29: Yes
B30: Microsoft 365 | C30: Yes
B31: Cloud Security | C31: Yes
B32: Application Security | C32: Yes
B33: API Security | C33: Yes
B34: Security Operations | C34: Yes
B35: Vulnerability Management | C35: Yes
... B41: AI Systems (future) | C41: Yes

Sheet Dashboard
B1: SAOS Executive Dashboard
B2: ="Client: "&IF(Scope!C4="","(not set)",Scope!C4)&" | Assessment period: "&IF(Scope!C6="","(not set)",TEXT(Scope!C6,"yyyy-mm-dd"))&" to "&IF(Scope!C7="","(not set)",TEXT(Scope!C7,"yyyy-mm-dd")) -> Client: (not set) | Assessment period: (not set) to (not set)
B4: Overall maturity (0-5) | C4: Maturity % | E4: Assessment completion | G4: Controls with a gap | I4: Critical / High residual | K4: Open Critical/High findings
B5: =IFERROR(SUMPRODUCT((Assessment!$J$5:$J$2000="Yes")*ISNUMBER(Assessment!$K$5:$K$2000)*Assessment!$G$5:$G$2000*Assessment!$K$5:$K$2000)/SUMPRODUCT((Assessment!$J$5:$J$2000="Yes")*ISNUMBER(Assessment!$K$5:$K$2000)*Assessment!$G$5:$G$2000),"n/a") -> n/a | C5: =IFERROR(SUMPRODUCT((Assessment!$J$5:$J$2000="Yes")*ISNUMBER(Assessment!$K$5:$K$2000)*Assessment!$G$5:$G$2000*Assessment!$K$5:$K$2000)/SUMPRODUCT((Assessment!$J$5:$J$2000="Yes")*ISNUMBER(Assessment!$K$5:$K$2000)*Assessment!$G$5:$G$2000)/5,"n/a") -> n/a | E5: =IFERROR(COUNTIFS(Assessment!$J$5:$J$2000,"Yes",Assessment!$K$5:$K$2000,">=0")/COUNTIF(Assessment!$J$5:$J$2000,"Yes"),0) -> 0 | G5: =COUNTIF(Assessment!$N$5:$N$2000,"Gap") -> 0 | I5: =COUNTIF(Assessment!$Z$5:$Z$2000,"Critical")+COUNTIF(Assessment!$Z$5:$Z$2000,"High") -> 0 | K5: =COUNTIFS(Findings_Register!$F$6:$F$205,"Critical",Findings_Register!$K$6:$K$205,"Open")+COUNTIFS(Findings_Register!$F$6:$F$205,"Critical",Findings_Register!$K$6:$K$205,"In Progress")+COUNTIFS(Findings_Register!$F$6:$F$205,"High",Findings_Register!$K$6:$K$205,"Open")+COUNTIFS(Findings_Register!$F$6:$F$205,"High",Findings_Register!$K$6:$K$205,"In Progress") -> 0
B7: Domain scores
B8: Domain | C8: Controls in library | D8: In scope | E8: Assessed | F8: Avg maturity | G8: Avg target | H8: Gap | I8: Status
B9: Governance | C9: =COUNTIF(Control_Library!$B$5:$B$3000,B9) -> 0 | D9: =COUNTIFS(Assessment!$B$5:$B$2000,B9,Assessment!$J$5:$J$2000,"Yes") -> 0 | E9: =COUNTIFS(Assessment!$B$5:$B$2000,$B9,Assessment!$J$5:$J$2000,"Yes",Assessment!$K$5:$K$2000,">=0") -> 0 | F9: =IF(E9=0,"-",SUMPRODUCT((Assessment!$B$5:$B$2000=$B9)*(Assessment!$J$5:$J$2000="Yes")*ISNUMBER(Assessment!$K$5:$K$2000)*Assessment!$G$5:$G$2000*Assessment!$K$5:$K$2000)/SUMPRODUCT((Assessment!$B$5:$B$2000=$B9)*(Assessment!$J$5:$J$2000="Yes")*ISNUMBER(Assessment!$K$5:$K$2000)*Assessment!$G$5:$G$2000)) -> - | G9: =IF(E9=0,"-",SUMPRODUCT((Assessment!$B$5:$B$2000=$B9)*(Assessment!$J$5:$J$2000="Yes")*ISNUMBER(Assessment!$K$5:$K$2000)*Assessment!$G$5:$G$2000*Assessment!$L$5:$L$2000)/SUMPRODUCT((Assessment!$B$5:$B$2000=$B9)*(Assessment!$J$5:$J$2000="Yes")*ISNUMBER(Assessment!$K$5:$K$2000)*Assessment!$G$5:$G$2000)) -> - | H9: =IF(E9=0,"-",MAX(0,G9-F9)) -> - | I9: =IF(E9=0,"Not assessed",IF(H9<=0,"On target",IF(H9<=1,"Minor gap","Significant gap"))) -> Not assessed
B10: Asset Management | C10: =COUNTIF(Control_Library!$B$5:$B$3000,B10) -> 0 | D10: =COUNTIFS(Assessment!$B$5:$B$2000,B10,Assessment!$J$5:$J$2000,"Yes") -> 0 | E10: =COUNTIFS(Assessment!$B$5:$B$2000,$B10,Assessment!$J$5:$J$2000,"Yes",Assessment!$K$5:$K$2000,">=0") -> 0 | F10: =IF(E10=0,"-",SUMPRODUCT((Assessment!$B$5:$B$2000=$B10)*(Assessment!$J$5:$J$2000="Yes")*ISNUMBER(Assessment!$K$5:$K$2000)*Assessment!$G$5:$G$2000*Assessment!$K$5:$K$2000)/SUMPRODUCT((Assessment!$B$5:$B$2000=$B10)*(Assessment!$J$5:$J$2000="Yes")*ISNUMBER(Assessment!$K$5:$K$2000)*Assessment!$G$5:$G$2000)) -> - | G10: =IF(E10=0,"-",SUMPRODUCT((Assessment!$B$5:$B$2000=$B10)*(Assessment!$J$5:$J$2000="Yes")*ISNUMBER(Assessment!$K$5:$K$2000)*Assessment!$G$5:$G$2000*Assessment!$L$5:$L$2000)/SUMPRODUCT((Assessment!$B$5:$B$2000=$B10)*(Assessment!$J$5:$J$2000="Yes")*ISNUMBER(Assessment!$K$5:$K$2000)*Assessment!$G$5:$G$2000)) -> - | H10: =IF(E10=0,"-",MAX(0,G10-F10)) -> - | I10: =IF(E10=0,"Not assessed",IF(H10<=0,"On target",IF(H10<=1,"Minor gap","Significant gap"))) -> Not assessed
B11: Identity and Access Management | C11: =COUNTIF(Control_Library!$B$5:$B$3000,B11) -> 0 | D11: =COUNTIFS(Assessment!$B$5:$B$2000,B11,Assessment!$J$5:$J$2000,"Yes") -> 0 | E11: =COUNTIFS(Assessment!$B$5:$B$2000,$B11,Assessment!$J$5:$J$2000,"Yes",Assessment!$K$5:$K$2000,">=0") -> 0 | F11: =IF(E11=0,"-",SUMPRODUCT((Assessment!$B$5:$B$2000=$B11)*(Assessment!$J$5:$J$2000="Yes")*ISNUMBER(Assessment!$K$5:$K$2000)*Assessment!$G$5:$G$2000*Assessment!$K$5:$K$2000)/SUMPRODUCT((Assessment!$B$5:$B$2000=$B11)*(Assessment!$J$5:$J$2000="Yes")*ISNUMBER(Assessment!$K$5:$K$2000)*Assessment!$G$5:$G$2000)) -> - | G11: =IF(E11=0,"-",SUMPRODUCT((Assessment!$B$5:$B$2000=$B11)*(Assessment!$J$5:$J$2000="Yes")*ISNUMBER(Assessment!$K$5:$K$2000)*Assessment!$G$5:$G$2000*Assessment!$L$5:$L$2000)/SUMPRODUCT((Assessment!$B$5:$B$2000=$B11)*(Assessment!$J$5:$J$2000="Yes")*ISNUMBER(Assessment!$K$5:$K$2000)*Assessment!$G$5:$G$2000)) -> - | H11: =IF(E11=0,"-",MAX(0,G11-F11)) -> - | I11: =IF(E11=0,"Not assessed",IF(H11<=0,"On target",IF(H11<=1,"Minor gap","Significant gap"))) -> Not assessed
B12: Endpoint Security | C12: =COUNTIF(Control_Library!$B$5:$B$3000,B12) -> 0 | D12: =COUNTIFS(Assessment!$B$5:$B$2000,B12,Assessment!$J$5:$J$2000,"Yes") -> 0 | E12: =COUNTIFS(Assessment!$B$5:$B$2000,$B12,Assessment!$J$5:$J$2000,"Yes",Assessment!$K$5:$K$2000,">=0") -> 0 | F12: =IF(E12=0,"-",SUMPRODUCT((Assessment!$B$5:$B$2000=$B12)*(Assessment!$J$5:$J$2000="Yes")*ISNUMBER(Assessment!$K$5:$K$2000)*Assessment!$G$5:$G$2000*Assessment!$K$5:$K$2000)/SUMPRODUCT((Assessment!$B$5:$B$2000=$B12)*(Assessment!$J$5:$J$2000="Yes")*ISNUMBER(Assessment!$K$5:$K$2000)*Assessment!$G$5:$G$2000)) -> - | G12: =IF(E12=0,"-",SUMPRODUCT((Assessment!$B$5:$B$2000=$B12)*(Assessment!$J$5:$J$2000="Yes")*ISNUMBER(Assessment!$K$5:$K$2000)*Assessment!$G$5:$G$2000*Assessment!$L$5:$L$2000)/SUMPRODUCT((Assessment!$B$5:$B$2000=$B12)*(Assessment!$J$5:$J$2000="Yes")*ISNUMBER(Assessment!$K$5:$K$2000)*Assessment!$G$5:$G$2000)) -> - | H12: =IF(E12=0,"-",MAX(0,G12-F12)) -> - | I12: =IF(E12=0,"Not assessed",IF(H12<=0,"On target",IF(H12<=1,"Minor gap","Significant gap"))) -> Not assessed
B13: Server Security | C13: =COUNTIF(Control_Library!$B$5:$B$3000,B13) -> 60 | D13: =COUNTIFS(Assessment!$B$5:$B$2000,B13,Assessment!$J$5:$J$2000,"Yes") -> 60 | E13: =COUNTIFS(Assessment!$B$5:$B$2000,$B13,Assessment!$J$5:$J$2000,"Yes",Assessment!$K$5:$K$2000,">=0") -> 0 | F13: =IF(E13=0,"-",SUMPRODUCT((Assessment!$B$5:$B$2000=$B13)*(Assessment!$J$5:$J$2000="Yes")*ISNUMBER(Assessment!$K$5:$K$2000)*Assessment!$G$5:$G$2000*Assessment!$K$5:$K$2000)/SUMPRODUCT((Assessment!$B$5:$B$2000=$B13)*(Assessment!$J$5:$J$2000="Yes")*ISNUMBER(Assessment!$K$5:$K$2000)*Assessment!$G$5:$G$2000)) -> - | G13: =IF(E13=0,"-",SUMPRODUCT((Assessment!$B$5:$B$2000=$B13)*(Assessment!$J$5:$J$2000="Yes")*ISNUMBER(Assessment!$K$5:$K$2000)*Assessment!$G$5:$G$2000*Assessment!$L$5:$L$2000)/SUMPRODUCT((Assessment!$B$5:$B$2000=$B13)*(Assessment!$J$5:$J$2000="Yes")*ISNUMBER(Assessment!$K$5:$K$2000)*Assessment!$G$5:$G$2000)) -> - | H13: =IF(E13=0,"-",MAX(0,G13-F13)) -> - | I13: =IF(E13=0,"Not assessed",IF(H13<=0,"On target",IF(H13<=1,"Minor gap","Significant gap"))) -> Not assessed
B14: Network Security | C14: =COUNTIF(Control_Library!$B$5:$B$3000,B14) -> 0 | D14: =COUNTIFS(Assessment!$B$5:$B$2000,B14,Assessment!$J$5:$J$2000,"Yes") -> 0 | E14: =COUNTIFS(Assessment!$B$5:$B$2000,$B14,Assessment!$J$5:$J$2000,"Yes",Assessment!$K$5:$K$2000,">=0") -> 0 | F14: =IF(E14=0,"-",SUMPRODUCT((Assessment!$B$5:$B$2000=$B14)*(Assessment!$J$5:$J$2000="Yes")*ISNUMBER(Assessment!$K$5:$K$2000)*Assessment!$G$5:$G$2000*Assessment!$K$5:$K$2000)/SUMPRODUCT((Assessment!$B$5:$B$2000=$B14)*(Assessment!$J$5:$J$2000="Yes")*ISNUMBER(Assessment!$K$5:$K$2000)*Assessment!$G$5:$G$2000)) -> - | G14: =IF(E14=0,"-",SUMPRODUCT((Assessment!$B$5:$B$2000=$B14)*(Assessment!$J$5:$J$2000="Yes")*ISNUMBER(Assessment!$K$5:$K$2000)*Assessment!$G$5:$G$2000*Assessment!$L$5:$L$2000)/SUMPRODUCT((Assessment!$B$5:$B$2000=$B14)*(Assessment!$J$5:$J$2000="Yes")*ISNUMBER(Assessment!$K$5:$K$2000)*Assessment!$G$5:$G$2000)) -> - | H14: =IF(E14=0,"-",MAX(0,G14-F14)) -> - | I14: =IF(E14=0,"Not assessed",IF(H14<=0,"On target",IF(H14<=1,"Minor gap","Significant gap"))) -> Not assessed
B15: Microsoft 365 | C15: =COUNTIF(Control_Library!$B$5:$B$3000,B15) -> 0 | D15: =COUNTIFS(Assessment!$B$5:$B$2000,B15,Assessment!$J$5:$J$2000,"Yes") -> 0 | E15: =COUNTIFS(Assessment!$B$5:$B$2000,$B15,Assessment!$J$5:$J$2000,"Yes",Assessment!$K$5:$K$2000,">=0") -> 0 | F15: =IF(E15=0,"-",SUMPRODUCT((Assessment!$B$5:$B$2000=$B15)*(Assessment!$J$5:$J$2000="Yes")*ISNUMBER(Assessment!$K$5:$K$2000)*Assessment!$G$5:$G$2000*Assessment!$K$5:$K$2000)/SUMPRODUCT((Assessment!$B$5:$B$2000=$B15)*(Assessment!$J$5:$J$2000="Yes")*ISNUMBER(Assessment!$K$5:$K$2000)*Assessment!$G$5:$G$2000)) -> - | G15: =IF(E15=0,"-",SUMPRODUCT((Assessment!$B$5:$B$2000=$B15)*(Assessment!$J$5:$J$2000="Yes")*ISNUMBER(Assessment!$K$5:$K$2000)*Assessment!$G$5:$G$2000*Assessment!$L$5:$L$2000)/SUMPRODUCT((Assessment!$B$5:$B$2000=$B15)*(Assessment!$J$5:$J$2000="Yes")*ISNUMBER(Assessment!$K$5:$K$2000)*Assessment!$G$5:$G$2000)) -> - | H15: =IF(E15=0,"-",MAX(0,G15-F15)) -> - | I15: =IF(E15=0,"Not assessed",IF(H15<=0,"On target",IF(H15<=1,"Minor gap","Significant gap"))) -> Not assessed
B16: Cloud Security | C16: =COUNTIF(Control_Library!$B$5:$B$3000,B16) -> 0 | D16: =COUNTIFS(Assessment!$B$5:$B$2000,B16,Assessment!$J$5:$J$2000,"Yes") -> 0 | E16: =COUNTIFS(Assessment!$B$5:$B$2000,$B16,Assessment!$J$5:$J$2000,"Yes",Assessment!$K$5:$K$2000,">=0") -> 0 | F16: =IF(E16=0,"-",SUMPRODUCT((Assessment!$B$5:$B$2000=$B16)*(Assessment!$J$5:$J$2000="Yes")*ISNUMBER(Assessment!$K$5:$K$2000)*Assessment!$G$5:$G$2000*Assessment!$K$5:$K$2000)/SUMPRODUCT((Assessment!$B$5:$B$2000=$B16)*(Assessment!$J$5:$J$2000="Yes")*ISNUMBER(Assessment!$K$5:$K$2000)*Assessment!$G$5:$G$2000)) -> - | G16: =IF(E16=0,"-",SUMPRODUCT((Assessment!$B$5:$B$2000=$B16)*(Assessment!$J$5:$J$2000="Yes")*ISNUMBER(Assessment!$K$5:$K$2000)*Assessment!$G$5:$G$2000*Assessment!$L$5:$L$2000)/SUMPRODUCT((Assessment!$B$5:$B$2000=$B16)*(Assessment!$J$5:$J$2000="Yes")*ISNUMBER(Assessment!$K$5:$K$2000)*Assessment!$G$5:$G$2000)) -> - | H16: =IF(E16=0,"-",MAX(0,G16-F16)) -> - | I16: =IF(E16=0,"Not assessed",IF(H16<=0,"On target",IF(H16<=1,"Minor gap","Significant gap"))) -> Not assessed
B17: Application Security | C17: =COUNTIF(Control_Library!$B$5:$B$3000,B17) -> 0 | D17: =COUNTIFS(Assessment!$B$5:$B$2000,B17,Assessment!$J$5:$J$2000,"Yes") -> 0 | E17: =COUNTIFS(Assessment!$B$5:$B$2000,$B17,Assessment!$J$5:$J$2000,"Yes",Assessment!$K$5:$K$2000,">=0") -> 0 | F17: =IF(E17=0,"-",SUMPRODUCT((Assessment!$B$5:$B$2000=$B17)*(Assessment!$J$5:$J$2000="Yes")*ISNUMBER(Assessment!$K$5:$K$2000)*Assessment!$G$5:$G$2000*Assessment!$K$5:$K$2000)/SUMPRODUCT((Assessment!$B$5:$B$2000=$B17)*(Assessment!$J$5:$J$2000="Yes")*ISNUMBER(Assessment!$K$5:$K$2000)*Assessment!$G$5:$G$2000)) -> - | G17: =IF(E17=0,"-",SUMPRODUCT((Assessment!$B$5:$B$2000=$B17)*(Assessment!$J$5:$J$2000="Yes")*ISNUMBER(Assessment!$K$5:$K$2000)*Assessment!$G$5:$G$2000*Assessment!$L$5:$L$2000)/SUMPRODUCT((Assessment!$B$5:$B$2000=$B17)*(Assessment!$J$5:$J$2000="Yes")*ISNUMBER(Assessment!$K$5:$K$2000)*Assessment!$G$5:$G$2000)) -> - | H17: =IF(E17=0,"-",MAX(0,G17-F17)) -> - | I17: =IF(E17=0,"Not assessed",IF(H17<=0,"On target",IF(H17<=1,"Minor gap","Significant gap"))) -> Not assessed
B18: API Security | C18: =COUNTIF(Control_Library!$B$5:$B$3000,B18) -> 0 | D18: =COUNTIFS(Assessment!$B$5:$B$2000,B18,Assessment!$J$5:$J$2000,"Yes") -> 0 | E18: =COUNTIFS(Assessment!$B$5:$B$2000,$B18,Assessment!$J$5:$J$2000,"Yes",Assessment!$K$5:$K$2000,">=0") -> 0 | F18: =IF(E18=0,"-",SUMPRODUCT((Assessment!$B$5:$B$2000=$B18)*(Assessment!$J$5:$J$2000="Yes")*ISNUMBER(Assessment!$K$5:$K$2000)*Assessment!$G$5:$G$2000*Assessment!$K$5:$K$2000)/SUMPRODUCT((Assessment!$B$5:$B$2000=$B18)*(Assessment!$J$5:$J$2000="Yes")*ISNUMBER(Assessment!$K$5:$K$2000)*Assessment!$G$5:$G$2000)) -> - | G18: =IF(E18=0,"-",SUMPRODUCT((Assessment!$B$5:$B$2000=$B18)*(Assessment!$J$5:$J$2000="Yes")*ISNUMBER(Assessment!$K$5:$K$2000)*Assessment!$G$5:$G$2000*Assessment!$L$5:$L$2000)/SUMPRODUCT((Assessment!$B$5:$B$2000=$B18)*(Assessment!$J$5:$J$2000="Yes")*ISNUMBER(Assessment!$K$5:$K$2000)*Assessment!$G$5:$G$2000)) -> - | H18: =IF(E18=0,"-",MAX(0,G18-F18)) -> - | I18: =IF(E18=0,"Not assessed",IF(H18<=0,"On target",IF(H18<=1,"Minor gap","Significant gap"))) -> Not assessed
B19: Security Operations | C19: =COUNTIF(Control_Library!$B$5:$B$3000,B19) -> 0 | D19: =COUNTIFS(Assessment!$B$5:$B$2000,B19,Assessment!$J$5:$J$2000,"Yes") -> 0 | E19: =COUNTIFS(Assessment!$B$5:$B$2000,$B19,Assessment!$J$5:$J$2000,"Yes",Assessment!$K$5:$K$2000,">=0") -> 0 | F19: =IF(E19=0,"-",SUMPRODUCT((Assessment!$B$5:$B$2000=$B19)*(Assessment!$J$5:$J$2000="Yes")*ISNUMBER(Assessment!$K$5:$K$2000)*Assessment!$G$5:$G$2000*Assessment!$K$5:$K$2000)/SUMPRODUCT((Assessment!$B$5:$B$2000=$B19)*(Assessment!$J$5:$J$2000="Yes")*ISNUMBER(Assessment!$K$5:$K$2000)*Assessment!$G$5:$G$2000)) -> - | G19: =IF(E19=0,"-",SUMPRODUCT((Assessment!$B$5:$B$2000=$B19)*(Assessment!$J$5:$J$2000="Yes")*ISNUMBER(Assessment!$K$5:$K$2000)*Assessment!$G$5:$G$2000*Assessment!$L$5:$L$2000)/SUMPRODUCT((Assessment!$B$5:$B$2000=$B19)*(Assessment!$J$5:$J$2000="Yes")*ISNUMBER(Assessment!$K$5:$K$2000)*Assessment!$G$5:$G$2000)) -> - | H19: =IF(E19=0,"-",MAX(0,G19-F19)) -> - | I19: =IF(E19=0,"Not assessed",IF(H19<=0,"On target",IF(H19<=1,"Minor gap","Significant gap"))) -> Not assessed
B20: Vulnerability Management | C20: =COUNTIF(Control_Library!$B$5:$B$3000,B20) -> 0 | D20: =COUNTIFS(Assessment!$B$5:$B$2000,B20,Assessment!$J$5:$J$2000,"Yes") -> 0 | E20: =COUNTIFS(Assessment!$B$5:$B$2000,$B20,Assessment!$J$5:$J$2000,"Yes",Assessment!$K$5:$K$2000,">=0") -> 0 | F20: =IF(E20=0,"-",SUMPRODUCT((Assessment!$B$5:$B$2000=$B20)*(Assessment!$J$5:$J$2000="Yes")*ISNUMBER(Assessment!$K$5:$K$2000)*Assessment!$G$5:$G$2000*Assessment!$K$5:$K$2000)/SUMPRODUCT((Assessment!$B$5:$B$2000=$B20)*(Assessment!$J$5:$J$2000="Yes")*ISNUMBER(Assessment!$K$5:$K$2000)*Assessment!$G$5:$G$2000)) -> - | G20: =IF(E20=0,"-",SUMPRODUCT((Assessment!$B$5:$B$2000=$B20)*(Assessment!$J$5:$J$2000="Yes")*ISNUMBER(Assessment!$K$5:$K$2000)*Assessment!$G$5:$G$2000*Assessment!$L$5:$L$2000)/SUMPRODUCT((Assessment!$B$5:$B$2000=$B20)*(Assessment!$J$5:$J$2000="Yes")*ISNUMBER(Assessment!$K$5:$K$2000)*Assessment!$G$5:$G$2000)) -> - | H20: =IF(E20=0,"-",MAX(0,G20-F20)) -> - | I20: =IF(E20=0,"Not assessed",IF(H20<=0,"On target",IF(H20<=1,"Minor gap","Significant gap"))) -> Not assessed
... B26: AI Systems (future) | C26: =COUNTIF(Control_Library!$B$5:$B$3000,B26) -> 0 | D26: =COUNTIFS(Assessment!$B$5:$B$2000,B26,Assessment!$J$5:$J$2000,"Yes") -> 0 | E26: =COUNTIFS(Assessment!$B$5:$B$2000,$B26,Assessment!$J$5:$J$2000,"Yes",Assessment!$K$5:$K$2000,">=0") -> 0 | F26: =IF(E26=0,"-",SUMPRODUCT((Assessment!$B$5:$B$2000=$B26)*(Assessment!$J$5:$J$2000="Yes")*ISNUMBER(Assessment!$K$5:$K$2000)*Assessment!$G$5:$G$2000*Assessment!$K$5:$K$2000)/SUMPRODUCT((Assessment!$B$5:$B$2000=$B26)*(Assessment!$J$5:$J$2000="Yes")*ISNUMBER(Assessment!$K$5:$K$2000)*Assessment!$G$5:$G$2000)) -> - | G26: =IF(E26=0,"-",SUMPRODUCT((Assessment!$B$5:$B$2000=$B26)*(Assessment!$J$5:$J$2000="Yes")*ISNUMBER(Assessment!$K$5:$K$2000)*Assessment!$G$5:$G$2000*Assessment!$L$5:$L$2000)/SUMPRODUCT((Assessment!$B$5:$B$2000=$B26)*(Assessment!$J$5:$J$2000="Yes")*ISNUMBER(Assessment!$K$5:$K$2000)*Assessment!$G$5:$G$2000)) -> - | H26: =IF(E26=0,"-",MAX(0,G26-F26)) -> - | I26: =IF(E26=0,"Not assessed",IF(H26<=0,"On target",IF(H26<=1,"Minor gap","Significant gap"))) -> Not assessed
B28: Control family scores (heat map)
B29: Family | C29: Domain | D29: In scope | E29: Assessed | F29: Avg maturity | G29: Avg target | H29: Gap | I29: Status
B30: Physical and Environmental Security | C30: Server Security | D30: =COUNTIFS(Assessment!$B$5:$B$2000,C30,Assessment!$C$5:$C$2000,B30,Assessment!$J$5:$J$2000,"Yes") -> 4 | E30: =COUNTIFS(Assessment!$B$5:$B$2000,$C30,Assessment!$C$5:$C$2000,$B30,Assessment!$J$5:$J$2000,"Yes",Assessment!$K$5:$K$2000,">=0") -> 0 | F30: =IF(E30=0,"-",SUMPRODUCT((Assessment!$B$5:$B$2000=$C30)*(Assessment!$C$5:$C$2000=$B30)*(Assessment!$J$5:$J$2000="Yes")*ISNUMBER(Assessment!$K$5:$K$2000)*Assessment!$G$5:$G$2000*Assessment!$K$5:$K$2000)/SUMPRODUCT((Assessment!$B$5:$B$2000=$C30)*(Assessment!$C$5:$C$2000=$B30)*(Assessment!$J$5:$J$2000="Yes")*ISNUMBER(Assessment!$K$5:$K$2000)*Assessment!$G$5:$G$2000)) -> - | G30: =IF(E30=0,"-",SUMPRODUCT((Assessment!$B$5:$B$2000=$C30)*(Assessment!$C$5:$C$2000=$B30)*(Assessment!$J$5:$J$2000="Yes")*ISNUMBER(Assessment!$K$5:$K$2000)*Assessment!$G$5:$G$2000*Assessment!$L$5:$L$2000)/SUMPRODUCT((Assessment!$B$5:$B$2000=$C30)*(Assessment!$C$5:$C$2000=$B30)*(Assessment!$J$5:$J$2000="Yes")*ISNUMBER(Assessment!$K$5:$K$2000)*Assessment!$G$5:$G$2000)) -> - | H30: =IF(E30=0,"-",MAX(0,G30-F30)) -> - | I30: =IF(E30=0,"Not assessed",IF(H30<=0,"On target",IF(H30<=1,"Minor gap","Significant gap"))) -> Not assessed
B31: Secure Configuration and Change | C31: Server Security | D31: =COUNTIFS(Assessment!$B$5:$B$2000,C31,Assessment!$C$5:$C$2000,B31,Assessment!$J$5:$J$2000,"Yes") -> 7 | E31: =COUNTIFS(Assessment!$B$5:$B$2000,$C31,Assessment!$C$5:$C$2000,$B31,Assessment!$J$5:$J$2000,"Yes",Assessment!$K$5:$K$2000,">=0") -> 0 | F31: =IF(E31=0,"-",SUMPRODUCT((Assessment!$B$5:$B$2000=$C31)*(Assessment!$C$5:$C$2000=$B31)*(Assessment!$J$5:$J$2000="Yes")*ISNUMBER(Assessment!$K$5:$K$2000)*Assessment!$G$5:$G$2000*Assessment!$K$5:$K$2000)/SUMPRODUCT((Assessment!$B$5:$B$2000=$C31)*(Assessment!$C$5:$C$2000=$B31)*(Assessment!$J$5:$J$2000="Yes")*ISNUMBER(Assessment!$K$5:$K$2000)*Assessment!$G$5:$G$2000)) -> - | G31: =IF(E31=0,"-",SUMPRODUCT((Assessment!$B$5:$B$2000=$C31)*(Assessment!$C$5:$C$2000=$B31)*(Assessment!$J$5:$J$2000="Yes")*ISNUMBER(Assessment!$K$5:$K$2000)*Assessment!$G$5:$G$2000*Assessment!$L$5:$L$2000)/SUMPRODUCT((Assessment!$B$5:$B$2000=$C31)*(Assessment!$C$5:$C$2000=$B31)*(Assessment!$J$5:$J$2000="Yes")*ISNUMBER(Assessment!$K$5:$K$2000)*Assessment!$G$5:$G$2000)) -> - | H31: =IF(E31=0,"-",MAX(0,G31-F31)) -> - | I31: =IF(E31=0,"Not assessed",IF(H31<=0,"On target",IF(H31<=1,"Minor gap","Significant gap"))) -> Not assessed
B32: Patch and Lifecycle Management | C32: Server Security | D32: =COUNTIFS(Assessment!$B$5:$B$2000,C32,Assessment!$C$5:$C$2000,B32,Assessment!$J$5:$J$2000,"Yes") -> 5 | E32: =COUNTIFS(Assessment!$B$5:$B$2000,$C32,Assessment!$C$5:$C$2000,$B32,Assessment!$J$5:$J$2000,"Yes",Assessment!$K$5:$K$2000,">=0") -> 0 | F32: =IF(E32=0,"-",SUMPRODUCT((Assessment!$B$5:$B$2000=$C32)*(Assessment!$C$5:$C$2000=$B32)*(Assessment!$J$5:$J$2000="Yes")*ISNUMBER(Assessment!$K$5:$K$2000)*Assessment!$G$5:$G$2000*Assessment!$K$5:$K$2000)/SUMPRODUCT((Assessment!$B$5:$B$2000=$C32)*(Assessment!$C$5:$C$2000=$B32)*(Assessment!$J$5:$J$2000="Yes")*ISNUMBER(Assessment!$K$5:$K$2000)*Assessment!$G$5:$G$2000)) -> - | G32: =IF(E32=0,"-",SUMPRODUCT((Assessment!$B$5:$B$2000=$C32)*(Assessment!$C$5:$C$2000=$B32)*(Assessment!$J$5:$J$2000="Yes")*ISNUMBER(Assessment!$K$5:$K$2000)*Assessment!$G$5:$G$2000*Assessment!$L$5:$L$2000)/SUMPRODUCT((Assessment!$B$5:$B$2000=$C32)*(Assessment!$C$5:$C$2000=$B32)*(Assessment!$J$5:$J$2000="Yes")*ISNUMBER(Assessment!$K$5:$K$2000)*Assessment!$G$5:$G$2000)) -> - | H32: =IF(E32=0,"-",MAX(0,G32-F32)) -> - | I32: =IF(E32=0,"Not assessed",IF(H32<=0,"On target",IF(H32<=1,"Minor gap","Significant gap"))) -> Not assessed
B33: Logging and Time Synchronization | C33: Server Security | D33: =COUNTIFS(Assessment!$B$5:$B$2000,C33,Assessment!$C$5:$C$2000,B33,Assessment!$J$5:$J$2000,"Yes") -> 6 | E33: =COUNTIFS(Assessment!$B$5:$B$2000,$C33,Assessment!$C$5:$C$2000,$B33,Assessment!$J$5:$J$2000,"Yes",Assessment!$K$5:$K$2000,">=0") -> 0 | F33: =IF(E33=0,"-",SUMPRODUCT((Assessment!$B$5:$B$2000=$C33)*(Assessment!$C$5:$C$2000=$B33)*(Assessment!$J$5:$J$2000="Yes")*ISNUMBER(Assessment!$K$5:$K$2000)*Assessment!$G$5:$G$2000*Assessment!$K$5:$K$2000)/SUMPRODUCT((Assessment!$B$5:$B$2000=$C33)*(Assessment!$C$5:$C$2000=$B33)*(Assessment!$J$5:$J$2000="Yes")*ISNUMBER(Assessment!$K$5:$K$2000)*Assessment!$G$5:$G$2000)) -> - | G33: =IF(E33=0,"-",SUMPRODUCT((Assessment!$B$5:$B$2000=$C33)*(Assessment!$C$5:$C$2000=$B33)*(Assessment!$J$5:$J$2000="Yes")*ISNUMBER(Assessment!$K$5:$K$2000)*Assessment!$G$5:$G$2000*Assessment!$L$5:$L$2000)/SUMPRODUCT((Assessment!$B$5:$B$2000=$C33)*(Assessment!$C$5:$C$2000=$B33)*(Assessment!$J$5:$J$2000="Yes")*ISNUMBER(Assessment!$K$5:$K$2000)*Assessment!$G$5:$G$2000)) -> - | H33: =IF(E33=0,"-",MAX(0,G33-F33)) -> - | I33: =IF(E33=0,"Not assessed",IF(H33<=0,"On target",IF(H33<=1,"Minor gap","Significant gap"))) -> Not assessed
B34: Host Protection | C34: Server Security | D34: =COUNTIFS(Assessment!$B$5:$B$2000,C34,Assessment!$C$5:$C$2000,B34,Assessment!$J$5:$J$2000,"Yes") -> 4 | E34: =COUNTIFS(Assessment!$B$5:$B$2000,$C34,Assessment!$C$5:$C$2000,$B34,Assessment!$J$5:$J$2000,"Yes",Assessment!$K$5:$K$2000,">=0") -> 0 | F34: =IF(E34=0,"-",SUMPRODUCT((Assessment!$B$5:$B$2000=$C34)*(Assessment!$C$5:$C$2000=$B34)*(Assessment!$J$5:$J$2000="Yes")*ISNUMBER(Assessment!$K$5:$K$2000)*Assessment!$G$5:$G$2000*Assessment!$K$5:$K$2000)/SUMPRODUCT((Assessment!$B$5:$B$2000=$C34)*(Assessment!$C$5:$C$2000=$B34)*(Assessment!$J$5:$J$2000="Yes")*ISNUMBER(Assessment!$K$5:$K$2000)*Assessment!$G$5:$G$2000)) -> - | G34: =IF(E34=0,"-",SUMPRODUCT((Assessment!$B$5:$B$2000=$C34)*(Assessment!$C$5:$C$2000=$B34)*(Assessment!$J$5:$J$2000="Yes")*ISNUMBER(Assessment!$K$5:$K$2000)*Assessment!$G$5:$G$2000*Assessment!$L$5:$L$2000)/SUMPRODUCT((Assessment!$B$5:$B$2000=$C34)*(Assessment!$C$5:$C$2000=$B34)*(Assessment!$J$5:$J$2000="Yes")*ISNUMBER(Assessment!$K$5:$K$2000)*Assessment!$G$5:$G$2000)) -> - | H34: =IF(E34=0,"-",MAX(0,G34-F34)) -> - | I34: =IF(E34=0,"Not assessed",IF(H34<=0,"On target",IF(H34<=1,"Minor gap","Significant gap"))) -> Not assessed
B35: Vulnerability Assessment | C35: Server Security | D35: =COUNTIFS(Assessment!$B$5:$B$2000,C35,Assessment!$C$5:$C$2000,B35,Assessment!$J$5:$J$2000,"Yes") -> 4 | E35: =COUNTIFS(Assessment!$B$5:$B$2000,$C35,Assessment!$C$5:$C$2000,$B35,Assessment!$J$5:$J$2000,"Yes",Assessment!$K$5:$K$2000,">=0") -> 0 | F35: =IF(E35=0,"-",SUMPRODUCT((Assessment!$B$5:$B$2000=$C35)*(Assessment!$C$5:$C$2000=$B35)*(Assessment!$J$5:$J$2000="Yes")*ISNUMBER(Assessment!$K$5:$K$2000)*Assessment!$G$5:$G$2000*Assessment!$K$5:$K$2000)/SUMPRODUCT((Assessment!$B$5:$B$2000=$C35)*(Assessment!$C$5:$C$2000=$B35)*(Assessment!$J$5:$J$2000="Yes")*ISNUMBER(Assessment!$K$5:$K$2000)*Assessment!$G$5:$G$2000)) -> - | G35: =IF(E35=0,"-",SUMPRODUCT((Assessment!$B$5:$B$2000=$C35)*(Assessment!$C$5:$C$2000=$B35)*(Assessment!$J$5:$J$2000="Yes")*ISNUMBER(Assessment!$K$5:$K$2000)*Assessment!$G$5:$G$2000*Assessment!$L$5:$L$2000)/SUMPRODUCT((Assessment!$B$5:$B$2000=$C35)*(Assessment!$C$5:$C$2000=$B35)*(Assessment!$J$5:$J$2000="Yes")*ISNUMBER(Assessment!$K$5:$K$2000)*Assessment!$G$5:$G$2000)) -> - | H35: =IF(E35=0,"-",MAX(0,G35-F35)) -> - | I35: =IF(E35=0,"Not assessed",IF(H35<=0,"On target",IF(H35<=1,"Minor gap","Significant gap"))) -> Not assessed
B36: Network Placement and Exposure | C36: Server Security | D36: =COUNTIFS(Assessment!$B$5:$B$2000,C36,Assessment!$C$5:$C$2000,B36,Assessment!$J$5:$J$2000,"Yes") -> 1 | E36: =COUNTIFS(Assessment!$B$5:$B$2000,$C36,Assessment!$C$5:$C$2000,$B36,Assessment!$J$5:$J$2000,"Yes",Assessment!$K$5:$K$2000,">=0") -> 0 | F36: =IF(E36=0,"-",SUMPRODUCT((Assessment!$B$5:$B$2000=$C36)*(Assessment!$C$5:$C$2000=$B36)*(Assessment!$J$5:$J$2000="Yes")*ISNUMBER(Assessment!$K$5:$K$2000)*Assessment!$G$5:$G$2000*Assessment!$K$5:$K$2000)/SUMPRODUCT((Assessment!$B$5:$B$2000=$C36)*(Assessment!$C$5:$C$2000=$B36)*(Assessment!$J$5:$J$2000="Yes")*ISNUMBER(Assessment!$K$5:$K$2000)*Assessment!$G$5:$G$2000)) -> - | G36: =IF(E36=0,"-",SUMPRODUCT((Assessment!$B$5:$B$2000=$C36)*(Assessment!$C$5:$C$2000=$B36)*(Assessment!$J$5:$J$2000="Yes")*ISNUMBER(Assessment!$K$5:$K$2000)*Assessment!$G$5:$G$2000*Assessment!$L$5:$L$2000)/SUMPRODUCT((Assessment!$B$5:$B$2000=$C36)*(Assessment!$C$5:$C$2000=$B36)*(Assessment!$J$5:$J$2000="Yes")*ISNUMBER(Assessment!$K$5:$K$2000)*Assessment!$G$5:$G$2000)) -> - | H36: =IF(E36=0,"-",MAX(0,G36-F36)) -> - | I36: =IF(E36=0,"Not assessed",IF(H36<=0,"On target",IF(H36<=1,"Minor gap","Significant gap"))) -> Not assessed
B37: Authentication and Access Control | C37: Server Security | D37: =COUNTIFS(Assessment!$B$5:$B$2000,C37,Assessment!$C$5:$C$2000,B37,Assessment!$J$5:$J$2000,"Yes") -> 9 | E37: =COUNTIFS(Assessment!$B$5:$B$2000,$C37,Assessment!$C$5:$C$2000,$B37,Assessment!$J$5:$J$2000,"Yes",Assessment!$K$5:$K$2000,">=0") -> 0 | F37: =IF(E37=0,"-",SUMPRODUCT((Assessment!$B$5:$B$2000=$C37)*(Assessment!$C$5:$C$2000=$B37)*(Assessment!$J$5:$J$2000="Yes")*ISNUMBER(Assessment!$K$5:$K$2000)*Assessment!$G$5:$G$2000*Assessment!$K$5:$K$2000)/SUMPRODUCT((Assessment!$B$5:$B$2000=$C37)*(Assessment!$C$5:$C$2000=$B37)*(Assessment!$J$5:$J$2000="Yes")*ISNUMBER(Assessment!$K$5:$K$2000)*Assessment!$G$5:$G$2000)) -> - | G37: =IF(E37=0,"-",SUMPRODUCT((Assessment!$B$5:$B$2000=$C37)*(Assessment!$C$5:$C$2000=$B37)*(Assessment!$J$5:$J$2000="Yes")*ISNUMBER(Assessment!$K$5:$K$2000)*Assessment!$G$5:$G$2000*Assessment!$L$5:$L$2000)/SUMPRODUCT((Assessment!$B$5:$B$2000=$C37)*(Assessment!$C$5:$C$2000=$B37)*(Assessment!$J$5:$J$2000="Yes")*ISNUMBER(Assessment!$K$5:$K$2000)*Assessment!$G$5:$G$2000)) -> - | H37: =IF(E37=0,"-",MAX(0,G37-F37)) -> - | I37: =IF(E37=0,"Not assessed",IF(H37<=0,"On target",IF(H37<=1,"Minor gap","Significant gap"))) -> Not assessed
B38: Secure Administration | C38: Server Security | D38: =COUNTIFS(Assessment!$B$5:$B$2000,C38,Assessment!$C$5:$C$2000,B38,Assessment!$J$5:$J$2000,"Yes") -> 2 | E38: =COUNTIFS(Assessment!$B$5:$B$2000,$C38,Assessment!$C$5:$C$2000,$B38,Assessment!$J$5:$J$2000,"Yes",Assessment!$K$5:$K$2000,">=0") -> 0 | F38: =IF(E38=0,"-",SUMPRODUCT((Assessment!$B$5:$B$2000=$C38)*(Assessment!$C$5:$C$2000=$B38)*(Assessment!$J$5:$J$2000="Yes")*ISNUMBER(Assessment!$K$5:$K$2000)*Assessment!$G$5:$G$2000*Assessment!$K$5:$K$2000)/SUMPRODUCT((Assessment!$B$5:$B$2000=$C38)*(Assessment!$C$5:$C$2000=$B38)*(Assessment!$J$5:$J$2000="Yes")*ISNUMBER(Assessment!$K$5:$K$2000)*Assessment!$G$5:$G$2000)) -> - | G38: =IF(E38=0,"-",SUMPRODUCT((Assessment!$B$5:$B$2000=$C38)*(Assessment!$C$5:$C$2000=$B38)*(Assessment!$J$5:$J$2000="Yes")*ISNUMBER(Assessment!$K$5:$K$2000)*Assessment!$G$5:$G$2000*Assessment!$L$5:$L$2000)/SUMPRODUCT((Assessment!$B$5:$B$2000=$C38)*(Assessment!$C$5:$C$2000=$B38)*(Assessment!$J$5:$J$2000="Yes")*ISNUMBER(Assessment!$K$5:$K$2000)*Assessment!$G$5:$G$2000)) -> - | H38: =IF(E38=0,"-",MAX(0,G38-F38)) -> - | I38: =IF(E38=0,"Not assessed",IF(H38<=0,"On target",IF(H38<=1,"Minor gap","Significant gap"))) -> Not assessed
B39: Backup, Restore and Recovery | C39: Server Security | D39: =COUNTIFS(Assessment!$B$5:$B$2000,C39,Assessment!$C$5:$C$2000,B39,Assessment!$J$5:$J$2000,"Yes") -> 6 | E39: =COUNTIFS(Assessment!$B$5:$B$2000,$C39,Assessment!$C$5:$C$2000,$B39,Assessment!$J$5:$J$2000,"Yes",Assessment!$K$5:$K$2000,">=0") -> 0 | F39: =IF(E39=0,"-",SUMPRODUCT((Assessment!$B$5:$B$2000=$C39)*(Assessment!$C$5:$C$2000=$B39)*(Assessment!$J$5:$J$2000="Yes")*ISNUMBER(Assessment!$K$5:$K$2000)*Assessment!$G$5:$G$2000*Assessment!$K$5:$K$2000)/SUMPRODUCT((Assessment!$B$5:$B$2000=$C39)*(Assessment!$C$5:$C$2000=$B39)*(Assessment!$J$5:$J$2000="Yes")*ISNUMBER(Assessment!$K$5:$K$2000)*Assessment!$G$5:$G$2000)) -> - | G39: =IF(E39=0,"-",SUMPRODUCT((Assessment!$B$5:$B$2000=$C39)*(Assessment!$C$5:$C$2000=$B39)*(Assessment!$J$5:$J$2000="Yes")*ISNUMBER(Assessment!$K$5:$K$2000)*Assessment!$G$5:$G$2000*Assessment!$L$5:$L$2000)/SUMPRODUCT((Assessment!$B$5:$B$2000=$C39)*(Assessment!$C$5:$C$2000=$B39)*(Assessment!$J$5:$J$2000="Yes")*ISNUMBER(Assessment!$K$5:$K$2000)*Assessment!$G$5:$G$2000)) -> - | H39: =IF(E39=0,"-",MAX(0,G39-F39)) -> - | I39: =IF(E39=0,"Not assessed",IF(H39<=0,"On target",IF(H39<=1,"Minor gap","Significant gap"))) -> Not assessed
B40: Data Protection | C40: Server Security | D40: =COUNTIFS(Assessment!$B$5:$B$2000,C40,Assessment!$C$5:$C$2000,B40,Assessment!$J$5:$J$2000,"Yes") -> 3 | E40: =COUNTIFS(Assessment!$B$5:$B$2000,$C40,Assessment!$C$5:$C$2000,$B40,Assessment!$J$5:$J$2000,"Yes",Assessment!$K$5:$K$2000,">=0") -> 0 | F40: =IF(E40=0,"-",SUMPRODUCT((Assessment!$B$5:$B$2000=$C40)*(Assessment!$C$5:$C$2000=$B40)*(Assessment!$J$5:$J$2000="Yes")*ISNUMBER(Assessment!$K$5:$K$2000)*Assessment!$G$5:$G$2000*Assessment!$K$5:$K$2000)/SUMPRODUCT((Assessment!$B$5:$B$2000=$C40)*(Assessment!$C$5:$C$2000=$B40)*(Assessment!$J$5:$J$2000="Yes")*ISNUMBER(Assessment!$K$5:$K$2000)*Assessment!$G$5:$G$2000)) -> - | G40: =IF(E40=0,"-",SUMPRODUCT((Assessment!$B$5:$B$2000=$C40)*(Assessment!$C$5:$C$2000=$B40)*(Assessment!$J$5:$J$2000="Yes")*ISNUMBER(Assessment!$K$5:$K$2000)*Assessment!$G$5:$G$2000*Assessment!$L$5:$L$2000)/SUMPRODUCT((Assessment!$B$5:$B$2000=$C40)*(Assessment!$C$5:$C$2000=$B40)*(Assessment!$J$5:$J$2000="Yes")*ISNUMBER(Assessment!$K$5:$K$2000)*Assessment!$G$5:$G$2000)) -> - | H40: =IF(E40=0,"-",MAX(0,G40-F40)) -> - | I40: =IF(E40=0,"Not assessed",IF(H40<=0,"On target",IF(H40<=1,"Minor gap","Significant gap"))) -> Not assessed
B41: Governance, Ownership and Risk | C41: Server Security | D41: =COUNTIFS(Assessment!$B$5:$B$2000,C41,Assessment!$C$5:$C$2000,B41,Assessment!$J$5:$J$2000,"Yes") -> 4 | E41: =COUNTIFS(Assessment!$B$5:$B$2000,$C41,Assessment!$C$5:$C$2000,$B41,Assessment!$J$5:$J$2000,"Yes",Assessment!$K$5:$K$2000,">=0") -> 0 | F41: =IF(E41=0,"-",SUMPRODUCT((Assessment!$B$5:$B$2000=$C41)*(Assessment!$C$5:$C$2000=$B41)*(Assessment!$J$5:$J$2000="Yes")*ISNUMBER(Assessment!$K$5:$K$2000)*Assessment!$G$5:$G$2000*Assessment!$K$5:$K$2000)/SUMPRODUCT((Assessment!$B$5:$B$2000=$C41)*(Assessment!$C$5:$C$2000=$B41)*(Assessment!$J$5:$J$2000="Yes")*ISNUMBER(Assessment!$K$5:$K$2000)*Assessment!$G$5:$G$2000)) -> - | G41: =IF(E41=0,"-",SUMPRODUCT((Assessment!$B$5:$B$2000=$C41)*(Assessment!$C$5:$C$2000=$B41)*(Assessment!$J$5:$J$2000="Yes")*ISNUMBER(Assessment!$K$5:$K$2000)*Assessment!$G$5:$G$2000*Assessment!$L$5:$L$2000)/SUMPRODUCT((Assessment!$B$5:$B$2000=$C41)*(Assessment!$C$5:$C$2000=$B41)*(Assessment!$J$5:$J$2000="Yes")*ISNUMBER(Assessment!$K$5:$K$2000)*Assessment!$G$5:$G$2000)) -> - | H41: =IF(E41=0,"-",MAX(0,G41-F41)) -> - | I41: =IF(E41=0,"Not assessed",IF(H41<=0,"On target",IF(H41<=1,"Minor gap","Significant gap"))) -> Not assessed
B42: Virtualization Platforms | C42: Server Security | D42: =COUNTIFS(Assessment!$B$5:$B$2000,C42,Assessment!$C$5:$C$2000,B42,Assessment!$J$5:$J$2000,"Yes") -> 5 | E42: =COUNTIFS(Assessment!$B$5:$B$2000,$C42,Assessment!$C$5:$C$2000,$B42,Assessment!$J$5:$J$2000,"Yes",Assessment!$K$5:$K$2000,">=0") -> 0 | F42: =IF(E42=0,"-",SUMPRODUCT((Assessment!$B$5:$B$2000=$C42)*(Assessment!$C$5:$C$2000=$B42)*(Assessment!$J$5:$J$2000="Yes")*ISNUMBER(Assessment!$K$5:$K$2000)*Assessment!$G$5:$G$2000*Assessment!$K$5:$K$2000)/SUMPRODUCT((Assessment!$B$5:$B$2000=$C42)*(Assessment!$C$5:$C$2000=$B42)*(Assessment!$J$5:$J$2000="Yes")*ISNUMBER(Assessment!$K$5:$K$2000)*Assessment!$G$5:$G$2000)) -> - | G42: =IF(E42=0,"-",SUMPRODUCT((Assessment!$B$5:$B$2000=$C42)*(Assessment!$C$5:$C$2000=$B42)*(Assessment!$J$5:$J$2000="Yes")*ISNUMBER(Assessment!$K$5:$K$2000)*Assessment!$G$5:$G$2000*Assessment!$L$5:$L$2000)/SUMPRODUCT((Assessment!$B$5:$B$2000=$C42)*(Assessment!$C$5:$C$2000=$B42)*(Assessment!$J$5:$J$2000="Yes")*ISNUMBER(Assessment!$K$5:$K$2000)*Assessment!$G$5:$G$2000)) -> - | H42: =IF(E42=0,"-",MAX(0,G42-F42)) -> - | I42: =IF(E42=0,"Not assessed",IF(H42<=0,"On target",IF(H42<=1,"Minor gap","Significant gap"))) -> Not assessed
B44: Maturity distribution (in-scope controls)
B45: Maturity level | C45: Controls
B46: 0 - Non-Existent | C46: =COUNTIFS(Assessment!$J$5:$J$2000,"Yes",Assessment!$K$5:$K$2000,0) -> 0
B47: 1 - Initial | C47: =COUNTIFS(Assessment!$J$5:$J$2000,"Yes",Assessment!$K$5:$K$2000,1) -> 0
B48: 2 - Repeatable | C48: =COUNTIFS(Assessment!$J$5:$J$2000,"Yes",Assessment!$K$5:$K$2000,2) -> 0
B49: 3 - Defined | C49: =COUNTIFS(Assessment!$J$5:$J$2000,"Yes",Assessment!$K$5:$K$2000,3) -> 0
B50: 4 - Managed | C50: =COUNTIFS(Assessment!$J$5:$J$2000,"Yes",Assessment!$K$5:$K$2000,4) -> 0
B51: 5 - Optimized | C51: =COUNTIFS(Assessment!$J$5:$J$2000,"Yes",Assessment!$K$5:$K$2000,5) -> 0
B52: Not yet assessed | C52: =COUNTIF(Assessment!$J$5:$J$2000,"Yes")-SUM(C46:C51) -> 60
B54: Inherent risk heat map (in-scope controls: count by Likelihood x Impact)
B55: Likelihood \ Impact | C55: 1 | D55: 2 | E55: 3 | F55: 4 | G55: 5
B56: 5 - Almost certain | C56: =COUNTIFS(Assessment!$T$5:$T$2000,5,Assessment!$U$5:$U$2000,1,Assessment!$J$5:$J$2000,"Yes") -> 0 | D56: =COUNTIFS(Assessment!$T$5:$T$2000,5,Assessment!$U$5:$U$2000,2,Assessment!$J$5:$J$2000,"Yes") -> 0 | E56: =COUNTIFS(Assessment!$T$5:$T$2000,5,Assessment!$U$5:$U$2000,3,Assessment!$J$5:$J$2000,"Yes") -> 0 | F56: =COUNTIFS(Assessment!$T$5:$T$2000,5,Assessment!$U$5:$U$2000,4,Assessment!$J$5:$J$2000,"Yes") -> 0 | G56: =COUNTIFS(Assessment!$T$5:$T$2000,5,Assessment!$U$5:$U$2000,5,Assessment!$J$5:$J$2000,"Yes") -> 0
B57: 4 - Likely | C57: =COUNTIFS(Assessment!$T$5:$T$2000,4,Assessment!$U$5:$U$2000,1,Assessment!$J$5:$J$2000,"Yes") -> 0 | D57: =COUNTIFS(Assessment!$T$5:$T$2000,4,Assessment!$U$5:$U$2000,2,Assessment!$J$5:$J$2000,"Yes") -> 0 | E57: =COUNTIFS(Assessment!$T$5:$T$2000,4,Assessment!$U$5:$U$2000,3,Assessment!$J$5:$J$2000,"Yes") -> 0 | F57: =COUNTIFS(Assessment!$T$5:$T$2000,4,Assessment!$U$5:$U$2000,4,Assessment!$J$5:$J$2000,"Yes") -> 7 | G57: =COUNTIFS(Assessment!$T$5:$T$2000,4,Assessment!$U$5:$U$2000,5,Assessment!$J$5:$J$2000,"Yes") -> 9
B58: 3 - Possible | C58: =COUNTIFS(Assessment!$T$5:$T$2000,3,Assessment!$U$5:$U$2000,1,Assessment!$J$5:$J$2000,"Yes") -> 0 | D58: =COUNTIFS(Assessment!$T$5:$T$2000,3,Assessment!$U$5:$U$2000,2,Assessment!$J$5:$J$2000,"Yes") -> 0 | E58: =COUNTIFS(Assessment!$T$5:$T$2000,3,Assessment!$U$5:$U$2000,3,Assessment!$J$5:$J$2000,"Yes") -> 4 | F58: =COUNTIFS(Assessment!$T$5:$T$2000,3,Assessment!$U$5:$U$2000,4,Assessment!$J$5:$J$2000,"Yes") -> 20 | G58: =COUNTIFS(Assessment!$T$5:$T$2000,3,Assessment!$U$5:$U$2000,5,Assessment!$J$5:$J$2000,"Yes") -> 11
B59: 2 - Unlikely | C59: =COUNTIFS(Assessment!$T$5:$T$2000,2,Assessment!$U$5:$U$2000,1,Assessment!$J$5:$J$2000,"Yes") -> 0 | D59: =COUNTIFS(Assessment!$T$5:$T$2000,2,Assessment!$U$5:$U$2000,2,Assessment!$J$5:$J$2000,"Yes") -> 0 | E59: =COUNTIFS(Assessment!$T$5:$T$2000,2,Assessment!$U$5:$U$2000,3,Assessment!$J$5:$J$2000,"Yes") -> 2 | F59: =COUNTIFS(Assessment!$T$5:$T$2000,2,Assessment!$U$5:$U$2000,4,Assessment!$J$5:$J$2000,"Yes") -> 5 | G59: =COUNTIFS(Assessment!$T$5:$T$2000,2,Assessment!$U$5:$U$2000,5,Assessment!$J$5:$J$2000,"Yes") -> 1
B60: 1 - Rare | C60: =COUNTIFS(Assessment!$T$5:$T$2000,1,Assessment!$U$5:$U$2000,1,Assessment!$J$5:$J$2000,"Yes") -> 0 | D60: =COUNTIFS(Assessment!$T$5:$T$2000,1,Assessment!$U$5:$U$2000,2,Assessment!$J$5:$J$2000,"Yes") -> 1 | E60: =COUNTIFS(Assessment!$T$5:$T$2000,1,Assessment!$U$5:$U$2000,3,Assessment!$J$5:$J$2000,"Yes") -> 0 | F60: =COUNTIFS(Assessment!$T$5:$T$2000,1,Assessment!$U$5:$U$2000,4,Assessment!$J$5:$J$2000,"Yes") -> 0 | G60: =COUNTIFS(Assessment!$T$5:$T$2000,1,Assessment!$U$5:$U$2000,5,Assessment!$J$5:$J$2000,"Yes") -> 0
B62: Residual risk distribution (assessed controls)
B63: Residual rating | C63: Controls
B64: Critical | C64: =COUNTIF(Assessment!$Z$5:$Z$2000,"Critical") -> 0
B65: High | C65: =COUNTIF(Assessment!$Z$5:$Z$2000,"High") -> 0
B66: Medium | C66: =COUNTIF(Assessment!$Z$5:$Z$2000,"Medium") -> 0
B67: Low | C67: =COUNTIF(Assessment!$Z$5:$Z$2000,"Low") -> 0
B69: Top 10 residual risks
B70: Control | C70: Control ID | D70: Current | E70: Target | F70: Residual score | G70: Residual rating
B71: =IFERROR(INDEX(Assessment!$E$5:$E$2000,MATCH(LARGE(Assessment!$AA$5:$AA$2000,1),Assessment!$AA$5:$AA$2000,0)),"") | C71: =IFERROR(INDEX(Assessment!$A$5:$A$2000,MATCH(LARGE(Assessment!$AA$5:$AA$2000,1),Assessment!$AA$5:$AA$2000,0)),"") | D71: =IFERROR(INDEX(Assessment!$K$5:$K$2000,MATCH(LARGE(Assessment!$AA$5:$AA$2000,1),Assessment!$AA$5:$AA$2000,0)),"") | E71: =IFERROR(INDEX(Assessment!$L$5:$L$2000,MATCH(LARGE(Assessment!$AA$5:$AA$2000,1),Assessment!$AA$5:$AA$2000,0)),"") | F71: =IFERROR(INDEX(Assessment!$Y$5:$Y$2000,MATCH(LARGE(Assessment!$AA$5:$AA$2000,1),Assessment!$AA$5:$AA$2000,0)),"") | G71: =IFERROR(INDEX(Assessment!$Z$5:$Z$2000,MATCH(LARGE(Assessment!$AA$5:$AA$2000,1),Assessment!$AA$5:$AA$2000,0)),"")
B72: =IFERROR(INDEX(Assessment!$E$5:$E$2000,MATCH(LARGE(Assessment!$AA$5:$AA$2000,2),Assessment!$AA$5:$AA$2000,0)),"") | C72: =IFERROR(INDEX(Assessment!$A$5:$A$2000,MATCH(LARGE(Assessment!$AA$5:$AA$2000,2),Assessment!$AA$5:$AA$2000,0)),"") | D72: =IFERROR(INDEX(Assessment!$K$5:$K$2000,MATCH(LARGE(Assessment!$AA$5:$AA$2000,2),Assessment!$AA$5:$AA$2000,0)),"") | E72: =IFERROR(INDEX(Assessment!$L$5:$L$2000,MATCH(LARGE(Assessment!$AA$5:$AA$2000,2),Assessment!$AA$5:$AA$2000,0)),"") | F72: =IFERROR(INDEX(Assessment!$Y$5:$Y$2000,MATCH(LARGE(Assessment!$AA$5:$AA$2000,2),Assessment!$AA$5:$AA$2000,0)),"") | G72: =IFERROR(INDEX(Assessment!$Z$5:$Z$2000,MATCH(LARGE(Assessment!$AA$5:$AA$2000,2),Assessment!$AA$5:$AA$2000,0)),"")
B73: =IFERROR(INDEX(Assessment!$E$5:$E$2000,MATCH(LARGE(Assessment!$AA$5:$AA$2000,3),Assessment!$AA$5:$AA$2000,0)),"") | C73: =IFERROR(INDEX(Assessment!$A$5:$A$2000,MATCH(LARGE(Assessment!$AA$5:$AA$2000,3),Assessment!$AA$5:$AA$2000,0)),"") | D73: =IFERROR(INDEX(Assessment!$K$5:$K$2000,MATCH(LARGE(Assessment!$AA$5:$AA$2000,3),Assessment!$AA$5:$AA$2000,0)),"") | E73: =IFERROR(INDEX(Assessment!$L$5:$L$2000,MATCH(LARGE(Assessment!$AA$5:$AA$2000,3),Assessment!$AA$5:$AA$2000,0)),"") | F73: =IFERROR(INDEX(Assessment!$Y$5:$Y$2000,MATCH(LARGE(Assessment!$AA$5:$AA$2000,3),Assessment!$AA$5:$AA$2000,0)),"") | G73: =IFERROR(INDEX(Assessment!$Z$5:$Z$2000,MATCH(LARGE(Assessment!$AA$5:$AA$2000,3),Assessment!$AA$5:$AA$2000,0)),"")
B74: =IFERROR(INDEX(Assessment!$E$5:$E$2000,MATCH(LARGE(Assessment!$AA$5:$AA$2000,4),Assessment!$AA$5:$AA$2000,0)),"") | C74: =IFERROR(INDEX(Assessment!$A$5:$A$2000,MATCH(LARGE(Assessment!$AA$5:$AA$2000,4),Assessment!$AA$5:$AA$2000,0)),"") | D74: =IFERROR(INDEX(Assessment!$K$5:$K$2000,MATCH(LARGE(Assessment!$AA$5:$AA$2000,4),Assessment!$AA$5:$AA$2000,0)),"") | E74: =IFERROR(INDEX(Assessment!$L$5:$L$2000,MATCH(LARGE(Assessment!$AA$5:$AA$2000,4),Assessment!$AA$5:$AA$2000,0)),"") | F74: =IFERROR(INDEX(Assessment!$Y$5:$Y$2000,MATCH(LARGE(Assessment!$AA$5:$AA$2000,4),Assessment!$AA$5:$AA$2000,0)),"") | G74: =IFERROR(INDEX(Assessment!$Z$5:$Z$2000,MATCH(LARGE(Assessment!$AA$5:$AA$2000,4),Assessment!$AA$5:$AA$2000,0)),"")
B75: =IFERROR(INDEX(Assessment!$E$5:$E$2000,MATCH(LARGE(Assessment!$AA$5:$AA$2000,5),Assessment!$AA$5:$AA$2000,0)),"") | C75: =IFERROR(INDEX(Assessment!$A$5:$A$2000,MATCH(LARGE(Assessment!$AA$5:$AA$2000,5),Assessment!$AA$5:$AA$2000,0)),"") | D75: =IFERROR(INDEX(Assessment!$K$5:$K$2000,MATCH(LARGE(Assessment!$AA$5:$AA$2000,5),Assessment!$AA$5:$AA$2000,0)),"") | E75: =IFERROR(INDEX(Assessment!$L$5:$L$2000,MATCH(LARGE(Assessment!$AA$5:$AA$2000,5),Assessment!$AA$5:$AA$2000,0)),"") | F75: =IFERROR(INDEX(Assessment!$Y$5:$Y$2000,MATCH(LARGE(Assessment!$AA$5:$AA$2000,5),Assessment!$AA$5:$AA$2000,0)),"") | G75: =IFERROR(INDEX(Assessment!$Z$5:$Z$2000,MATCH(LARGE(Assessment!$AA$5:$AA$2000,5),Assessment!$AA$5:$AA$2000,0)),"")
B76: =IFERROR(INDEX(Assessment!$E$5:$E$2000,MATCH(LARGE(Assessment!$AA$5:$AA$2000,6),Assessment!$AA$5:$AA$2000,0)),"") | C76: =IFERROR(INDEX(Assessment!$A$5:$A$2000,MATCH(LARGE(Assessment!$AA$5:$AA$2000,6),Assessment!$AA$5:$AA$2000,0)),"") | D76: =IFERROR(INDEX(Assessment!$K$5:$K$2000,MATCH(LARGE(Assessment!$AA$5:$AA$2000,6),Assessment!$AA$5:$AA$2000,0)),"") | E76: =IFERROR(INDEX(Assessment!$L$5:$L$2000,MATCH(LARGE(Assessment!$AA$5:$AA$2000,6),Assessment!$AA$5:$AA$2000,0)),"") | F76: =IFERROR(INDEX(Assessment!$Y$5:$Y$2000,MATCH(LARGE(Assessment!$AA$5:$AA$2000,6),Assessment!$AA$5:$AA$2000,0)),"") | G76: =IFERROR(INDEX(Assessment!$Z$5:$Z$2000,MATCH(LARGE(Assessment!$AA$5:$AA$2000,6),Assessment!$AA$5:$AA$2000,0)),"")
B77: =IFERROR(INDEX(Assessment!$E$5:$E$2000,MATCH(LARGE(Assessment!$AA$5:$AA$2000,7),Assessment!$AA$5:$AA$2000,0)),"") | C77: =IFERROR(INDEX(Assessment!$A$5:$A$2000,MATCH(LARGE(Assessment!$AA$5:$AA$2000,7),Assessment!$AA$5:$AA$2000,0)),"") | D77: =IFERROR(INDEX(Assessment!$K$5:$K$2000,MATCH(LARGE(Assessment!$AA$5:$AA$2000,7),Assessment!$AA$5:$AA$2000,0)),"") | E77: =IFERROR(INDEX(Assessment!$L$5:$L$2000,MATCH(LARGE(Assessment!$AA$5:$AA$2000,7),Assessment!$AA$5:$AA$2000,0)),"") | F77: =IFERROR(INDEX(Assessment!$Y$5:$Y$2000,MATCH(LARGE(Assessment!$AA$5:$AA$2000,7),Assessment!$AA$5:$AA$2000,0)),"") | G77: =IFERROR(INDEX(Assessment!$Z$5:$Z$2000,MATCH(LARGE(Assessment!$AA$5:$AA$2000,7),Assessment!$AA$5:$AA$2000,0)),"")
B78: =IFERROR(INDEX(Assessment!$E$5:$E$2000,MATCH(LARGE(Assessment!$AA$5:$AA$2000,8),Assessment!$AA$5:$AA$2000,0)),"") | C78: =IFERROR(INDEX(Assessment!$A$5:$A$2000,MATCH(LARGE(Assessment!$AA$5:$AA$2000,8),Assessment!$AA$5:$AA$2000,0)),"") | D78: =IFERROR(INDEX(Assessment!$K$5:$K$2000,MATCH(LARGE(Assessment!$AA$5:$AA$2000,8),Assessment!$AA$5:$AA$2000,0)),"") | E78: =IFERROR(INDEX(Assessment!$L$5:$L$2000,MATCH(LARGE(Assessment!$AA$5:$AA$2000,8),Assessment!$AA$5:$AA$2000,0)),"") | F78: =IFERROR(INDEX(Assessment!$Y$5:$Y$2000,MATCH(LARGE(Assessment!$AA$5:$AA$2000,8),Assessment!$AA$5:$AA$2000,0)),"") | G78: =IFERROR(INDEX(Assessment!$Z$5:$Z$2000,MATCH(LARGE(Assessment!$AA$5:$AA$2000,8),Assessment!$AA$5:$AA$2000,0)),"")
B79: =IFERROR(INDEX(Assessment!$E$5:$E$2000,MATCH(LARGE(Assessment!$AA$5:$AA$2000,9),Assessment!$AA$5:$AA$2000,0)),"") | C79: =IFERROR(INDEX(Assessment!$A$5:$A$2000,MATCH(LARGE(Assessment!$AA$5:$AA$2000,9),Assessment!$AA$5:$AA$2000,0)),"") | D79: =IFERROR(INDEX(Assessment!$K$5:$K$2000,MATCH(LARGE(Assessment!$AA$5:$AA$2000,9),Assessment!$AA$5:$AA$2000,0)),"") | E79: =IFERROR(INDEX(Assessment!$L$5:$L$2000,MATCH(LARGE(Assessment!$AA$5:$AA$2000,9),Assessment!$AA$5:$AA$2000,0)),"") | F79: =IFERROR(INDEX(Assessment!$Y$5:$Y$2000,MATCH(LARGE(Assessment!$AA$5:$AA$2000,9),Assessment!$AA$5:$AA$2000,0)),"") | G79: =IFERROR(INDEX(Assessment!$Z$5:$Z$2000,MATCH(LARGE(Assessment!$AA$5:$AA$2000,9),Assessment!$AA$5:$AA$2000,0)),"")
B80: =IFERROR(INDEX(Assessment!$E$5:$E$2000,MATCH(LARGE(Assessment!$AA$5:$AA$2000,10),Assessment!$AA$5:$AA$2000,0)),"") | C80: =IFERROR(INDEX(Assessment!$A$5:$A$2000,MATCH(LARGE(Assessment!$AA$5:$AA$2000,10),Assessment!$AA$5:$AA$2000,0)),"") | D80: =IFERROR(INDEX(Assessment!$K$5:$K$2000,MATCH(LARGE(Assessment!$AA$5:$AA$2000,10),Assessment!$AA$5:$AA$2000,0)),"") | E80: =IFERROR(INDEX(Assessment!$L$5:$L$2000,MATCH(LARGE(Assessment!$AA$5:$AA$2000,10),Assessment!$AA$5:$AA$2000,0)),"") | F80: =IFERROR(INDEX(Assessment!$Y$5:$Y$2000,MATCH(LARGE(Assessment!$AA$5:$AA$2000,10),Assessment!$AA$5:$AA$2000,0)),"") | G80: =IFERROR(INDEX(Assessment!$Z$5:$Z$2000,MATCH(LARGE(Assessment!$AA$5:$AA$2000,10),Assessment!$AA$5:$AA$2000,0)),"")
B82: Findings overview
B83: Severity | C83: Total | D83: Open / In Progress | E83: Overdue
B84: Critical | C84: =COUNTIF(Findings_Register!$F$6:$F$205,B84) -> 0 | D84: =COUNTIFS(Findings_Register!$F$6:$F$205,B84,Findings_Register!$K$6:$K$205,"Open")+COUNTIFS(Findings_Register!$F$6:$F$205,B84,Findings_Register!$K$6:$K$205,"In Progress") -> 0 | E84: =COUNTIFS(Findings_Register!$F$6:$F$205,B84,Findings_Register!$N$6:$N$205,"Overdue") -> 0
B85: High | C85: =COUNTIF(Findings_Register!$F$6:$F$205,B85) -> 0 | D85: =COUNTIFS(Findings_Register!$F$6:$F$205,B85,Findings_Register!$K$6:$K$205,"Open")+COUNTIFS(Findings_Register!$F$6:$F$205,B85,Findings_Register!$K$6:$K$205,"In Progress") -> 0 | E85: =COUNTIFS(Findings_Register!$F$6:$F$205,B85,Findings_Register!$N$6:$N$205,"Overdue") -> 0
B86: Medium | C86: =COUNTIF(Findings_Register!$F$6:$F$205,B86) -> 0 | D86: =COUNTIFS(Findings_Register!$F$6:$F$205,B86,Findings_Register!$K$6:$K$205,"Open")+COUNTIFS(Findings_Register!$F$6:$F$205,B86,Findings_Register!$K$6:$K$205,"In Progress") -> 0 | E86: =COUNTIFS(Findings_Register!$F$6:$F$205,B86,Findings_Register!$N$6:$N$205,"Overdue") -> 0
B87: Low | C87: =COUNTIF(Findings_Register!$F$6:$F$205,B87) -> 0 | D87: =COUNTIFS(Findings_Register!$F$6:$F$205,B87,Findings_Register!$K$6:$K$205,"Open")+COUNTIFS(Findings_Register!$F$6:$F$205,B87,Findings_Register!$K$6:$K$205,"In Progress") -> 0 | E87: =COUNTIFS(Findings_Register!$F$6:$F$205,B87,Findings_Register!$N$6:$N$205,"Overdue") -> 0
B88: Informational | C88: =COUNTIF(Findings_Register!$F$6:$F$205,B88) -> 0 | D88: =COUNTIFS(Findings_Register!$F$6:$F$205,B88,Findings_Register!$K$6:$K$205,"Open")+COUNTIFS(Findings_Register!$F$6:$F$205,B88,Findings_Register!$K$6:$K$205,"In Progress") -> 0 | E88: =COUNTIFS(Findings_Register!$F$6:$F$205,B88,Findings_Register!$N$6:$N$205,"Overdue") -> 0
B90: Remediation and evidence overview
B91: Measure | C91: Value
B92: Actions: not started | C92: =COUNTIF(Remediation_Tracker!$J$6:$J$205,"Not Started") -> 0
B93: Actions: in progress | C93: =COUNTIF(Remediation_Tracker!$J$6:$J$205,"In Progress") -> 0
B94: Actions: blocked | C94: =COUNTIF(Remediation_Tracker!$J$6:$J$205,"Blocked") -> 0
B95: Actions: completed or verified | C95: =COUNTIF(Remediation_Tracker!$J$6:$J$205,"Completed")+COUNTIF(Remediation_Tracker!$J$6:$J$205,"Verified") -> 0
B96: Actions overdue | C96: =COUNTIF(Remediation_Tracker!$M$6:$M$205,"Overdue") -> 0
B97: Average % complete | C97: =IFERROR(AVERAGE(Remediation_Tracker!$K$6:$K$205),0) -> 0
B98: Evidence requests received | C98: =IFERROR(COUNTIF(Evidence_Requests!$F$5:$F$261,"Received")/COUNTA(Evidence_Requests!$A$5:$A$261),0) -> 0
B100: Trend analysis
B101: First row is live. At the end of each assessment cycle copy the live values into the next empty row (paste as values) to build the trend.
B102: Period | C102: Overall maturity | D102: Crit/High residual | E102: Open Crit/High findings
B103: Current (live) | C103: =B5 -> n/a | D103: =I5 -> 0 | E103: =K5 -> 0

Sheet Assessment
A1: Assessment Workbook
A2: Yellow cells with blue text are inputs. Applicable? is pre-filled from Scope (overtype to override). Score 0-5 using Maturity_Model and the anchors in Control_Library.
A4: Control ID | B4: Domain | C4: Control Family | D4: Platform | E4: Control Name | F4: Assessment Question | G4: Weight | H4: Default Likelihood | I4: Default Impact | J4: Applicable? | K4: Current Maturity (0-5) | L4: Target Maturity (0-5) | M4: Gap | N4: Status | O4: Tests Performed | P4: Evidence Ref(s) | Q4: Assessor Notes / Observations | R4: Likelihood Override | S4: Impact Override | T4: Likelihood Used | U4: Impact Used | V4: Inherent Score | W4: Inherent Rating | X4: Control Effectiveness | Y4: Residual Score | Z4: Residual Rating | AA4: Rank Key (helper)
A5: SRV-PHY-01 | B5: Server Security | C5: Physical and Environmental Security | D5: All | E5: Physical access to servers is restricted and logged | F5: Are servers housed in locked racks or access-controlled rooms, with access limited to authorised staff and logged? | G5: 2 | H5: 2 | I5: 5 | J5: =IF(IFERROR(INDEX(Scope!$C$24:$C$41,MATCH($B5,Scope!$B$24:$B$41,0)),"Yes")="No","No",IF($D5="All","Yes",IF(IFERROR(INDEX(Scope!$C$18:$C$20,MATCH($D5,Scope!$B$18:$B$20,0)),"Yes")="No","No","Yes"))) -> Yes | L5: =Scope!$C$13 -> 3 | M5: =IF(AND(J5="Yes",K5<>""),MAX(0,L5-K5),"") | N5: =IF(J5="No","N/A",IF(K5="","Not assessed",IF(K5>=L5,"Meets target","Gap"))) -> Not assessed | T5: =IF(R5<>"",R5,H5) -> 2 | U5: =IF(S5<>"",S5,I5) -> 5 | V5: =T5*U5 -> 10 | W5: =INDEX(Risk_Model!$B$30:$B$33,MATCH(V5,Risk_Model!$A$30:$A$33,1)) -> High | X5: =IF(OR(J5="No",K5=""),"",INDEX(Risk_Model!$C$38:$C$43,MATCH(K5,Risk_Model!$A$38:$A$43,0))) | Y5: =IF(X5="","",ROUND(V5*(1-X5),1)) | Z5: =IF(Y5="","",INDEX(Risk_Model!$B$30:$B$33,MATCH(Y5,Risk_Model!$A$30:$A$33,1))) | AA5: =IF(Y5="","",Y5+ROW()/1000000)
A6: SRV-PHY-02 | B6: Server Security | C6: Physical and Environmental Security | D6: All | E6: Out-of-band management interfaces are isolated and hardened | F6: Are out-of-band management interfaces on a dedicated management network, patched, with default credentials changed and strong authentication enforced? | G6: 3 | H6: 3 | I6: 5 | J6: =IF(IFERROR(INDEX(Scope!$C$24:$C$41,MATCH($B6,Scope!$B$24:$B$41,0)),"Yes")="No","No",IF($D6="All","Yes",IF(IFERROR(INDEX(Scope!$C$18:$C$20,MATCH($D6,Scope!$B$18:$B$20,0)),"Yes")="No","No","Yes"))) -> Yes | L6: =Scope!$C$13 -> 3 | M6: =IF(AND(J6="Yes",K6<>""),MAX(0,L6-K6),"") | N6: =IF(J6="No","N/A",IF(K6="","Not assessed",IF(K6>=L6,"Meets target","Gap"))) -> Not assessed | T6: =IF(R6<>"",R6,H6) -> 3 | U6: =IF(S6<>"",S6,I6) -> 5 | V6: =T6*U6 -> 15 | W6: =INDEX(Risk_Model!$B$30:$B$33,MATCH(V6,Risk_Model!$A$30:$A$33,1)) -> High | X6: =IF(OR(J6="No",K6=""),"",INDEX(Risk_Model!$C$38:$C$43,MATCH(K6,Risk_Model!$A$38:$A$43,0))) | Y6: =IF(X6="","",ROUND(V6*(1-X6),1)) | Z6: =IF(Y6="","",INDEX(Risk_Model!$B$30:$B$33,MATCH(Y6,Risk_Model!$A$30:$A$33,1))) | AA6: =IF(Y6="","",Y6+ROW()/1000000)
A7: SRV-PHY-03 | B7: Server Security | C7: Physical and Environmental Security | D7: All | E7: Removable media and unused ports are controlled | F7: Are USB and removable-media ports, unused console ports and boot-from-removable options disabled or controlled on servers? | G7: 1 | H7: 2 | I7: 4 | J7: =IF(IFERROR(INDEX(Scope!$C$24:$C$41,MATCH($B7,Scope!$B$24:$B$41,0)),"Yes")="No","No",IF($D7="All","Yes",IF(IFERROR(INDEX(Scope!$C$18:$C$20,MATCH($D7,Scope!$B$18:$B$20,0)),"Yes")="No","No","Yes"))) -> Yes | L7: =Scope!$C$13 -> 3 | M7: =IF(AND(J7="Yes",K7<>""),MAX(0,L7-K7),"") | N7: =IF(J7="No","N/A",IF(K7="","Not assessed",IF(K7>=L7,"Meets target","Gap"))) -> Not assessed | T7: =IF(R7<>"",R7,H7) -> 2 | U7: =IF(S7<>"",S7,I7) -> 4 | V7: =T7*U7 -> 8 | W7: =INDEX(Risk_Model!$B$30:$B$33,MATCH(V7,Risk_Model!$A$30:$A$33,1)) -> Medium | X7: =IF(OR(J7="No",K7=""),"",INDEX(Risk_Model!$C$38:$C$43,MATCH(K7,Risk_Model!$A$38:$A$43,0))) | Y7: =IF(X7="","",ROUND(V7*(1-X7),1)) | Z7: =IF(Y7="","",INDEX(Risk_Model!$B$30:$B$33,MATCH(Y7,Risk_Model!$A$30:$A$33,1))) | AA7: =IF(Y7="","",Y7+ROW()/1000000)
A8: SRV-PHY-04 | B8: Server Security | C8: Physical and Environmental Security | D8: All | E8: Storage media is sanitised or destroyed before replacement and disposal | F8: Is media containing confidential data sanitised to a recognised standard or destroyed, with certificates retained, before leaving the organisation or being re-used? | G8: 2 | H8: 2 | I8: 4 | J8: =IF(IFERROR(INDEX(Scope!$C$24:$C$41,MATCH($B8,Scope!$B$24:$B$41,0)),"Yes")="No","No",IF($D8="All","Yes",IF(IFERROR(INDEX(Scope!$C$18:$C$20,MATCH($D8,Scope!$B$18:$B$20,0)),"Yes")="No","No","Yes"))) -> Yes | L8: =Scope!$C$13 -> 3 | M8: =IF(AND(J8="Yes",K8<>""),MAX(0,L8-K8),"") | N8: =IF(J8="No","N/A",IF(K8="","Not assessed",IF(K8>=L8,"Meets target","Gap"))) -> Not assessed | T8: =IF(R8<>"",R8,H8) -> 2 | U8: =IF(S8<>"",S8,I8) -> 4 | V8: =T8*U8 -> 8 | W8: =INDEX(Risk_Model!$B$30:$B$33,MATCH(V8,Risk_Model!$A$30:$A$33,1)) -> Medium | X8: =IF(OR(J8="No",K8=""),"",INDEX(Risk_Model!$C$38:$C$43,MATCH(K8,Risk_Model!$A$38:$A$43,0))) | Y8: =IF(X8="","",ROUND(V8*(1-X8),1)) | Z8: =IF(Y8="","",INDEX(Risk_Model!$B$30:$B$33,MATCH(Y8,Risk_Model!$A$30:$A$33,1))) | AA8: =IF(Y8="","",Y8+ROW()/1000000)
A9: SRV-CFG-01 | B9: Server Security | C9: Secure Configuration and Change | D9: All | E9: Secure configuration baselines are defined for every server platform | F9: Is there an approved hardening baseline (for example CIS Benchmark level) for each server OS and role, and is it applied at build? | G9: 3 | H9: 4 | I9: 4 | J9: =IF(IFERROR(INDEX(Scope!$C$24:$C$41,MATCH($B9,Scope!$B$24:$B$41,0)),"Yes")="No","No",IF($D9="All","Yes",IF(IFERROR(INDEX(Scope!$C$18:$C$20,MATCH($D9,Scope!$B$18:$B$20,0)),"Yes")="No","No","Yes"))) -> Yes | L9: =Scope!$C$13 -> 3 | M9: =IF(AND(J9="Yes",K9<>""),MAX(0,L9-K9),"") | N9: =IF(J9="No","N/A",IF(K9="","Not assessed",IF(K9>=L9,"Meets target","Gap"))) -> Not assessed | T9: =IF(R9<>"",R9,H9) -> 4 | U9: =IF(S9<>"",S9,I9) -> 4 | V9: =T9*U9 -> 16 | W9: =INDEX(Risk_Model!$B$30:$B$33,MATCH(V9,Risk_Model!$A$30:$A$33,1)) -> High | X9: =IF(OR(J9="No",K9=""),"",INDEX(Risk_Model!$C$38:$C$43,MATCH(K9,Risk_Model!$A$38:$A$43,0))) | Y9: =IF(X9="","",ROUND(V9*(1-X9),1)) | Z9: =IF(Y9="","",INDEX(Risk_Model!$B$30:$B$33,MATCH(Y9,Risk_Model!$A$30:$A$33,1))) | AA9: =IF(Y9="","",Y9+ROW()/1000000)
A10: SRV-CFG-02 | B10: Server Security | C10: Secure Configuration and Change | D10: All | E10: Configuration drift from the baseline is detected and corrected | F10: Is compliance with the baseline continuously or periodically assessed, with deviations tracked to closure? | G10: 2 | H10: 3 | I10: 3 | J10: =IF(IFERROR(INDEX(Scope!$C$24:$C$41,MATCH($B10,Scope!$B$24:$B$41,0)),"Yes")="No","No",IF($D10="All","Yes",IF(IFERROR(INDEX(Scope!$C$18:$C$20,MATCH($D10,Scope!$B$18:$B$20,0)),"Yes")="No","No","Yes"))) -> Yes | L10: =Scope!$C$13 -> 3 | M10: =IF(AND(J10="Yes",K10<>""),MAX(0,L10-K10),"") | N10: =IF(J10="No","N/A",IF(K10="","Not assessed",IF(K10>=L10,"Meets target","Gap"))) -> Not assessed | T10: =IF(R10<>"",R10,H10) -> 3 | U10: =IF(S10<>"",S10,I10) -> 3 | V10: =T10*U10 -> 9 | W10: =INDEX(Risk_Model!$B$30:$B$33,MATCH(V10,Risk_Model!$A$30:$A$33,1)) -> Medium | X10: =IF(OR(J10="No",K10=""),"",INDEX(Risk_Model!$C$38:$C$43,MATCH(K10,Risk_Model!$A$38:$A$43,0))) | Y10: =IF(X10="","",ROUND(V10*(1-X10),1)) | Z10: =IF(Y10="","",INDEX(Risk_Model!$B$30:$B$33,MATCH(Y10,Risk_Model!$A$30:$A$33,1))) | AA10: =IF(Y10="","",Y10+ROW()/1000000)
A11: SRV-CFG-03 | B11: Server Security | C11: Secure Configuration and Change | D11: All | E11: Unnecessary services, roles, features and ports are disabled or removed | F11: Are all services, roles, features, protocols and listening ports not required by the server role disabled or removed? | G11: 3 | H11: 3 | I11: 4 | J11: =IF(IFERROR(INDEX(Scope!$C$24:$C$41,MATCH($B11,Scope!$B$24:$B$41,0)),"Yes")="No","No",IF($D11="All","Yes",IF(IFERROR(INDEX(Scope!$C$18:$C$20,MATCH($D11,Scope!$B$18:$B$20,0)),"Yes")="No","No","Yes"))) -> Yes | L11: =Scope!$C$13 -> 3 | M11: =IF(AND(J11="Yes",K11<>""),MAX(0,L11-K11),"") | N11: =IF(J11="No","N/A",IF(K11="","Not assessed",IF(K11>=L11,"Meets target","Gap"))) -> Not assessed | T11: =IF(R11<>"",R11,H11) -> 3 | U11: =IF(S11<>"",S11,I11) -> 4 | V11: =T11*U11 -> 12 | W11: =INDEX(Risk_Model!$B$30:$B$33,MATCH(V11,Risk_Model!$A$30:$A$33,1)) -> High | X11: =IF(OR(J11="No",K11=""),"",INDEX(Risk_Model!$C$38:$C$43,MATCH(K11,Risk_Model!$A$38:$A$43,0))) | Y11: =IF(X11="","",ROUND(V11*(1-X11),1)) | Z11: =IF(Y11="","",INDEX(Risk_Model!$B$30:$B$33,MATCH(Y11,Risk_Model!$A$30:$A$33,1))) | AA11: =IF(Y11="","",Y11+ROW()/1000000)
A12: SRV-CFG-04 | B12: Server Security | C12: Secure Configuration and Change | D12: All | E12: An approved authorised-use banner is displayed at login | F12: Do servers display a legally approved authorised-use notice at console, SSH, RDP and web administration logins? | G12: 1 | H12: 1 | I12: 2 | J12: =IF(IFERROR(INDEX(Scope!$C$24:$C$41,MATCH($B12,Scope!$B$24:$B$41,0)),"Yes")="No","No",IF($D12="All","Yes",IF(IFERROR(INDEX(Scope!$C$18:$C$20,MATCH($D12,Scope!$B$18:$B$20,0)),"Yes")="No","No","Yes"))) -> Yes | L12: =Scope!$C$13 -> 3 | M12: =IF(AND(J12="Yes",K12<>""),MAX(0,L12-K12),"") | N12: =IF(J12="No","N/A",IF(K12="","Not assessed",IF(K12>=L12,"Meets target","Gap"))) -> Not assessed | T12: =IF(R12<>"",R12,H12) -> 1 | U12: =IF(S12<>"",S12,I12) -> 2 | V12: =T12*U12 -> 2 | W12: =INDEX(Risk_Model!$B$30:$B$33,MATCH(V12,Risk_Model!$A$30:$A$33,1)) -> Low | X12: =IF(OR(J12="No",K12=""),"",INDEX(Risk_Model!$C$38:$C$43,MATCH(K12,Risk_Model!$A$38:$A$43,0))) | Y12: =IF(X12="","",ROUND(V12*(1-X12),1)) | Z12: =IF(Y12="","",INDEX(Risk_Model!$B$30:$B$33,MATCH(Y12,Risk_Model!$A$30:$A$33,1))) | AA12: =IF(Y12="","",Y12+ROW()/1000000)
A13: SRV-CFG-05 | B13: Server Security | C13: Secure Configuration and Change | D13: All | E13: Boot chain integrity protections are enabled | F13: Are Secure Boot, a UEFI/BIOS administrator password, TPM-backed measured boot and restricted boot order enabled on physical and virtual servers where supported? | G13: 2 | H13: 2 | I13: 4 | J13: =IF(IFERROR(INDEX(Scope!$C$24:$C$41,MATCH($B13,Scope!$B$24:$B$41,0)),"Yes")="No","No",IF($D13="All","Yes",IF(IFERROR(INDEX(Scope!$C$18:$C$20,MATCH($D13,Scope!$B$18:$B$20,0)),"Yes")="No","No","Yes"))) -> Yes | L13: =Scope!$C$13 -> 3 | M13: =IF(AND(J13="Yes",K13<>""),MAX(0,L13-K13),"") | N13: =IF(J13="No","N/A",IF(K13="","Not assessed",IF(K13>=L13,"Meets target","Gap"))) -> Not assessed | T13: =IF(R13<>"",R13,H13) -> 2 | U13: =IF(S13<>"",S13,I13) -> 4 | V13: =T13*U13 -> 8 | W13: =INDEX(Risk_Model!$B$30:$B$33,MATCH(V13,Risk_Model!$A$30:$A$33,1)) -> Medium | X13: =IF(OR(J13="No",K13=""),"",INDEX(Risk_Model!$C$38:$C$43,MATCH(K13,Risk_Model!$A$38:$A$43,0))) | Y13: =IF(X13="","",ROUND(V13*(1-X13),1)) | Z13: =IF(Y13="","",INDEX(Risk_Model!$B$30:$B$33,MATCH(Y13,Risk_Model!$A$30:$A$33,1))) | AA13: =IF(Y13="","",Y13+ROW()/1000000)
A14: SRV-CFG-06 | B14: Server Security | C14: Secure Configuration and Change | D14: All | E14: Server configuration changes follow documented change control | F14: Is there a documented change process for server configuration (request, risk review, approval, test, rollback, post-change review) and is it followed? | G14: 2 | H14: 3 | I14: 3 | J14: =IF(IFERROR(INDEX(Scope!$C$24:$C$41,MATCH($B14,Scope!$B$24:$B$41,0)),"Yes")="No","No",IF($D14="All","Yes",IF(IFERROR(INDEX(Scope!$C$18:$C$20,MATCH($D14,Scope!$B$18:$B$20,0)),"Yes")="No","No","Yes"))) -> Yes | L14: =Scope!$C$13 -> 3 | M14: =IF(AND(J14="Yes",K14<>""),MAX(0,L14-K14),"") | N14: =IF(J14="No","N/A",IF(K14="","Not assessed",IF(K14>=L14,"Meets target","Gap"))) -> Not assessed | T14: =IF(R14<>"",R14,H14) -> 3 | U14: =IF(S14<>"",S14,I14) -> 3 | V14: =T14*U14 -> 9 | W14: =INDEX(Risk_Model!$B$30:$B$33,MATCH(V14,Risk_Model!$A$30:$A$33,1)) -> Medium | X14: =IF(OR(J14="No",K14=""),"",INDEX(Risk_Model!$C$38:$C$43,MATCH(K14,Risk_Model!$A$38:$A$43,0))) | Y14: =IF(X14="","",ROUND(V14*(1-X14),1)) | Z14: =IF(Y14="","",INDEX(Risk_Model!$B$30:$B$33,MATCH(Y14,Risk_Model!$A$30:$A$33,1))) | AA14: =IF(Y14="","",Y14+ROW()/1000000)
A15: SRV-CFG-07 | B15: Server Security | C15: Secure Configuration and Change | D15: All | E15: Only authorised software can execute or be installed on servers | F15: Is application allow-listing or equivalent execution control enforced on servers, and is software installation restricted to approved administrators and sources? | G15: 2 | H15: 3 | I15: 4 | J15: =IF(IFERROR(INDEX(Scope!$C$24:$C$41,MATCH($B15,Scope!$B$24:$B$41,0)),"Yes")="No","No",IF($D15="All","Yes",IF(IFERROR(INDEX(Scope!$C$18:$C$20,MATCH($D15,Scope!$B$18:$B$20,0)),"Yes")="No","No","Yes"))) -> Yes | L15: =Scope!$C$13 -> 3 | M15: =IF(AND(J15="Yes",K15<>""),MAX(0,L15-K15),"") | N15: =IF(J15="No","N/A",IF(K15="","Not assessed",IF(K15>=L15,"Meets target","Gap"))) -> Not assessed | T15: =IF(R15<>"",R15,H15) -> 3 | U15: =IF(S15<>"",S15,I15) -> 4 | V15: =T15*U15 -> 12 | W15: =INDEX(Risk_Model!$B$30:$B$33,MATCH(V15,Risk_Model!$A$30:$A$33,1)) -> High | X15: =IF(OR(J15="No",K15=""),"",INDEX(Risk_Model!$C$38:$C$43,MATCH(K15,Risk_Model!$A$38:$A$43,0))) | Y15: =IF(X15="","",ROUND(V15*(1-X15),1)) | Z15: =IF(Y15="","",INDEX(Risk_Model!$B$30:$B$33,MATCH(Y15,Risk_Model!$A$30:$A$33,1))) | AA15: =IF(Y15="","",Y15+ROW()/1000000)
A16: SRV-PAT-01 | B16: Server Security | C16: Patch and Lifecycle Management | D16: All | E16: A documented patch management process with risk-based timelines exists | F16: Is there a documented patch process defining roles, schedules, severity-based timelines, testing, exceptions and coverage of OS, applications and firmware? | G16: 3 | H16: 4 | I16: 5 | J16: =IF(IFERROR(INDEX(Scope!$C$24:$C$41,MATCH($B16,Scope!$B$24:$B$41,0)),"Yes")="No","No",IF($D16="All","Yes",IF(IFERROR(INDEX(Scope!$C$18:$C$20,MATCH($D16,Scope!$B$18:$B$20,0)),"Yes")="No","No","Yes"))) -> Yes | L16: =Scope!$C$13 -> 3 | M16: =IF(AND(J16="Yes",K16<>""),MAX(0,L16-K16),"") | N16: =IF(J16="No","N/A",IF(K16="","Not assessed",IF(K16>=L16,"Meets target","Gap"))) -> Not assessed | T16: =IF(R16<>"",R16,H16) -> 4 | U16: =IF(S16<>"",S16,I16) -> 5 | V16: =T16*U16 -> 20 | W16: =INDEX(Risk_Model!$B$30:$B$33,MATCH(V16,Risk_Model!$A$30:$A$33,1)) -> Critical | X16: =IF(OR(J16="No",K16=""),"",INDEX(Risk_Model!$C$38:$C$43,MATCH(K16,Risk_Model!$A$38:$A$43,0))) | Y16: =IF(X16="","",ROUND(V16*(1-X16),1)) | Z16: =IF(Y16="","",INDEX(Risk_Model!$B$30:$B$33,MATCH(Y16,Risk_Model!$A$30:$A$33,1))) | AA16: =IF(Y16="","",Y16+ROW()/1000000)
... A64: SRV-VIR-05 | B64: Server Security | C64: Virtualization Platforms | D64: Hypervisor | E64: Hypervisor logging and ransomware resilience controls are in place | F64: Are hypervisor and management logs forwarded to the SIEM, shell and SSH services disabled by default, host configuration backed up, and ransomware protections (acceptance levels, execution restrictions, datastore snapshots and backups) in place? | G64: 3 | H64: 3 | I64: 5 | J64: =IF(IFERROR(INDEX(Scope!$C$24:$C$41,MATCH($B64,Scope!$B$24:$B$41,0)),"Yes")="No","No",IF($D64="All","Yes",IF(IFERROR(INDEX(Scope!$C$18:$C$20,MATCH($D64,Scope!$B$18:$B$20,0)),"Yes")="No","No","Yes"))) -> Yes | L64: =Scope!$C$13 -> 3 | M64: =IF(AND(J64="Yes",K64<>""),MAX(0,L64-K64),"") | N64: =IF(J64="No","N/A",IF(K64="","Not assessed",IF(K64>=L64,"Meets target","Gap"))) -> Not assessed | T64: =IF(R64<>"",R64,H64) -> 3 | U64: =IF(S64<>"",S64,I64) -> 5 | V64: =T64*U64 -> 15 | W64: =INDEX(Risk_Model!$B$30:$B$33,MATCH(V64,Risk_Model!$A$30:$A$33,1)) -> High | X64: =IF(OR(J64="No",K64=""),"",INDEX(Risk_Model!$C$38:$C$43,MATCH(K64,Risk_Model!$A$38:$A$43,0))) | Y64: =IF(X64="","",ROUND(V64*(1-X64),1)) | Z64: =IF(Y64="","",INDEX(Risk_Model!$B$30:$B$33,MATCH(Y64,Risk_Model!$A$30:$A$33,1))) | AA64: =IF(Y64="","",Y64+ROW()/1000000)

Sheet Evidence_Requests
A1: Evidence Workbook - Request List (PBC)
A2: One row per evidence item required by the control library. Send to the client, track receipt, and link received items to the Evidence_Register.
A4: Request ID | B4: Control ID | C4: Control Name | D4: Evidence Item Requested | E4: Date Requested | F4: Status | G4: Date Received | H4: Evidence ID | I4: Notes
A5: ER-SRV-PHY-01-1 | B5: SRV-PHY-01 | C5: Physical access to servers is restricted and logged | D5: Authorised access list | F5: Not requested
A6: ER-SRV-PHY-01-2 | B6: SRV-PHY-01 | C6: Physical access to servers is restricted and logged | D6: badge and visitor logs (90 days) | F6: Not requested
A7: ER-SRV-PHY-01-3 | B7: SRV-PHY-01 | C7: Physical access to servers is restricted and logged | D7: CCTV coverage evidence | F7: Not requested
A8: ER-SRV-PHY-01-4 | B8: SRV-PHY-01 | C8: Physical access to servers is restricted and logged | D8: photos of rack locks | F8: Not requested
A9: ER-SRV-PHY-01-5 | B9: SRV-PHY-01 | C9: Physical access to servers is restricted and logged | D9: physical security policy | F9: Not requested
A10: ER-SRV-PHY-01-6 | B10: SRV-PHY-01 | C10: Physical access to servers is restricted and logged | D10: colocation contract and assurance report if hosted | F10: Not requested
A11: ER-SRV-PHY-02-1 | B11: SRV-PHY-02 | C11: Out-of-band management interfaces are isolated and hardened | D11: Management network diagram | F11: Not requested
A12: ER-SRV-PHY-02-2 | B12: SRV-PHY-02 | C12: Out-of-band management interfaces are isolated and hardened | D12: BMC inventory with firmware versions | F12: Not requested
A13: ER-SRV-PHY-02-3 | B13: SRV-PHY-02 | C13: Out-of-band management interfaces are isolated and hardened | D13: firewall rules for the management VLAN | F13: Not requested
A14: ER-SRV-PHY-02-4 | B14: SRV-PHY-02 | C14: Out-of-band management interfaces are isolated and hardened | D14: BMC user list and authentication settings | F14: Not requested
A15: ER-SRV-PHY-03-1 | B15: SRV-PHY-03 | C15: Removable media and unused ports are controlled | D15: GPO, MDM, udev or USBGuard configuration | F15: Not requested
A16: ER-SRV-PHY-03-2 | B16: SRV-PHY-03 | C16: Removable media and unused ports are controlled | D16: BIOS/UEFI boot-order settings | F16: Not requested
... A261: ER-SRV-VIR-05-5 | B261: SRV-VIR-05 | C261: Hypervisor logging and ransomware resilience controls are in place | D261: vendor hardening guide compliance | F261: Not requested

Sheet Evidence_Register
A1: Evidence Register
A2: Row 5 is an example. Enter evidence from row 6. Control name looks up from the Assessment sheet.
A4: Evidence ID | B4: Control ID | C4: Control Name | D4: Evidence Type | E4: Description | F4: Source System / Asset | G4: Collection Method | H4: Collected By | I4: Date Collected | J4: Storage Location / Link | K4: SHA-256 (optional) | L4: Reviewer | M4: Review Status | N4: Confidentiality
A5: EXAMPLE | B5: SRV-LOG-02 | C5: =IFERROR(INDEX(Assessment!$E$5:$E$2000,MATCH(B5,Assessment!$A$5:$A$2000,0)),"") -> Logs are forwarded in near real time to a central tamper-resistant store | D5: Screenshot | E5: SIEM log-source health dashboard showing last-seen time per server | F5: Splunk | G5: Manual | H5: A. Assessor | I5: 46296 | J5: Evidence/SRV-LOG-02/siem_health.png | L5: B. Reviewer | M5: Accepted | N5: Confidential
C6: =IF(B6="","",IFERROR(INDEX(Assessment!$E$5:$E$2000,MATCH(B6,Assessment!$A$5:$A$2000,0)),"Not found"))
C7: =IF(B7="","",IFERROR(INDEX(Assessment!$E$5:$E$2000,MATCH(B7,Assessment!$A$5:$A$2000,0)),"Not found"))
C8: =IF(B8="","",IFERROR(INDEX(Assessment!$E$5:$E$2000,MATCH(B8,Assessment!$A$5:$A$2000,0)),"Not found"))
C9: =IF(B9="","",IFERROR(INDEX(Assessment!$E$5:$E$2000,MATCH(B9,Assessment!$A$5:$A$2000,0)),"Not found"))
C10: =IF(B10="","",IFERROR(INDEX(Assessment!$E$5:$E$2000,MATCH(B10,Assessment!$A$5:$A$2000,0)),"Not found"))
C11: =IF(B11="","",IFERROR(INDEX(Assessment!$E$5:$E$2000,MATCH(B11,Assessment!$A$5:$A$2000,0)),"Not found"))
C12: =IF(B12="","",IFERROR(INDEX(Assessment!$E$5:$E$2000,MATCH(B12,Assessment!$A$5:$A$2000,0)),"Not found"))
C13: =IF(B13="","",IFERROR(INDEX(Assessment!$E$5:$E$2000,MATCH(B13,Assessment!$A$5:$A$2000,0)),"Not found"))
C14: =IF(B14="","",IFERROR(INDEX(Assessment!$E$5:$E$2000,MATCH(B14,Assessment!$A$5:$A$2000,0)),"Not found"))
C15: =IF(B15="","",IFERROR(INDEX(Assessment!$E$5:$E$2000,MATCH(B15,Assessment!$A$5:$A$2000,0)),"Not found"))
C16: =IF(B16="","",IFERROR(INDEX(Assessment!$E$5:$E$2000,MATCH(B16,Assessment!$A$5:$A$2000,0)),"Not found"))
C17: =IF(B17="","",IFERROR(INDEX(Assessment!$E$5:$E$2000,MATCH(B17,Assessment!$A$5:$A$2000,0)),"Not found"))
... C205: =IF(B205="","",IFERROR(INDEX(Assessment!$E$5:$E$2000,MATCH(B205,Assessment!$A$5:$A$2000,0)),"Not found"))

Sheet Findings_Register
A1: Findings Register
A2: Row 5 is an example. Enter findings from row 6. Open = Open or In Progress. Overdue is calculated from the due date.
A4: Finding ID | B4: Control ID | C4: Control Name | D4: Domain | E4: Finding | F4: Severity | G4: Evidence Ref(s) | H4: Recommendation | I4: Owner | J4: Due Date | K4: Status | L4: Date Raised | M4: Days Open | N4: Overdue?
A5: EXAMPLE | B5: SRV-LOG-02 | E5: Only 60% of servers forward logs to the SIEM and no alert exists for cleared Security logs. | F5: High | G5: EV-001 | H5: Deploy forwarders to all servers and create alerts for silent sources and event 1102. | I5: Infrastructure Lead | J5: 46371 | K5: Open | L5: 46297
C6: =IF(B6="","",IFERROR(INDEX(Assessment!$E$5:$E$2000,MATCH(B6,Assessment!$A$5:$A$2000,0)),"Not found")) | D6: =IF(B6="","",IFERROR(INDEX(Assessment!$B$5:$B$2000,MATCH(B6,Assessment!$A$5:$A$2000,0)),"Not found")) | M6: =IF(OR(L6="",K6="Closed",K6="Risk Accepted"),"",TODAY()-L6) | N6: =IF(OR(J6="",K6="Closed",K6="Risk Accepted",K6="Remediated"),"",IF(TODAY()>J6,"Overdue",""))
C7: =IF(B7="","",IFERROR(INDEX(Assessment!$E$5:$E$2000,MATCH(B7,Assessment!$A$5:$A$2000,0)),"Not found")) | D7: =IF(B7="","",IFERROR(INDEX(Assessment!$B$5:$B$2000,MATCH(B7,Assessment!$A$5:$A$2000,0)),"Not found")) | M7: =IF(OR(L7="",K7="Closed",K7="Risk Accepted"),"",TODAY()-L7) | N7: =IF(OR(J7="",K7="Closed",K7="Risk Accepted",K7="Remediated"),"",IF(TODAY()>J7,"Overdue",""))
C8: =IF(B8="","",IFERROR(INDEX(Assessment!$E$5:$E$2000,MATCH(B8,Assessment!$A$5:$A$2000,0)),"Not found")) | D8: =IF(B8="","",IFERROR(INDEX(Assessment!$B$5:$B$2000,MATCH(B8,Assessment!$A$5:$A$2000,0)),"Not found")) | M8: =IF(OR(L8="",K8="Closed",K8="Risk Accepted"),"",TODAY()-L8) | N8: =IF(OR(J8="",K8="Closed",K8="Risk Accepted",K8="Remediated"),"",IF(TODAY()>J8,"Overdue",""))
C9: =IF(B9="","",IFERROR(INDEX(Assessment!$E$5:$E$2000,MATCH(B9,Assessment!$A$5:$A$2000,0)),"Not found")) | D9: =IF(B9="","",IFERROR(INDEX(Assessment!$B$5:$B$2000,MATCH(B9,Assessment!$A$5:$A$2000,0)),"Not found")) | M9: =IF(OR(L9="",K9="Closed",K9="Risk Accepted"),"",TODAY()-L9) | N9: =IF(OR(J9="",K9="Closed",K9="Risk Accepted",K9="Remediated"),"",IF(TODAY()>J9,"Overdue",""))
C10: =IF(B10="","",IFERROR(INDEX(Assessment!$E$5:$E$2000,MATCH(B10,Assessment!$A$5:$A$2000,0)),"Not found")) | D10: =IF(B10="","",IFERROR(INDEX(Assessment!$B$5:$B$2000,MATCH(B10,Assessment!$A$5:$A$2000,0)),"Not found")) | M10: =IF(OR(L10="",K10="Closed",K10="Risk Accepted"),"",TODAY()-L10) | N10: =IF(OR(J10="",K10="Closed",K10="Risk Accepted",K10="Remediated"),"",IF(TODAY()>J10,"Overdue",""))
C11: =IF(B11="","",IFERROR(INDEX(Assessment!$E$5:$E$2000,MATCH(B11,Assessment!$A$5:$A$2000,0)),"Not found")) | D11: =IF(B11="","",IFERROR(INDEX(Assessment!$B$5:$B$2000,MATCH(B11,Assessment!$A$5:$A$2000,0)),"Not found")) | M11: =IF(OR(L11="",K11="Closed",K11="Risk Accepted"),"",TODAY()-L11) | N11: =IF(OR(J11="",K11="Closed",K11="Risk Accepted",K11="Remediated"),"",IF(TODAY()>J11,"Overdue",""))
C12: =IF(B12="","",IFERROR(INDEX(Assessment!$E$5:$E$2000,MATCH(B12,Assessment!$A$5:$A$2000,0)),"Not found")) | D12: =IF(B12="","",IFERROR(INDEX(Assessment!$B$5:$B$2000,MATCH(B12,Assessment!$A$5:$A$2000,0)),"Not found")) | M12: =IF(OR(L12="",K12="Closed",K12="Risk Accepted"),"",TODAY()-L12) | N12: =IF(OR(J12="",K12="Closed",K12="Risk Accepted",K12="Remediated"),"",IF(TODAY()>J12,"Overdue",""))
C13: =IF(B13="","",IFERROR(INDEX(Assessment!$E$5:$E$2000,MATCH(B13,Assessment!$A$5:$A$2000,0)),"Not found")) | D13: =IF(B13="","",IFERROR(INDEX(Assessment!$B$5:$B$2000,MATCH(B13,Assessment!$A$5:$A$2000,0)),"Not found")) | M13: =IF(OR(L13="",K13="Closed",K13="Risk Accepted"),"",TODAY()-L13) | N13: =IF(OR(J13="",K13="Closed",K13="Risk Accepted",K13="Remediated"),"",IF(TODAY()>J13,"Overdue",""))
C14: =IF(B14="","",IFERROR(INDEX(Assessment!$E$5:$E$2000,MATCH(B14,Assessment!$A$5:$A$2000,0)),"Not found")) | D14: =IF(B14="","",IFERROR(INDEX(Assessment!$B$5:$B$2000,MATCH(B14,Assessment!$A$5:$A$2000,0)),"Not found")) | M14: =IF(OR(L14="",K14="Closed",K14="Risk Accepted"),"",TODAY()-L14) | N14: =IF(OR(J14="",K14="Closed",K14="Risk Accepted",K14="Remediated"),"",IF(TODAY()>J14,"Overdue",""))
C15: =IF(B15="","",IFERROR(INDEX(Assessment!$E$5:$E$2000,MATCH(B15,Assessment!$A$5:$A$2000,0)),"Not found")) | D15: =IF(B15="","",IFERROR(INDEX(Assessment!$B$5:$B$2000,MATCH(B15,Assessment!$A$5:$A$2000,0)),"Not found")) | M15: =IF(OR(L15="",K15="Closed",K15="Risk Accepted"),"",TODAY()-L15) | N15: =IF(OR(J15="",K15="Closed",K15="Risk Accepted",K15="Remediated"),"",IF(TODAY()>J15,"Overdue",""))
C16: =IF(B16="","",IFERROR(INDEX(Assessment!$E$5:$E$2000,MATCH(B16,Assessment!$A$5:$A$2000,0)),"Not found")) | D16: =IF(B16="","",IFERROR(INDEX(Assessment!$B$5:$B$2000,MATCH(B16,Assessment!$A$5:$A$2000,0)),"Not found")) | M16: =IF(OR(L16="",K16="Closed",K16="Risk Accepted"),"",TODAY()-L16) | N16: =IF(OR(J16="",K16="Closed",K16="Risk Accepted",K16="Remediated"),"",IF(TODAY()>J16,"Overdue",""))
C17: =IF(B17="","",IFERROR(INDEX(Assessment!$E$5:$E$2000,MATCH(B17,Assessment!$A$5:$A$2000,0)),"Not found")) | D17: =IF(B17="","",IFERROR(INDEX(Assessment!$B$5:$B$2000,MATCH(B17,Assessment!$A$5:$A$2000,0)),"Not found")) | M17: =IF(OR(L17="",K17="Closed",K17="Risk Accepted"),"",TODAY()-L17) | N17: =IF(OR(J17="",K17="Closed",K17="Risk Accepted",K17="Remediated"),"",IF(TODAY()>J17,"Overdue",""))
... C205: =IF(B205="","",IFERROR(INDEX(Assessment!$E$5:$E$2000,MATCH(B205,Assessment!$A$5:$A$2000,0)),"Not found")) | D205: =IF(B205="","",IFERROR(INDEX(Assessment!$B$5:$B$2000,MATCH(B205,Assessment!$A$5:$A$2000,0)),"Not found")) | M205: =IF(OR(L205="",K205="Closed",K205="Risk Accepted"),"",TODAY()-L205) | N205: =IF(OR(J205="",K205="Closed",K205="Risk Accepted",K205="Remediated"),"",IF(TODAY()>J205,"Overdue",""))

Sheet Risk_Register
A1: Risk Register
A2: Row 5 is an example. Enter risks from row 6. Residual risk uses the assessed maturity of the linked control.
A4: Risk ID | B4: Control ID | C4: Control | D4: Linked Finding ID | E4: Finding / Risk Description | F4: Likelihood (1-5) | G4: Impact (1-5) | H4: Risk Score | I4: Rating | J4: Treatment | K4: Control Maturity | L4: Residual Score | M4: Residual Rating | N4: Owner | O4: Target Date | P4: Status | Q4: Business Impact
A5: EXAMPLE | B5: SRV-LOG-02 | C5: =IF(B5="","",IFERROR(INDEX(Assessment!$E$5:$E$2000,MATCH(B5,Assessment!$A$5:$A$2000,0)),"Not found")) -> Logs are forwarded in near real time to a central tamper-resistant store | D5: EXAMPLE | E5: Intrusions on unforwarded servers could go undetected and evidence could be erased. | F5: 4 | G5: 5 | H5: =IF(OR(F5="",G5=""),"",F5*G5) -> 20 | I5: =IF(H5="","",INDEX(Risk_Model!$B$30:$B$33,MATCH(H5,Risk_Model!$A$30:$A$33,1))) -> Critical | J5: Mitigate | K5: =IF(B5="","",IFERROR(IF(INDEX(Assessment!$K$5:$K$2000,MATCH(B5,Assessment!$A$5:$A$2000,0))="","",INDEX(Assessment!$K$5:$K$2000,MATCH(B5,Assessment!$A$5:$A$2000,0))),"")) | L5: =IF(OR(H5="",K5=""),"",ROUND(H5*(1-INDEX(Risk_Model!$C$38:$C$43,MATCH(K5,Risk_Model!$A$38:$A$43,0))),1)) | M5: =IF(L5="","",INDEX(Risk_Model!$B$30:$B$33,MATCH(L5,Risk_Model!$A$30:$A$33,1))) | N5: Infrastructure Lead | O5: 46371 | P5: Open | Q5: Regulatory
C6: =IF(B6="","",IFERROR(INDEX(Assessment!$E$5:$E$2000,MATCH(B6,Assessment!$A$5:$A$2000,0)),"Not found")) | H6: =IF(OR(F6="",G6=""),"",F6*G6) | I6: =IF(H6="","",INDEX(Risk_Model!$B$30:$B$33,MATCH(H6,Risk_Model!$A$30:$A$33,1))) | K6: =IF(B6="","",IFERROR(IF(INDEX(Assessment!$K$5:$K$2000,MATCH(B6,Assessment!$A$5:$A$2000,0))="","",INDEX(Assessment!$K$5:$K$2000,MATCH(B6,Assessment!$A$5:$A$2000,0))),"")) | L6: =IF(OR(H6="",K6=""),"",ROUND(H6*(1-INDEX(Risk_Model!$C$38:$C$43,MATCH(K6,Risk_Model!$A$38:$A$43,0))),1)) | M6: =IF(L6="","",INDEX(Risk_Model!$B$30:$B$33,MATCH(L6,Risk_Model!$A$30:$A$33,1)))
C7: =IF(B7="","",IFERROR(INDEX(Assessment!$E$5:$E$2000,MATCH(B7,Assessment!$A$5:$A$2000,0)),"Not found")) | H7: =IF(OR(F7="",G7=""),"",F7*G7) | I7: =IF(H7="","",INDEX(Risk_Model!$B$30:$B$33,MATCH(H7,Risk_Model!$A$30:$A$33,1))) | K7: =IF(B7="","",IFERROR(IF(INDEX(Assessment!$K$5:$K$2000,MATCH(B7,Assessment!$A$5:$A$2000,0))="","",INDEX(Assessment!$K$5:$K$2000,MATCH(B7,Assessment!$A$5:$A$2000,0))),"")) | L7: =IF(OR(H7="",K7=""),"",ROUND(H7*(1-INDEX(Risk_Model!$C$38:$C$43,MATCH(K7,Risk_Model!$A$38:$A$43,0))),1)) | M7: =IF(L7="","",INDEX(Risk_Model!$B$30:$B$33,MATCH(L7,Risk_Model!$A$30:$A$33,1)))
C8: =IF(B8="","",IFERROR(INDEX(Assessment!$E$5:$E$2000,MATCH(B8,Assessment!$A$5:$A$2000,0)),"Not found")) | H8: =IF(OR(F8="",G8=""),"",F8*G8) | I8: =IF(H8="","",INDEX(Risk_Model!$B$30:$B$33,MATCH(H8,Risk_Model!$A$30:$A$33,1))) | K8: =IF(B8="","",IFERROR(IF(INDEX(Assessment!$K$5:$K$2000,MATCH(B8,Assessment!$A$5:$A$2000,0))="","",INDEX(Assessment!$K$5:$K$2000,MATCH(B8,Assessment!$A$5:$A$2000,0))),"")) | L8: =IF(OR(H8="",K8=""),"",ROUND(H8*(1-INDEX(Risk_Model!$C$38:$C$43,MATCH(K8,Risk_Model!$A$38:$A$43,0))),1)) | M8: =IF(L8="","",INDEX(Risk_Model!$B$30:$B$33,MATCH(L8,Risk_Model!$A$30:$A$33,1)))
C9: =IF(B9="","",IFERROR(INDEX(Assessment!$E$5:$E$2000,MATCH(B9,Assessment!$A$5:$A$2000,0)),"Not found")) | H9: =IF(OR(F9="",G9=""),"",F9*G9) | I9: =IF(H9="","",INDEX(Risk_Model!$B$30:$B$33,MATCH(H9,Risk_Model!$A$30:$A$33,1))) | K9: =IF(B9="","",IFERROR(IF(INDEX(Assessment!$K$5:$K$2000,MATCH(B9,Assessment!$A$5:$A$2000,0))="","",INDEX(Assessment!$K$5:$K$2000,MATCH(B9,Assessment!$A$5:$A$2000,0))),"")) | L9: =IF(OR(H9="",K9=""),"",ROUND(H9*(1-INDEX(Risk_Model!$C$38:$C$43,MATCH(K9,Risk_Model!$A$38:$A$43,0))),1)) | M9: =IF(L9="","",INDEX(Risk_Model!$B$30:$B$33,MATCH(L9,Risk_Model!$A$30:$A$33,1)))
C10: =IF(B10="","",IFERROR(INDEX(Assessment!$E$5:$E$2000,MATCH(B10,Assessment!$A$5:$A$2000,0)),"Not found")) | H10: =IF(OR(F10="",G10=""),"",F10*G10) | I10: =IF(H10="","",INDEX(Risk_Model!$B$30:$B$33,MATCH(H10,Risk_Model!$A$30:$A$33,1))) | K10: =IF(B10="","",IFERROR(IF(INDEX(Assessment!$K$5:$K$2000,MATCH(B10,Assessment!$A$5:$A$2000,0))="","",INDEX(Assessment!$K$5:$K$2000,MATCH(B10,Assessment!$A$5:$A$2000,0))),"")) | L10: =IF(OR(H10="",K10=""),"",ROUND(H10*(1-INDEX(Risk_Model!$C$38:$C$43,MATCH(K10,Risk_Model!$A$38:$A$43,0))),1)) | M10: =IF(L10="","",INDEX(Risk_Model!$B$30:$B$33,MATCH(L10,Risk_Model!$A$30:$A$33,1)))
C11: =IF(B11="","",IFERROR(INDEX(Assessment!$E$5:$E$2000,MATCH(B11,Assessment!$A$5:$A$2000,0)),"Not found")) | H11: =IF(OR(F11="",G11=""),"",F11*G11) | I11: =IF(H11="","",INDEX(Risk_Model!$B$30:$B$33,MATCH(H11,Risk_Model!$A$30:$A$33,1))) | K11: =IF(B11="","",IFERROR(IF(INDEX(Assessment!$K$5:$K$2000,MATCH(B11,Assessment!$A$5:$A$2000,0))="","",INDEX(Assessment!$K$5:$K$2000,MATCH(B11,Assessment!$A$5:$A$2000,0))),"")) | L11: =IF(OR(H11="",K11=""),"",ROUND(H11*(1-INDEX(Risk_Model!$C$38:$C$43,MATCH(K11,Risk_Model!$A$38:$A$43,0))),1)) | M11: =IF(L11="","",INDEX(Risk_Model!$B$30:$B$33,MATCH(L11,Risk_Model!$A$30:$A$33,1)))
C12: =IF(B12="","",IFERROR(INDEX(Assessment!$E$5:$E$2000,MATCH(B12,Assessment!$A$5:$A$2000,0)),"Not found")) | H12: =IF(OR(F12="",G12=""),"",F12*G12) | I12: =IF(H12="","",INDEX(Risk_Model!$B$30:$B$33,MATCH(H12,Risk_Model!$A$30:$A$33,1))) | K12: =IF(B12="","",IFERROR(IF(INDEX(Assessment!$K$5:$K$2000,MATCH(B12,Assessment!$A$5:$A$2000,0))="","",INDEX(Assessment!$K$5:$K$2000,MATCH(B12,Assessment!$A$5:$A$2000,0))),"")) | L12: =IF(OR(H12="",K12=""),"",ROUND(H12*(1-INDEX(Risk_Model!$C$38:$C$43,MATCH(K12,Risk_Model!$A$38:$A$43,0))),1)) | M12: =IF(L12="","",INDEX(Risk_Model!$B$30:$B$33,MATCH(L12,Risk_Model!$A$30:$A$33,1)))
C13: =IF(B13="","",IFERROR(INDEX(Assessment!$E$5:$E$2000,MATCH(B13,Assessment!$A$5:$A$2000,0)),"Not found")) | H13: =IF(OR(F13="",G13=""),"",F13*G13) | I13: =IF(H13="","",INDEX(Risk_Model!$B$30:$B$33,MATCH(H13,Risk_Model!$A$30:$A$33,1))) | K13: =IF(B13="","",IFERROR(IF(INDEX(Assessment!$K$5:$K$2000,MATCH(B13,Assessment!$A$5:$A$2000,0))="","",INDEX(Assessment!$K$5:$K$2000,MATCH(B13,Assessment!$A$5:$A$2000,0))),"")) | L13: =IF(OR(H13="",K13=""),"",ROUND(H13*(1-INDEX(Risk_Model!$C$38:$C$43,MATCH(K13,Risk_Model!$A$38:$A$43,0))),1)) | M13: =IF(L13="","",INDEX(Risk_Model!$B$30:$B$33,MATCH(L13,Risk_Model!$A$30:$A$33,1)))
C14: =IF(B14="","",IFERROR(INDEX(Assessment!$E$5:$E$2000,MATCH(B14,Assessment!$A$5:$A$2000,0)),"Not found")) | H14: =IF(OR(F14="",G14=""),"",F14*G14) | I14: =IF(H14="","",INDEX(Risk_Model!$B$30:$B$33,MATCH(H14,Risk_Model!$A$30:$A$33,1))) | K14: =IF(B14="","",IFERROR(IF(INDEX(Assessment!$K$5:$K$2000,MATCH(B14,Assessment!$A$5:$A$2000,0))="","",INDEX(Assessment!$K$5:$K$2000,MATCH(B14,Assessment!$A$5:$A$2000,0))),"")) | L14: =IF(OR(H14="",K14=""),"",ROUND(H14*(1-INDEX(Risk_Model!$C$38:$C$43,MATCH(K14,Risk_Model!$A$38:$A$43,0))),1)) | M14: =IF(L14="","",INDEX(Risk_Model!$B$30:$B$33,MATCH(L14,Risk_Model!$A$30:$A$33,1)))
C15: =IF(B15="","",IFERROR(INDEX(Assessment!$E$5:$E$2000,MATCH(B15,Assessment!$A$5:$A$2000,0)),"Not found")) | H15: =IF(OR(F15="",G15=""),"",F15*G15) | I15: =IF(H15="","",INDEX(Risk_Model!$B$30:$B$33,MATCH(H15,Risk_Model!$A$30:$A$33,1))) | K15: =IF(B15="","",IFERROR(IF(INDEX(Assessment!$K$5:$K$2000,MATCH(B15,Assessment!$A$5:$A$2000,0))="","",INDEX(Assessment!$K$5:$K$2000,MATCH(B15,Assessment!$A$5:$A$2000,0))),"")) | L15: =IF(OR(H15="",K15=""),"",ROUND(H15*(1-INDEX(Risk_Model!$C$38:$C$43,MATCH(K15,Risk_Model!$A$38:$A$43,0))),1)) | M15: =IF(L15="","",INDEX(Risk_Model!$B$30:$B$33,MATCH(L15,Risk_Model!$A$30:$A$33,1)))
C16: =IF(B16="","",IFERROR(INDEX(Assessment!$E$5:$E$2000,MATCH(B16,Assessment!$A$5:$A$2000,0)),"Not found")) | H16: =IF(OR(F16="",G16=""),"",F16*G16) | I16: =IF(H16="","",INDEX(Risk_Model!$B$30:$B$33,MATCH(H16,Risk_Model!$A$30:$A$33,1))) | K16: =IF(B16="","",IFERROR(IF(INDEX(Assessment!$K$5:$K$2000,MATCH(B16,Assessment!$A$5:$A$2000,0))="","",INDEX(Assessment!$K$5:$K$2000,MATCH(B16,Assessment!$A$5:$A$2000,0))),"")) | L16: =IF(OR(H16="",K16=""),"",ROUND(H16*(1-INDEX(Risk_Model!$C$38:$C$43,MATCH(K16,Risk_Model!$A$38:$A$43,0))),1)) | M16: =IF(L16="","",INDEX(Risk_Model!$B$30:$B$33,MATCH(L16,Risk_Model!$A$30:$A$33,1)))
C17: =IF(B17="","",IFERROR(INDEX(Assessment!$E$5:$E$2000,MATCH(B17,Assessment!$A$5:$A$2000,0)),"Not found")) | H17: =IF(OR(F17="",G17=""),"",F17*G17) | I17: =IF(H17="","",INDEX(Risk_Model!$B$30:$B$33,MATCH(H17,Risk_Model!$A$30:$A$33,1))) | K17: =IF(B17="","",IFERROR(IF(INDEX(Assessment!$K$5:$K$2000,MATCH(B17,Assessment!$A$5:$A$2000,0))="","",INDEX(Assessment!$K$5:$K$2000,MATCH(B17,Assessment!$A$5:$A$2000,0))),"")) | L17: =IF(OR(H17="",K17=""),"",ROUND(H17*(1-INDEX(Risk_Model!$C$38:$C$43,MATCH(K17,Risk_Model!$A$38:$A$43,0))),1)) | M17: =IF(L17="","",INDEX(Risk_Model!$B$30:$B$33,MATCH(L17,Risk_Model!$A$30:$A$33,1)))
... C205: =IF(B205="","",IFERROR(INDEX(Assessment!$E$5:$E$2000,MATCH(B205,Assessment!$A$5:$A$2000,0)),"Not found")) | H205: =IF(OR(F205="",G205=""),"",F205*G205) | I205: =IF(H205="","",INDEX(Risk_Model!$B$30:$B$33,MATCH(H205,Risk_Model!$A$30:$A$33,1))) | K205: =IF(B205="","",IFERROR(IF(INDEX(Assessment!$K$5:$K$2000,MATCH(B205,Assessment!$A$5:$A$2000,0))="","",INDEX(Assessment!$K$5:$K$2000,MATCH(B205,Assessment!$A$5:$A$2000,0))),"")) | L205: =IF(OR(H205="",K205=""),"",ROUND(H205*(1-INDEX(Risk_Model!$C$38:$C$43,MATCH(K205,Risk_Model!$A$38:$A$43,0))),1)) | M205: =IF(L205="","",INDEX(Risk_Model!$B$30:$B$33,MATCH(L205,Risk_Model!$A$30:$A$33,1)))

Sheet Remediation_Tracker
A1: Remediation Tracker
A2: Row 5 is an example. Enter actions from row 6. RAG is calculated from due date and status.
A4: Action ID | B4: Finding ID | C4: Control ID | D4: Severity | E4: Remediation Action | F4: Owner | G4: Priority | H4: Start Date | I4: Due Date | J4: Status | K4: % Complete | L4: Days to Due | M4: RAG | N4: Verification Evidence ID | O4: Notes
A5: EXAMPLE | B5: EXAMPLE | C5: =IF(B5="","",IFERROR(INDEX(Findings_Register!$B$6:$B$205,MATCH(B5,Findings_Register!$A$6:$A$205,0)),"")) | D5: =IF(B5="","",IFERROR(INDEX(Findings_Register!$F$6:$F$205,MATCH(B5,Findings_Register!$A$6:$A$205,0)),"")) | E5: Roll out log forwarder to remaining servers; create silent-source and log-cleared alerts. | F5: Infrastructure Lead | G5: P2 - High | H5: 46307 | I5: 46371 | J5: In Progress | K5: 0.25 | L5: =IF(OR(I5="",J5="Completed",J5="Verified"),"",I5-TODAY()) -> 72 | M5: =IF(OR(J5="Completed",J5="Verified"),"Done",IF(I5="","",IF(TODAY()>I5,"Overdue",IF(I5-TODAY()<=14,"Due within 14d","On track")))) -> On track
C6: =IF(B6="","",IFERROR(INDEX(Findings_Register!$B$6:$B$205,MATCH(B6,Findings_Register!$A$6:$A$205,0)),"")) | D6: =IF(B6="","",IFERROR(INDEX(Findings_Register!$F$6:$F$205,MATCH(B6,Findings_Register!$A$6:$A$205,0)),"")) | L6: =IF(OR(I6="",J6="Completed",J6="Verified"),"",I6-TODAY()) | M6: =IF(OR(J6="Completed",J6="Verified"),"Done",IF(I6="","",IF(TODAY()>I6,"Overdue",IF(I6-TODAY()<=14,"Due within 14d","On track"))))
C7: =IF(B7="","",IFERROR(INDEX(Findings_Register!$B$6:$B$205,MATCH(B7,Findings_Register!$A$6:$A$205,0)),"")) | D7: =IF(B7="","",IFERROR(INDEX(Findings_Register!$F$6:$F$205,MATCH(B7,Findings_Register!$A$6:$A$205,0)),"")) | L7: =IF(OR(I7="",J7="Completed",J7="Verified"),"",I7-TODAY()) | M7: =IF(OR(J7="Completed",J7="Verified"),"Done",IF(I7="","",IF(TODAY()>I7,"Overdue",IF(I7-TODAY()<=14,"Due within 14d","On track"))))
C8: =IF(B8="","",IFERROR(INDEX(Findings_Register!$B$6:$B$205,MATCH(B8,Findings_Register!$A$6:$A$205,0)),"")) | D8: =IF(B8="","",IFERROR(INDEX(Findings_Register!$F$6:$F$205,MATCH(B8,Findings_Register!$A$6:$A$205,0)),"")) | L8: =IF(OR(I8="",J8="Completed",J8="Verified"),"",I8-TODAY()) | M8: =IF(OR(J8="Completed",J8="Verified"),"Done",IF(I8="","",IF(TODAY()>I8,"Overdue",IF(I8-TODAY()<=14,"Due within 14d","On track"))))
C9: =IF(B9="","",IFERROR(INDEX(Findings_Register!$B$6:$B$205,MATCH(B9,Findings_Register!$A$6:$A$205,0)),"")) | D9: =IF(B9="","",IFERROR(INDEX(Findings_Register!$F$6:$F$205,MATCH(B9,Findings_Register!$A$6:$A$205,0)),"")) | L9: =IF(OR(I9="",J9="Completed",J9="Verified"),"",I9-TODAY()) | M9: =IF(OR(J9="Completed",J9="Verified"),"Done",IF(I9="","",IF(TODAY()>I9,"Overdue",IF(I9-TODAY()<=14,"Due within 14d","On track"))))
C10: =IF(B10="","",IFERROR(INDEX(Findings_Register!$B$6:$B$205,MATCH(B10,Findings_Register!$A$6:$A$205,0)),"")) | D10: =IF(B10="","",IFERROR(INDEX(Findings_Register!$F$6:$F$205,MATCH(B10,Findings_Register!$A$6:$A$205,0)),"")) | L10: =IF(OR(I10="",J10="Completed",J10="Verified"),"",I10-TODAY()) | M10: =IF(OR(J10="Completed",J10="Verified"),"Done",IF(I10="","",IF(TODAY()>I10,"Overdue",IF(I10-TODAY()<=14,"Due within 14d","On track"))))
C11: =IF(B11="","",IFERROR(INDEX(Findings_Register!$B$6:$B$205,MATCH(B11,Findings_Register!$A$6:$A$205,0)),"")) | D11: =IF(B11="","",IFERROR(INDEX(Findings_Register!$F$6:$F$205,MATCH(B11,Findings_Register!$A$6:$A$205,0)),"")) | L11: =IF(OR(I11="",J11="Completed",J11="Verified"),"",I11-TODAY()) | M11: =IF(OR(J11="Completed",J11="Verified"),"Done",IF(I11="","",IF(TODAY()>I11,"Overdue",IF(I11-TODAY()<=14,"Due within 14d","On track"))))
C12: =IF(B12="","",IFERROR(INDEX(Findings_Register!$B$6:$B$205,MATCH(B12,Findings_Register!$A$6:$A$205,0)),"")) | D12: =IF(B12="","",IFERROR(INDEX(Findings_Register!$F$6:$F$205,MATCH(B12,Findings_Register!$A$6:$A$205,0)),"")) | L12: =IF(OR(I12="",J12="Completed",J12="Verified"),"",I12-TODAY()) | M12: =IF(OR(J12="Completed",J12="Verified"),"Done",IF(I12="","",IF(TODAY()>I12,"Overdue",IF(I12-TODAY()<=14,"Due within 14d","On track"))))
C13: =IF(B13="","",IFERROR(INDEX(Findings_Register!$B$6:$B$205,MATCH(B13,Findings_Register!$A$6:$A$205,0)),"")) | D13: =IF(B13="","",IFERROR(INDEX(Findings_Register!$F$6:$F$205,MATCH(B13,Findings_Register!$A$6:$A$205,0)),"")) | L13: =IF(OR(I13="",J13="Completed",J13="Verified"),"",I13-TODAY()) | M13: =IF(OR(J13="Completed",J13="Verified"),"Done",IF(I13="","",IF(TODAY()>I13,"Overdue",IF(I13-TODAY()<=14,"Due within 14d","On track"))))
C14: =IF(B14="","",IFERROR(INDEX(Findings_Register!$B$6:$B$205,MATCH(B14,Findings_Register!$A$6:$A$205,0)),"")) | D14: =IF(B14="","",IFERROR(INDEX(Findings_Register!$F$6:$F$205,MATCH(B14,Findings_Register!$A$6:$A$205,0)),"")) | L14: =IF(OR(I14="",J14="Completed",J14="Verified"),"",I14-TODAY()) | M14: =IF(OR(J14="Completed",J14="Verified"),"Done",IF(I14="","",IF(TODAY()>I14,"Overdue",IF(I14-TODAY()<=14,"Due within 14d","On track"))))
C15: =IF(B15="","",IFERROR(INDEX(Findings_Register!$B$6:$B$205,MATCH(B15,Findings_Register!$A$6:$A$205,0)),"")) | D15: =IF(B15="","",IFERROR(INDEX(Findings_Register!$F$6:$F$205,MATCH(B15,Findings_Register!$A$6:$A$205,0)),"")) | L15: =IF(OR(I15="",J15="Completed",J15="Verified"),"",I15-TODAY()) | M15: =IF(OR(J15="Completed",J15="Verified"),"Done",IF(I15="","",IF(TODAY()>I15,"Overdue",IF(I15-TODAY()<=14,"Due within 14d","On track"))))
C16: =IF(B16="","",IFERROR(INDEX(Findings_Register!$B$6:$B$205,MATCH(B16,Findings_Register!$A$6:$A$205,0)),"")) | D16: =IF(B16="","",IFERROR(INDEX(Findings_Register!$F$6:$F$205,MATCH(B16,Findings_Register!$A$6:$A$205,0)),"")) | L16: =IF(OR(I16="",J16="Completed",J16="Verified"),"",I16-TODAY()) | M16: =IF(OR(J16="Completed",J16="Verified"),"Done",IF(I16="","",IF(TODAY()>I16,"Overdue",IF(I16-TODAY()<=14,"Due within 14d","On track"))))
C17: =IF(B17="","",IFERROR(INDEX(Findings_Register!$B$6:$B$205,MATCH(B17,Findings_Register!$A$6:$A$205,0)),"")) | D17: =IF(B17="","",IFERROR(INDEX(Findings_Register!$F$6:$F$205,MATCH(B17,Findings_Register!$A$6:$A$205,0)),"")) | L17: =IF(OR(I17="",J17="Completed",J17="Verified"),"",I17-TODAY()) | M17: =IF(OR(J17="Completed",J17="Verified"),"Done",IF(I17="","",IF(TODAY()>I17,"Overdue",IF(I17-TODAY()<=14,"Due within 14d","On track"))))
... C205: =IF(B205="","",IFERROR(INDEX(Findings_Register!$B$6:$B$205,MATCH(B205,Findings_Register!$A$6:$A$205,0)),"")) | D205: =IF(B205="","",IFERROR(INDEX(Findings_Register!$F$6:$F$205,MATCH(B205,Findings_Register!$A$6:$A$205,0)),"")) | L205: =IF(OR(I205="",J205="Completed",J205="Verified"),"",I205-TODAY()) | M205: =IF(OR(J205="Completed",J205="Verified"),"Done",IF(I205="","",IF(TODAY()>I205,"Overdue",IF(I205-TODAY()<=14,"Due within 14d","On track"))))

Sheet Crown_Jewels
A1: Crown Jewel Assessment
A2: Identify critical assets, their business dependencies and high-value targets. Row 5 is an example. Criticality = highest of C, I, A.
A4: ID | B4: Crown Jewel (asset / service / data) | C4: Business Process Supported | D4: Business Owner | E4: Data Classification | F4: C (1-5) | G4: I (1-5) | H4: A (1-5) | I4: Criticality | J4: RTO | K4: RPO | L4: Upstream Dependencies | M4: Downstream Dependencies | N4: Hosting / Platforms | O4: High-Value Target? | P4: Linked Control IDs / Domains | Q4: Notes
A5: EXAMPLE | B5: Core banking database cluster | C5: Payments and account management | D5: Head of Retail Ops | E5: Restricted | F5: 5 | G5: 5 | H5: 5 | I5: =MAX(F5:H5) -> 5 | J5: 4h | K5: 15m | L5: Active Directory, DNS, SAN storage | M5: Mobile banking, ATM switch | N5: VMware, SQL Server | O5: Yes | P5: SRV-BCK-04, SRV-IAM-07
I6: =IF(F6="","",MAX(F6:H6))
I7: =IF(F7="","",MAX(F7:H7))
I8: =IF(F8="","",MAX(F8:H8))
I9: =IF(F9="","",MAX(F9:H9))
I10: =IF(F10="","",MAX(F10:H10))
I11: =IF(F11="","",MAX(F11:H11))
I12: =IF(F12="","",MAX(F12:H12))
I13: =IF(F13="","",MAX(F13:H13))
I14: =IF(F14="","",MAX(F14:H14))
I15: =IF(F15="","",MAX(F15:H15))
I16: =IF(F16="","",MAX(F16:H16))
I17: =IF(F17="","",MAX(F17:H17))
... I25: =IF(F25="","",MAX(F25:H25))

Sheet Attack_Paths
A1: Attack Path Review
A2: Document realistic paths to crown jewels (External, Internal, Cloud, Identity, Supply Chain). Row 5 is an example.
A4: Path ID | B4: Category | C4: Target Crown Jewel ID | D4: Entry Point | E4: Attack Path Narrative (steps) | F4: ATT&CK Techniques | G4: Enabling Weaknesses (Control / Finding IDs) | H4: Existing Detection | I4: Likelihood (1-5) | J4: Impact (1-5) | K4: Path Risk Score | L4: Rating | M4: Recommended Chokepoints | N4: Owner | O4: Status
A5: EXAMPLE | B5: Identity | C5: EXAMPLE | D5: Phished helpdesk account | E5: 1) Phish helpdesk user. 2) Reuse shared local admin password across servers. 3) Reach backup server joined to production domain. 4) Delete restore points and deploy ransomware. | F5: T1078, T1550, T1490, T1486 | G5: SRV-IAM-07, SRV-BCK-06, SRV-BCK-04 | H5: EDR alerts only on final stage | I5: 4 | J5: 5 | K5: =I5*J5 -> 20 | L5: =INDEX(Risk_Model!$B$30:$B$33,MATCH(K5,Risk_Model!$A$30:$A$33,1)) -> Critical | M5: Deploy LAPS; isolate backup identity plane; add immutable copy. | N5: CISO | O5: Open
K6: =IF(OR(I6="",J6=""),"",I6*J6) | L6: =IF(K6="","",INDEX(Risk_Model!$B$30:$B$33,MATCH(K6,Risk_Model!$A$30:$A$33,1)))
K7: =IF(OR(I7="",J7=""),"",I7*J7) | L7: =IF(K7="","",INDEX(Risk_Model!$B$30:$B$33,MATCH(K7,Risk_Model!$A$30:$A$33,1)))
K8: =IF(OR(I8="",J8=""),"",I8*J8) | L8: =IF(K8="","",INDEX(Risk_Model!$B$30:$B$33,MATCH(K8,Risk_Model!$A$30:$A$33,1)))
K9: =IF(OR(I9="",J9=""),"",I9*J9) | L9: =IF(K9="","",INDEX(Risk_Model!$B$30:$B$33,MATCH(K9,Risk_Model!$A$30:$A$33,1)))
K10: =IF(OR(I10="",J10=""),"",I10*J10) | L10: =IF(K10="","",INDEX(Risk_Model!$B$30:$B$33,MATCH(K10,Risk_Model!$A$30:$A$33,1)))
K11: =IF(OR(I11="",J11=""),"",I11*J11) | L11: =IF(K11="","",INDEX(Risk_Model!$B$30:$B$33,MATCH(K11,Risk_Model!$A$30:$A$33,1)))
K12: =IF(OR(I12="",J12=""),"",I12*J12) | L12: =IF(K12="","",INDEX(Risk_Model!$B$30:$B$33,MATCH(K12,Risk_Model!$A$30:$A$33,1)))
K13: =IF(OR(I13="",J13=""),"",I13*J13) | L13: =IF(K13="","",INDEX(Risk_Model!$B$30:$B$33,MATCH(K13,Risk_Model!$A$30:$A$33,1)))
K14: =IF(OR(I14="",J14=""),"",I14*J14) | L14: =IF(K14="","",INDEX(Risk_Model!$B$30:$B$33,MATCH(K14,Risk_Model!$A$30:$A$33,1)))
K15: =IF(OR(I15="",J15=""),"",I15*J15) | L15: =IF(K15="","",INDEX(Risk_Model!$B$30:$B$33,MATCH(K15,Risk_Model!$A$30:$A$33,1)))
K16: =IF(OR(I16="",J16=""),"",I16*J16) | L16: =IF(K16="","",INDEX(Risk_Model!$B$30:$B$33,MATCH(K16,Risk_Model!$A$30:$A$33,1)))
K17: =IF(OR(I17="",J17=""),"",I17*J17) | L17: =IF(K17="","",INDEX(Risk_Model!$B$30:$B$33,MATCH(K17,Risk_Model!$A$30:$A$33,1)))
... K25: =IF(OR(I25="",J25=""),"",I25*J25) | L25: =IF(K25="","",INDEX(Risk_Model!$B$30:$B$33,MATCH(K25,Risk_Model!$A$30:$A$33,1)))

Sheet Control_Library
A1: Master Control Library
A2: 60 controls. Source of truth is the YAML library; this sheet is generated. Do not edit here - edit the YAML and rebuild.
A4: Control ID | B4: Domain | C4: Control Family | D4: Control Name | E4: Platform | F4: Objective | G4: Business Justification | H4: Threat Prevented | I4: Assessment Question | J4: Control Type | K4: Evidence Required | L4: Validation Procedure | M4: Interview | N4: Document Review | O4: Configuration Review | P4: Observation | Q4: Technical Validation | R4: Automated Validation | S4: Penetration Validation | T4: Automation Possibility | U4: Automation Method | V4: Default Likelihood (1-5) | W4: Default Impact (1-5) | X4: Inherent Score | Y4: Risk Rating | Z4: Criticality Weight (1-3) | AA4: Maturity Anchor L1 (Initial) | AB4: Maturity Anchor L3 (Defined) | AC4: Maturity Anchor L5 (Optimized) | AD4: Remediation Guidance | AE4: References | AF4: Framework Mapping (summary) | AG4: Checklist Origin
A5: SRV-PHY-01 | B5: Server Security | C5: Physical and Environmental Security | D5: Physical access to servers is restricted and logged | E5: All | F5: Prevent unauthorised physical access to server hardware, consoles and storage. | G5: Physical access bypasses most logical controls and can lead to data theft, tampering or prolonged outage. | H5: Hardware tampering, console and boot-media attacks, drive theft, rogue device insertion. | I5: Are servers housed in locked racks or access-controlled rooms, with access limited to authorised staff and logged? | J5: Preventive | K5: - Authorised access list - badge and visitor logs (90 days) - CCTV coverage evidence - photos of rack locks - physical security policy - colocation contract and assurance report if hosted | L5: 1. Interview the facilities owner and obtain the authorised-access list. 2. Walk the server room: check rack locks, door controls, cameras and visitor escort practice. 3. Sample 10 names on the list against HR leavers and job roles; review badge logs for after-hours entry. 4. For hosted or colocation sites, obtain the provider SOC 2 Type II or ISO 27001 certificate and confirm physical controls are in scope. | M5: ● | N5: ● | P5: ● | T5: Low | U5: Badge-system export compared with the HR leaver list (CSV reconciliation). | V5: 2 | W5: 5 | X5: =V5*W5 -> 10 | Y5: =INDEX(Risk_Model!$B$30:$B$33,MATCH(X5,Risk_Model!$A$30:$A$33,1)) -> High | Z5: 2 | AA5: Servers sit in open or shared areas; access is ad hoc and unlogged. | AB5: Locked room or racks, documented access list, logs retained and reviewed annually. | AC5: Multi-factor physical entry, CCTV with retention, quarterly access recertification, automated leaver revocation and anomaly alerts. | AD5: Move servers into locked racks or rooms, define the authorised list, enable badge logging and CCTV, and recertify access at least quarterly for sensitive sites. | AE5: NIST SP 800-53 Rev.5 PE family; ISO/IEC 27002:2022 clause 7; NIST SP 800-88 Rev.1 (media sanitization); vendor hardware hardening guides | AF5: ISO 27001:2022 A.7.1, A.7.2, A.7.4, A.7.6; NIST CSF 2.0 PR.AA-06; CIS v8.1 N/A; SOC 2 CC6.4 | AG5: 1.1
A6: SRV-PHY-02 | B6: Server Security | C6: Physical and Environmental Security | D6: Out-of-band management interfaces are isolated and hardened | E6: All | F6: Ensure BMC, iDRAC, iLO, IPMI and KVM-over-IP interfaces cannot be used to take over servers. | G6: A compromised BMC gives console, power and virtual-media control that sits below the operating system and its security tooling. | H6: BMC firmware and IPMI protocol exploitation, default credentials, firmware implants, remote console takeover. | I6: Are out-of-band management interfaces on a dedicated management network, patched, with default credentials changed and strong authentication enforced? | J6: Preventive | K6: - Management network diagram - BMC inventory with firmware versions - firewall rules for the management VLAN - BMC user list and authentication settings | L6: From an authorised host on the management VLAN, discover IPMI exposure with `nmap -sU -p 623 --script ipmi-version <mgmt-subnet>` and confirm IPMI-over-LAN is disabled or restricted. Review BMC accounts, TLS certificate and firmware date in the web console or via Redfish (`curl -k -u <user> https://<bmc>/redfish/v1/Managers`). Confirm the BMC subnet is unreachable from user and internet segments (`nc -vz <bmc-ip> 443` from a user VLAN should fail). | M6: ● | O6: ● | Q6: ● | T6: Medium | U6: Redfish API inventory of firmware versions and accounts; vendor tools (OpenManage, iLO RESTful API). | V6: 3 | W6: 5 | X6: =V6*W6 -> 15 | Y6: =INDEX(Risk_Model!$B$30:$B$33,MATCH(X6,Risk_Model!$A$30:$A$33,1)) -> High | Z6: 3 | AA6: BMCs reachable from the production LAN with default credentials. | AB6: Dedicated management VLAN, unique credentials, firmware versions tracked. | AC6: Access only via MFA jump host, Redfish-driven firmware compliance, IPMI-over-LAN disabled, BMC configuration baselined and monitored. | AD6: Move BMCs to an isolated management network, change all default credentials, disable IPMI-over-LAN or restrict it, patch firmware, and require access through a hardened jump host. | AE6: NIST SP 800-53 Rev.5 PE family; ISO/IEC 27002:2022 clause 7; NIST SP 800-88 Rev.1 (media sanitization); vendor hardware hardening guides | AF6: ISO 27001:2022 A.8.9, A.8.20, A.8.22; NIST CSF 2.0 PR.IR-01, PR.PS-01; CIS v8.1 4.6, 12.2; SOC 2 CC6.1, CC6.6 | AG6: New
A7: SRV-PHY-03 | B7: Server Security | C7: Physical and Environmental Security | D7: Removable media and unused ports are controlled | E7: All | F7: Reduce the risk of malware introduction and data removal through USB, optical, serial and console ports. | G7: Removable media remains a path for malware delivery and unmonitored data exfiltration from servers. | H7: Malware via removable media, boot from unauthorised media, data exfiltration. | I7: Are USB and removable-media ports, unused console ports and boot-from-removable options disabled or controlled on servers? | J7: Preventive | K7: - GPO, MDM, udev or USBGuard configuration - BIOS/UEFI boot-order settings - media handling policy - exception register | L7: Windows: `reg query HKLM\SYSTEM\CurrentControlSet\Services\USBSTOR /v Start` (value 4 means disabled) and review the GPO "Removable Storage Access". Linux: `lsmod | grep usb_storage`, `systemctl status usbguard`, `grep -r usb-storage /etc/modprobe.d/`. Review UEFI boot order and boot-device password settings for a sample of physical servers. | O7: ● | P7: ● | Q7: ● | T7: Medium | U7: GPO or Intune export; Ansible or OpenSCAP check for a blacklisted usb-storage module. | V7: 2 | W7: 4 | X7: =V7*W7 -> 8 | Y7: =INDEX(Risk_Model!$B$30:$B$33,MATCH(X7,Risk_Model!$A$30:$A$33,1)) -> Medium | Z7: 1 | AA7: Ports and boot options are open on all servers. | AB7: Removable storage blocked by policy, boot order locked, exceptions approved. | AC7: Device control enforced by EDR with alerts on blocked attempts, quarterly exception review. | AD7: Block removable storage by policy, lock boot order with a firmware password, and use EDR device control with alerting where USB access is needed. | AE7: NIST SP 800-53 Rev.5 PE family; ISO/IEC 27002:2022 clause 7; NIST SP 800-88 Rev.1 (media sanitization); vendor hardware hardening guides | AF7: ISO 27001:2022 A.7.10, A.8.9; NIST CSF 2.0 PR.PS-01; CIS v8.1 4.8, 10.3; SOC 2 CC6.7 | AG7: New
A8: SRV-PHY-04 | B8: Server Security | C8: Physical and Environmental Security | D8: Storage media is sanitised or destroyed before replacement and disposal | E8: All | F8: Ensure data cannot be recovered from storage devices that are replaced, returned, re-used or retired. | G8: Discarded drives and vendor returns are a recurring source of confidential data exposure and regulatory breaches. | H8: Data recovery from discarded drives, leakage through vendor RMA returns. | I8: Is media containing confidential data sanitised to a recognised standard or destroyed, with certificates retained, before leaving the organisation or being re-used? | J8: Preventive | K8: - Media disposal procedure - certificates of destruction - asset disposal log - RMA records - encryption-at-rest evidence for returned drives | L8: Sample 5 retired or RMA-returned servers from the asset register and trace each to a sanitisation record or destruction certificate. Confirm the sanitisation method meets NIST SP 800-88 (clear, purge or destroy) and that crypto-erase is evidenced where self-encrypting drives are used. Review vendor contracts for media retention or "keep your drive" clauses. | M8: ● | N8: ● | T8: Low | U8: ITAM workflow that blocks asset closure without an attached sanitisation certificate. | V8: 2 | W8: 4 | X8: =V8*W8 -> 8 | Y8: =INDEX(Risk_Model!$B$30:$B$33,MATCH(X8,Risk_Model!$A$30:$A$33,1)) -> Medium | Z8: 2 | AA8: Drives are discarded or returned without a defined process. | AB8: Documented sanitisation standard, certificates retained for most disposals. | AC8: Full-disk encryption plus crypto-erase on every retirement, automated closure checks, periodic vendor audits. | AD8: Adopt a media sanitisation standard aligned to NIST SP 800-88, require certificates for every disposal, and add contract clauses for vendor-held media. | AE8: NIST SP 800-53 Rev.5 PE family; ISO/IEC 27002:2022 clause 7; NIST SP 800-88 Rev.1 (media sanitization); vendor hardware hardening guides | AF8: ISO 27001:2022 A.7.14, A.7.10, A.8.10; NIST CSF 2.0 ID.AM-08, PR.DS-01; CIS v8.1 3.5; SOC 2 CC6.5 | AG8: 11.1
A9: SRV-CFG-01 | B9: Server Security | C9: Secure Configuration and Change | D9: Secure configuration baselines are defined for every server platform | E9: All | F9: Ensure servers are built to an approved, hardened and documented configuration. | G9: Insecure defaults and inconsistent builds are a leading cause of avoidable compromise and audit findings. | H9: Exploitation of insecure defaults and misconfiguration. | I9: Is there an approved hardening baseline (for example CIS Benchmark level) for each server OS and role, and is it applied at build? | J9: Preventive | K9: - Baseline standard per OS - golden image or build pipeline definitions (Packer, MDT, Ansible, Terraform) - sample build checklist - exceptions register | L9: Obtain baselines and confirm they track a current CIS Benchmark or Microsoft security baseline version. Sample 5 servers and measure compliance. Windows: Microsoft Security Compliance Toolkit (Policy Analyzer) or CIS-CAT. Linux: `oscap xccdf eval --profile <cis-profile> --report out.html <ssg-datastream>` or `lynis audit system`. Record the percentage of controls passed and review the exceptions register for approval and expiry. | N9: ● | O9: ● | Q9: ● | R9: ● | T9: High | U9: OpenSCAP, CIS-CAT or Lynis scheduled scans; Microsoft Defender for Cloud or Intune configuration assessment; Ansible check mode. | V9: 4 | W9: 4 | X9: =V9*W9 -> 16 | Y9: =INDEX(Risk_Model!$B$30:$B$33,MATCH(X9,Risk_Model!$A$30:$A$33,1)) -> High | Z9: 3 | AA9: Servers are built manually from the vendor defaults. | AB9: Documented baselines per platform applied through build scripts, exceptions approved. | AC9: Baselines versioned as code, continuously assessed with automated compliance scoring, drift auto-remediated. | AD9: Adopt a CIS or vendor baseline per platform, encode it in build automation, and track exceptions with expiry dates. | AE9: CIS Benchmarks (Windows Server, RHEL, Ubuntu); Microsoft Security Baselines; DISA STIGs; NIST SP 800-123; NIST SP 800-70 | AF9: ISO 27001:2022 A.8.9; NIST CSF 2.0 PR.PS-01; CIS v8.1 4.1; SOC 2 CC5.2, CC7.1 | AG9: New
A10: SRV-CFG-02 | B10: Server Security | C10: Secure Configuration and Change | D10: Configuration drift from the baseline is detected and corrected | E10: All | F10: Detect and remediate deviations from approved configurations in a timely way. | G10: Unmanaged drift silently erodes hardening and can mask malicious modification. | H10: Gradual misconfiguration, unauthorised changes, attacker persistence settings left unnoticed. | I10: Is compliance with the baseline continuously or periodically assessed, with deviations tracked to closure? | J10: Detective | K10: - Compliance scan reports (last 3 cycles) - remediation tickets - scan schedule - compliance dashboards | L10: Obtain the latest compliance scan and trend. Windows: `Get-DscConfigurationStatus` if DSC is used, or the Intune and Defender for Endpoint secure configuration export. Linux: `ansible-playbook site.yml --check --diff` or `aide --check`. Select 3 failed items and verify each has an owner, a ticket and a remediation date. | N10: ● | Q10: ● | R10: ● | T10: High | U10: Scheduled OpenSCAP, Ansible check mode, Intune compliance reports, Defender for Cloud recommendations. | V10: 3 | W10: 3 | X10: =V10*W10 -> 9 | Y10: =INDEX(Risk_Model!$B$30:$B$33,MATCH(X10,Risk_Model!$A$30:$A$33,1)) -> Medium | Z10: 2 | AA10: No drift checks; configuration is reviewed only after incidents. | AB10: Periodic compliance scans with tracked remediation. | AC10: Continuous drift detection with automatic reversion and compliance trend reporting to management. | AD10: Schedule automated baseline scans, route failures to owners via tickets, and auto-remediate low-risk drift. | AE10: CIS Benchmarks (Windows Server, RHEL, Ubuntu); Microsoft Security Baselines; DISA STIGs; NIST SP 800-123; NIST SP 800-70 | AF10: ISO 27001:2022 A.8.9, A.8.16; NIST CSF 2.0 PR.PS-01, DE.CM-09; CIS v8.1 4.1; SOC 2 CC7.1 | AG10: New
A11: SRV-CFG-03 | B11: Server Security | C11: Secure Configuration and Change | D11: Unnecessary services, roles, features and ports are disabled or removed | E11: All | F11: Minimise attack surface by running only what each server role requires. | G11: Every unneeded service is an additional vulnerability and monitoring burden. | H11: Exploitation of unused or legacy services (SMBv1, telnet, FTP, print spooler on non-print servers). | I11: Are all services, roles, features, protocols and listening ports not required by the server role disabled or removed? | J11: Preventive | K11: - Service and role inventory per server - listening-port list - change records for removals - scan results | L11: Windows: `Get-WindowsFeature | where Installed`, `Get-Service | where Status -eq Running`, `Get-NetTCPConnection -State Listen`, `Get-SmbServerConfiguration | select EnableSMB1Protocol`. Linux: `systemctl list-unit-files --state=enabled`, `ss -tulpn`, and check for telnet, rsh and ftp packages with `rpm -qa` or `dpkg -l`. Compare results with the documented role requirement and record unexplained services. | O11: ● | Q11: ● | R11: ● | T11: High | U11: osquery (listening_ports, services tables), Ansible facts, scheduled Nmap scans. | V11: 3 | W11: 4 | X11: =V11*W11 -> 12 | Y11: =INDEX(Risk_Model!$B$30:$B$33,MATCH(X11,Risk_Model!$A$30:$A$33,1)) -> High | Z11: 3 | AA11: Default installs with all services enabled. | AB11: Role-based builds with documented service lists; periodic review. | AC11: Minimal images, automated detection of unauthorised services and ports with alerts. | AD11: Build from minimal images, remove or disable unneeded services, and alert on newly listening ports. | AE11: CIS Benchmarks (Windows Server, RHEL, Ubuntu); Microsoft Security Baselines; DISA STIGs; NIST SP 800-123; NIST SP 800-70 | AF11: ISO 27001:2022 A.8.9, A.8.19; NIST CSF 2.0 PR.PS-01; CIS v8.1 4.8; SOC 2 CC6.1, CC6.6 | AG11: 4.3
A12: SRV-CFG-04 | B12: Server Security | C12: Secure Configuration and Change | D12: An approved authorised-use banner is displayed at login | E12: All | F12: Establish a legal notice of authorised use at every administrative login interface. | G12: A banner supports lawful monitoring and enforcement and is commonly required by regulators and insurers. | H12: Disputed unauthorised-access enforcement and claims of implied consent. | I12: Do servers display a legally approved authorised-use notice at console, SSH, RDP and web administration logins? | J12: Preventive | K12: - Legal-approved banner text - screenshots of console, SSH and RDP logins - GPO or sshd configuration - exception list | L12: Windows: `reg query "HKLM\SOFTWARE\Microsoft\Windows\CurrentVersion\Policies\System" /v legalnoticetext`. Linux: `sshd -T | grep -i banner` and `cat /etc/issue /etc/issue.net`. Attempt a login to confirm the banner appears and record any interface where it is technically impossible. | O12: ● | P12: ● | Q12: ● | T12: High | U12: GPO export or Ansible lineinfile check. | V12: 1 | W12: 2 | X12: =V12*W12 -> 2 | Y12: =INDEX(Risk_Model!$B$30:$B$33,MATCH(X12,Risk_Model!$A$30:$A$33,1)) -> Low | Z12: 1 | AA12: No banner configured. | AB12: Legal-approved banner deployed to all administrative interfaces. | AC12: Banner enforced as code with drift alerts and annual legal review. | AD12: Obtain legal-approved wording and deploy it by GPO or configuration management to all login interfaces. | AE12: CIS Benchmarks (Windows Server, RHEL, Ubuntu); Microsoft Security Baselines; DISA STIGs; NIST SP 800-123; NIST SP 800-70 | AF12: ISO 27001:2022 A.5.10, A.8.5; NIST CSF 2.0 GV.PO-01; CIS v8.1 N/A; SOC 2 CC6.1 | AG12: 1.4
A13: SRV-CFG-05 | B13: Server Security | C13: Secure Configuration and Change | D13: Boot chain integrity protections are enabled | E13: All | F13: Ensure the server only boots trusted firmware and operating system components. | G13: Bootkits and firmware implants survive reinstallation and evade operating-system security tools. | H13: Bootkits, firmware implants, boot from unauthorised media. | I13: Are Secure Boot, a UEFI/BIOS administrator password, TPM-backed measured boot and restricted boot order enabled on physical and virtual servers where supported? | J13: Preventive | K13: - UEFI settings exports or screenshots - Secure Boot and TPM status output - virtual machine firmware settings - exception list | L13: Windows: `Confirm-SecureBootUEFI`, `Get-Tpm`, and msinfo32 (BIOS Mode UEFI, Secure Boot State On). Linux: `mokutil --sb-state`, `ls /sys/firmware/efi`, and `tpm2_pcrread` where tpm2-tools is installed. Hyper-V guests: `Get-VMFirmware -VMName <vm> | select SecureBoot`. List legacy-BIOS machines as exceptions. | O13: ● | Q13: ● | R13: ● | T13: Medium | U13: Defender for Endpoint or Intune device health attestation; osquery secureboot table; Redfish BIOS attributes. | V13: 2 | W13: 4 | X13: =V13*W13 -> 8 | Y13: =INDEX(Risk_Model!$B$30:$B$33,MATCH(X13,Risk_Model!$A$30:$A$33,1)) -> Medium | Z13: 2 | AA13: Legacy BIOS boot with no firmware protection. | AB13: Secure Boot and firmware password on most servers, exceptions documented. | AC13: Measured boot with remote attestation and firmware settings monitored for change. | AD13: Convert to UEFI, enable Secure Boot and TPM, set firmware passwords, and restrict boot devices. | AE13: CIS Benchmarks (Windows Server, RHEL, Ubuntu); Microsoft Security Baselines; DISA STIGs; NIST SP 800-123; NIST SP 800-70 | AF13: ISO 27001:2022 A.8.9; NIST CSF 2.0 PR.PS-01, PR.DS-06; CIS v8.1 4.1; SOC 2 CC6.8 | AG13: 4.1, 4.7
A14: SRV-CFG-06 | B14: Server Security | C14: Secure Configuration and Change | D14: Server configuration changes follow documented change control | E14: All | F14: Ensure changes are assessed, approved, tested and traceable. | G14: Uncontrolled change causes outages and security regressions, and obscures malicious modification. | H14: Unauthorised or untested changes, concealed malicious changes. | I14: Is there a documented change process for server configuration (request, risk review, approval, test, rollback, post-change review) and is it followed? | J14: Preventive | K14: - Change management policy - sample of 10 change tickets - CAB minutes - emergency change log - configuration repository history | L14: Sample 10 recent system changes from the configuration repository or logs and trace each to an approved ticket (target 90% match or better). Windows: `Get-WinEvent -FilterHashtable @{LogName='Security';Id=4719}` (audit policy changes). Linux: `ausearch -k config_change`, `dnf history` or `/var/log/dpkg.log`. Review emergency changes for after-the-fact approval. | M14: ● | N14: ● | Q14: ● | T14: Medium | U14: ITSM-to-CMDB reconciliation; Ansible Tower/AWX job logs; mandatory ticket reference in Git commits. | V14: 3 | W14: 3 | X14: =V14*W14 -> 9 | Y14: =INDEX(Risk_Model!$B$30:$B$33,MATCH(X14,Risk_Model!$A$30:$A$33,1)) -> Medium | Z14: 2 | AA14: Changes made ad hoc by administrators. | AB14: Documented process with approval and testing; sampled evidence of compliance. | AC14: Pipeline-enforced change with automatic ticket linkage, metrics, and unauthorised-change alerting. | AD14: Implement a change process with risk-based approval, rollback plans and automated reconciliation of detected changes to tickets. | AE14: CIS Benchmarks (Windows Server, RHEL, Ubuntu); Microsoft Security Baselines; DISA STIGs; NIST SP 800-123; NIST SP 800-70 | AF14: ISO 27001:2022 A.8.32, A.8.9; NIST CSF 2.0 PR.PS-01; CIS v8.1 4.1; SOC 2 CC8.1 | AG14: 4.2
A15: SRV-CFG-07 | B15: Server Security | C15: Secure Configuration and Change | D15: Only authorised software can execute or be installed on servers | E15: All | F15: Prevent execution of unapproved binaries and scripts. | G15: Application allow-listing blocks the majority of commodity malware and living-off-the-land tooling. | H15: Ransomware and malware execution, attacker tooling, unauthorised software. | I15: Is application allow-listing or equivalent execution control enforced on servers, and is software installation restricted to approved administrators and sources? | J15: Preventive | K15: - AppLocker or WDAC policy export - fapolicyd or SELinux/AppArmor configuration - software inventory against approved list - audit-mode results | L15: Windows: `Get-AppLockerPolicy -Effective -Xml` and `Get-CimInstance -ClassName Win32_DeviceGuard -Namespace root\Microsoft\Windows\DeviceGuard` (code integrity enforcement status). Linux: `systemctl status fapolicyd`, `getenforce` or `aa-status`. Compare the software inventory with the approved list and confirm policies are in enforce mode, not audit. | O15: ● | Q15: ● | R15: ● | T15: Medium | U15: Intune or GPO policy export; osquery programs table; EDR application control reports. | V15: 3 | W15: 4 | X15: =V15*W15 -> 12 | Y15: =INDEX(Risk_Model!$B$30:$B$33,MATCH(X15,Risk_Model!$A$30:$A$33,1)) -> High | Z15: 2 | AA15: Any software can be installed or run. | AB15: Allow-listing enforced for critical servers, installs restricted. | AC15: Enforced allow-listing on all servers with managed exception workflow and violation alerting. | AD15: Deploy WDAC/AppLocker or fapolicyd in audit mode, tune, then enforce; restrict installation rights. | AE15: CIS Benchmarks (Windows Server, RHEL, Ubuntu); Microsoft Security Baselines; DISA STIGs; NIST SP 800-123; NIST SP 800-70 | AF15: ISO 27001:2022 A.8.19, A.8.7; NIST CSF 2.0 PR.PS-05; CIS v8.1 2.3, 2.5; SOC 2 CC6.8 | AG15: New
A16: SRV-PAT-01 | B16: Server Security | C16: Patch and Lifecycle Management | D16: A documented patch management process with risk-based timelines exists | E16: All | F16: Ensure operating systems, applications and firmware are patched within defined timeframes. | G16: Known unpatched vulnerabilities remain the most common route to server compromise and ransomware. | H16: Exploitation of known vulnerabilities. | I16: Is there a documented patch process defining roles, schedules, severity-based timelines, testing, exceptions and coverage of OS, applications and firmware? | J16: Preventive | K16: - Patch policy or standard - patch calendar - timeline (SLA) table - records from two recent patch cycles - exception log | L16: Review the policy for timelines by severity and exploitation status, and for coverage of third-party applications, firmware and hypervisors. Sample the last two patch cycles: scope versus asset inventory, approvals, test evidence and deployment rate. Confirm where the process is documented and who owns it. | M16: ● | N16: ● | Q16: ● | T16: High | U16: WSUS, Intune, Update Manager or Red Hat Satellite compliance exports via API. | V16: 4 | W16: 5 | X16: =V16*W16 -> 20 | Y16: =INDEX(Risk_Model!$B$30:$B$33,MATCH(X16,Risk_Model!$A$30:$A$33,1)) -> Critical | Z16: 3 | AA16: Patching is ad hoc and left to individual administrators. | AB16: Documented process and calendar, timelines defined, most servers patched in time. | AC16: Automated patching with measured timelines, exception governance and threat-led acceleration. | AD16: Define severity and exploitability-based patch timelines, assign ownership, and automate deployment with compliance reporting. | AE16: NIST SP 800-40 Rev.4; CISA Known Exploited Vulnerabilities catalog; vendor lifecycle and support policies | AF16: ISO 27001:2022 A.8.8, A.5.37; NIST CSF 2.0 ID.RA-01, PR.PS-02; CIS v8.1 7.3, 7.4; SOC 2 CC7.1 | AG16: 2.1, 2.3, 2.4
A17: SRV-PAT-02 | B17: Server Security | C17: Patch and Lifecycle Management | D17: Patch currency is verified per server and installation failures are resolved | E17: All | F17: Know the real patch level of each server and detect failed or pending installations. | G17: Reported patch compliance often overstates reality when failures and pending reboots go unnoticed. | H17: Unpatched systems believed to be compliant. | I17: Can the organisation show the current patch level per server, and are failed or pending installations detected and resolved? | J17: Detective | K17: - Patch compliance report - failed-installation report - tickets for failures - pending-reboot report | L17: Windows: `Get-HotFix | sort InstalledOn -Descending | select -First 10`; pending reboot via registry key `HKLM:\SOFTWARE\Microsoft\Windows\CurrentVersion\Component Based Servicing\RebootPending`. Linux: `apt list --upgradable` or `dnf updateinfo list security`; `needs-restarting -r` or `/var/run/reboot-required`. Compare results with the console report and timelines; sample failed installs against tickets. | O17: ● | Q17: ● | R17: ● | T17: High | U17: Patch console exports, Defender TVM, Nessus credentialed patch audit plugins. | V17: 4 | W17: 4 | X17: =V17*W17 -> 16 | Y17: =INDEX(Risk_Model!$B$30:$B$33,MATCH(X17,Risk_Model!$A$30:$A$33,1)) -> High | Z17: 3 | AA17: Patch level is unknown outside manual checks. | AB17: Per-server patch inventory with failure monitoring. | AC17: Automated reconciliation of console data and scanner results, failures auto-ticketed. | AD17: Reconcile patch tooling reports against credentialed scans, auto-ticket failures, and track pending reboots. | AE17: NIST SP 800-40 Rev.4; CISA Known Exploited Vulnerabilities catalog; vendor lifecycle and support policies | AF17: ISO 27001:2022 A.8.8; NIST CSF 2.0 ID.RA-01, PR.PS-02; CIS v8.1 7.3, 7.4, 7.7; SOC 2 CC7.1 | AG17: 2.5, 2.6
A18: SRV-PAT-03 | B18: Server Security | C18: Patch and Lifecycle Management | D18: Unsupported and end-of-life systems are governed through approved exceptions | E18: All | F18: Prevent unsupported platforms from running without compensating controls and a retirement plan. | G18: End-of-life systems receive no security fixes and are routinely used for initial access and lateral movement. | H18: Unpatchable vulnerabilities in end-of-life operating systems and applications. | I18: Are operating systems and applications beyond vendor support identified and either removed, isolated, or covered by a time-bound, risk-accepted exception with compensating controls? | J18: Preventive | K18: - End-of-life inventory with dates - exception register with approvals and expiry - compensating-control evidence - migration roadmap | L18: Windows: `Get-CimInstance Win32_OperatingSystem | select Caption,Version`. Linux: `cat /etc/os-release`. Compare every server against the vendor lifecycle (vendor pages or endoflife.date), for example Windows Server 2012 R2 or CentOS 7. For each end-of-life host, verify an approved exception, an expiry date, and isolation or monitoring as compensating controls. | N18: ● | Q18: ● | R18: ● | T18: High | U18: CMDB lifecycle fields plus scanner "unsupported operating system" findings. | V18: 4 | W18: 5 | X18: =V18*W18 -> 20 | Y18: =INDEX(Risk_Model!$B$30:$B$33,MATCH(X18,Risk_Model!$A$30:$A$33,1)) -> Critical | Z18: 3 | AA18: Unsupported systems are unknown or unmanaged. | AB18: Inventory of end-of-life systems with approved, dated exceptions. | AC18: Lifecycle-driven roadmap, no unmanaged end-of-life systems, automatic alerts ahead of support end. | AD18: Inventory support dates, migrate or isolate end-of-life hosts, and require time-bound exceptions signed by the risk owner. | AE18: NIST SP 800-40 Rev.4; CISA Known Exploited Vulnerabilities catalog; vendor lifecycle and support policies | AF18: ISO 27001:2022 A.8.8, A.5.9; NIST CSF 2.0 ID.AM-08, PR.PS-02; CIS v8.1 2.2; SOC 2 CC7.1 | AG18: 2.2
A19: SRV-PAT-04 | B19: Server Security | C19: Patch and Lifecycle Management | D19: Emergency patching exists for actively exploited and critical vulnerabilities | E19: All | F19: Compress time-to-remediate for vulnerabilities with known exploitation. | G19: Exploits are often weaponised within days of disclosure; routine cycles are too slow for these cases. | H19: Rapid exploitation of newly disclosed vulnerabilities. | I19: Is there a tested fast-track process for actively exploited or critical vulnerabilities (including CISA KEV entries), with timelines that are measured and met? | J19: Corrective | K19: - Emergency patch procedure - threat-intelligence or KEV subscription - last 3 emergency events with timelines - time-to-patch metrics | L19: Select 3 recent KEV or critical CVEs affecting the estate and measure disclosure-to-remediation time per server. Compare with the target. The source checklist required remediation of CVSS 7 or higher within one business day; this framework recommends risk-based targets (for example internet-facing KEV within 72 hours). Verify mitigations for systems that cannot be patched immediately. | M19: ● | N19: ● | Q19: ● | T19: Medium | U19: KEV feed correlated with scanner or Defender TVM asset data. | V19: 4 | W19: 5 | X19: =V19*W19 -> 20 | Y19: =INDEX(Risk_Model!$B$30:$B$33,MATCH(X19,Risk_Model!$A$30:$A$33,1)) -> Critical | Z19: 3 | AA19: No emergency process; critical patches wait for the monthly cycle. | AB19: Defined fast-track with owners; usually met for internet-facing systems. | AC19: Threat-intel triggered automation with measured, consistently met targets. | AD19: Subscribe to KEV and vendor advisories, define emergency timelines by exposure, and rehearse the process. | AE19: NIST SP 800-40 Rev.4; CISA Known Exploited Vulnerabilities catalog; vendor lifecycle and support policies | AF19: ISO 27001:2022 A.8.8, A.5.7; NIST CSF 2.0 ID.RA-01, ID.RA-02; CIS v8.1 7.7; SOC 2 CC7.1 | AG19: 5.6
A20: SRV-PAT-05 | B20: Server Security | C20: Patch and Lifecycle Management | D20: Firmware and hypervisor layers are inventoried and patched | E20: All | F20: Keep BIOS/UEFI, BMC, controller, NIC firmware and hypervisor builds current. | G20: Firmware and hypervisor flaws affect every workload above them and are often missed by OS patching. | H20: Firmware implants, hypervisor escape and ESXi-targeting ransomware exploits. | I20: Are firmware and hypervisor versions inventoried and patched on a managed cadence? | J20: Preventive | K20: - Firmware inventory (OpenManage, iLO, Redfish) - hypervisor build numbers versus vendor advisories - firmware change tickets | L20: VMware: `Get-VMHost | select Name,Version,Build` (PowerCLI). Hyper-V: `Get-ComputerInfo`. Proxmox: `pveversion -v`. Redfish: `curl -k -u <user> https://<bmc>/redfish/v1/UpdateService/FirmwareInventory`. Compare against current vendor security advisories and note hosts behind the supported builds. | O20: ● | Q20: ● | R20: ● | T20: Medium | U20: Redfish and vendor management APIs; PowerCLI scheduled reports. | V20: 3 | W20: 5 | X20: =V20*W20 -> 15 | Y20: =INDEX(Risk_Model!$B$30:$B$33,MATCH(X20,Risk_Model!$A$30:$A$33,1)) -> High | Z20: 2 | AA20: Firmware is never updated after installation. | AB20: Annual firmware cycle and tracked hypervisor patching. | AC20: Continuous firmware compliance reporting and risk-based expedited updates. | AD20: Inventory firmware and hypervisor versions, subscribe to vendor advisories, and schedule updates with maintenance windows. | AE20: NIST SP 800-40 Rev.4; CISA Known Exploited Vulnerabilities catalog; vendor lifecycle and support policies | AF20: ISO 27001:2022 A.8.8, A.7.13; NIST CSF 2.0 PR.PS-02, PR.PS-03; CIS v8.1 7.3; SOC 2 CC7.1 | AG20: New
A21: SRV-LOG-01 | B21: Server Security | C21: Logging and Time Synchronization | D21: Security-relevant events are logged on every server | E21: All | F21: Generate the audit trail needed to detect and investigate compromise. | G21: Without logs, intrusions cannot be detected, scoped or proven, and regulatory obligations cannot be met. | H21: Undetected compromise and loss of forensic evidence. | I21: Are authentication, privilege use, account and group changes, access-control changes, scheduled job and service creation, and system integrity events logged with timestamps? | J21: Detective | K21: - Audit policy export - auditd and rsyslog configuration - sample log events - log source inventory | L21: Windows: `auditpol /get /category:*`; `Get-WinEvent -ListLog Security | select LogName,MaximumSizeInBytes`; confirm events 4624, 4625, 4672, 4720, 4728, 4732, 4697, 4698 and 7045 occur; check PowerShell script block logging at `HKLM\SOFTWARE\Policies\Microsoft\Windows\PowerShell\ScriptBlockLogging`. Linux: `systemctl is-active auditd`, `auditctl -l` (look for rules on /etc/passwd, /etc/shadow, sudoers and execve), `last -n 20`. | O21: ● | Q21: ● | R21: ● | T21: High | U21: GPO and auditd configuration exports; Ansible audit role; osquery event tables. | V21: 4 | W21: 4 | X21: =V21*W21 -> 16 | Y21: =INDEX(Risk_Model!$B$30:$B$33,MATCH(X21,Risk_Model!$A$30:$A$33,1)) -> High | Z21: 3 | AA21: Default logging only. | AB21: Defined audit policy applied consistently with timestamps and critical events covered. | AC21: Threat-informed audit policy (including command-line and script logging) validated by detection tests. | AD21: Enable advanced audit policy, auditd rules and PowerShell logging aligned to a documented logging standard. | AE21: NIST SP 800-92; CIS Control 8; Microsoft Windows auditing guidance; CISA/ASD logging best-practice guidance | AF21: ISO 27001:2022 A.8.15, A.8.16; NIST CSF 2.0 PR.PS-04, DE.CM-09; CIS v8.1 8.2, 8.5; SOC 2 CC7.2 | AG21: 3.1, 3.5
A22: SRV-LOG-02 | B22: Server Security | C22: Logging and Time Synchronization | D22: Logs are forwarded in near real time to a central tamper-resistant store | E22: All | F22: Preserve evidence off-host and detect log tampering or forwarding failure. | G22: Attackers routinely clear local logs; central storage preserves evidence and enables correlation. | H22: Log clearing, loss of evidence, single point of failure on the host. | I22: Are logs forwarded in near real time to a central, access-restricted platform, with alerts when forwarding stops or logs are cleared? | J22: Detective | K22: - SIEM log-source health dashboard - forwarder configuration (WEF/WEC, Azure Monitor Agent, rsyslog, Splunk UF) - alert rules for log clearing and silent sources | L22: Windows: `wecutil gs <subscription>` or check the agent service. Linux: `grep -R "omfwd" /etc/rsyslog.conf /etc/rsyslog.d/`. In the SIEM, verify last-event time per server (stale beyond 15 minutes is a gap). Generate benign test events: `logger -p auth.notice "SAOS-test"` and `eventcreate /T INFORMATION /ID 999 /L APPLICATION /SO SAOS /D "test"`, then confirm arrival. Confirm an alert exists for Security log cleared (event 1102). | O22: ● | Q22: ● | R22: ● | T22: High | U22: SIEM API for last-seen per source; synthetic heartbeat events. | V22: 4 | W22: 5 | X22: =V22*W22 -> 20 | Y22: =INDEX(Risk_Model!$B$30:$B$33,MATCH(X22,Risk_Model!$A$30:$A$33,1)) -> Critical | Z22: 3 | AA22: Logs remain only on local servers. | AB22: Central collection for most servers with documented coverage. | AC22: Complete coverage with write-once storage, heartbeat monitoring and log-clear alerts. | AD22: Deploy forwarders to all servers, send to a restricted SIEM or log store, and alert on silent sources and log clearing. | AE22: NIST SP 800-92; CIS Control 8; Microsoft Windows auditing guidance; CISA/ASD logging best-practice guidance | AF22: ISO 27001:2022 A.8.15, A.8.16; NIST CSF 2.0 PR.PS-04, DE.CM-09, DE.AE-02; CIS v8.1 8.9, 13.1; SOC 2 CC7.2 | AG22: 3.7
A23: SRV-LOG-03 | B23: Server Security | C23: Logging and Time Synchronization | D23: Log retention satisfies investigation and regulatory needs | E23: All | F23: Keep logs long enough to investigate incidents that are discovered late. | G23: Intrusions are often found weeks after initial access; short retention destroys the evidence needed to scope them. | H23: Loss of forensic evidence when local logs roll over. | I23: Is log retention (online and archive) defined to meet investigation and regulatory requirements, and are local log sizes sufficient to prevent early overwrite? | J23: Detective | K23: - Retention policy - SIEM retention configuration - local log size settings - regulatory retention requirements | L23: Windows: `wevtutil gl Security` (maxSize and retention). Linux: `journalctl --disk-usage` and `grep -E 'max_log_file|num_logs' /etc/audit/auditd.conf`. Confirm the SIEM can return events older than the required window. The source checklist required at least 2 weeks locally; this framework recommends at least 90 days online and 12 months archived, subject to regulation. | N23: ● | O23: ● | Q23: ● | T23: High | U23: SIEM retention API; scripted check of oldest available event per source. | V23: 3 | W23: 3 | X23: =V23*W23 -> 9 | Y23: =INDEX(Risk_Model!$B$30:$B$33,MATCH(X23,Risk_Model!$A$30:$A$33,1)) -> Medium | Z23: 2 | AA23: Logs overwrite quickly with no retention requirement. | AB23: Retention defined and configured to policy. | AC23: Tiered retention aligned to regulation and threat profile, validated by periodic retrieval tests. | AD23: Set minimum retention (online and archive) by data class and regulation, and size local logs to cover forwarding outages. | AE23: NIST SP 800-92; CIS Control 8; Microsoft Windows auditing guidance; CISA/ASD logging best-practice guidance | AF23: ISO 27001:2022 A.8.15, A.5.33; NIST CSF 2.0 PR.PS-04; CIS v8.1 8.3, 8.10; SOC 2 CC7.2 | AG23: 3.5
A24: SRV-LOG-04 | B24: Server Security | C24: Logging and Time Synchronization | D24: Sensitive data is excluded from logs and log files are protected | E24: All | F24: Prevent logs from becoming a store of credentials or personal data. | G24: Credentials and personal data in logs create breach exposure and privacy compliance failures. | H24: Credential exposure through logs and privacy breaches. | I24: Is logging configured to exclude passwords, secrets, tokens and sensitive personal data, and are log files access-restricted? | J24: Preventive | K24: - Application logging configuration - sample log review - log file permission listings - secret-scan results for log stores | L24: Windows: review process command-line auditing (event 4688) and PowerShell transcripts for secrets. Linux: `grep -riE "password=|passwd|secret|token" /var/log 2>/dev/null | head` and `ls -l /var/log`. With authorisation, run `gitleaks detect --no-git -s /var/log` or `trufflehog filesystem /var/log`. | O24: ● | Q24: ● | R24: ● | T24: Medium | U24: Secret scanners against log stores; SIEM masking and data-loss rules. | V24: 3 | W24: 4 | X24: =V24*W24 -> 12 | Y24: =INDEX(Risk_Model!$B$30:$B$33,MATCH(X24,Risk_Model!$A$30:$A$33,1)) -> High | Z24: 2 | AA24: Logs contain secrets and are world-readable. | AB24: Logging standard prohibits sensitive data and permissions are restricted. | AC24: Automated secret scanning of logs with masking at source. | AD24: Mask sensitive fields at source, restrict log permissions, and scan log stores for secrets. | AE24: NIST SP 800-92; CIS Control 8; Microsoft Windows auditing guidance; CISA/ASD logging best-practice guidance | AF24: ISO 27001:2022 A.8.15, A.5.34; NIST CSF 2.0 PR.DS-01, PR.PS-04; CIS v8.1 3.3; SOC 2 CC6.1 | AG24: 3.6
A25: SRV-LOG-05 | B25: Server Security | C25: Logging and Time Synchronization | D25: Log monitoring and alert triage run on a defined schedule and are reviewed for effectiveness | E25: All | F25: Ensure collected logs are actually examined and that monitoring quality is measured. | G25: Logs that are never reviewed give a false sense of assurance. | H25: Missed intrusions despite available evidence. | I25: Is there a documented, scheduled monitoring and triage process with defined detection use cases, ownership, and an effectiveness review at least monthly? | J25: Detective | K25: - Log monitoring procedure and schedule - server use-case catalogue - triage records - monthly review minutes - detection metrics | L25: Review the procedure and schedule and sample 3 months of review evidence. Select 5 use cases (new local administrator, service creation, failed-logon spike, audit log cleared, new SSH key) and trigger benign test events. Verify alerts fire, are triaged and result in tickets within the target time. | M25: ● | N25: ● | Q25: ● | T25: Medium | U25: SIEM detection rules as code; purple-team or Atomic Red Team test execution. | V25: 3 | W25: 4 | X25: =V25*W25 -> 12 | Y25: =INDEX(Risk_Model!$B$30:$B$33,MATCH(X25,Risk_Model!$A$30:$A$33,1)) -> High | Z25: 3 | AA25: No defined monitoring; logs reviewed only after incidents. | AB25: Documented schedule and use cases with evidence of triage. | AC25: Measured detection coverage against ATT&CK with regular testing and tuning. | AD25: Define server detection use cases, assign monitoring ownership, and review detection performance monthly. | AE25: NIST SP 800-92; CIS Control 8; Microsoft Windows auditing guidance; CISA/ASD logging best-practice guidance | AF25: ISO 27001:2022 A.8.15, A.8.16; NIST CSF 2.0 DE.CM-09, DE.AE-02, DE.AE-03; CIS v8.1 8.11, 13.1; SOC 2 CC7.2, CC7.3 | AG25: 3.2, 3.3, 3.4
A26: SRV-LOG-06 | B26: Server Security | C26: Logging and Time Synchronization | D26: Servers use authoritative time and name-resolution sources | E26: All | F26: Ensure consistent time for log correlation and authentication, and trustworthy name resolution. | G26: Inconsistent time breaks forensic timelines and Kerberos; untrusted DNS enables redirection attacks. | H26: Log correlation failure, authentication failures, DNS spoofing. | I26: Do all servers synchronise time from authoritative, resilient sources and use authorised DNS resolvers? | J26: Preventive | K26: - NTP configuration - DNS resolver configuration - time status output - AD time hierarchy documentation | L26: Windows: `w32tm /query /status`, `w32tm /query /source`, `Get-DnsClientServerAddress` (domain members should follow the domain hierarchy; the PDC emulator syncs to a reliable external source). Linux: `chronyc sources -v`, `timedatectl show`, `resolvectl status` or `cat /etc/resolv.conf`. Confirm clock offset is well under one second and resolvers are the approved internal servers. | O26: ● | Q26: ● | R26: ● | T26: High | U26: Fleet-wide chrony/w32tm offset reports; DNS configuration compliance checks. | V26: 2 | W26: 3 | X26: =V26*W26 -> 6 | Y26: =INDEX(Risk_Model!$B$30:$B$33,MATCH(X26,Risk_Model!$A$30:$A$33,1)) -> Medium | Z26: 2 | AA26: Clocks drift and resolvers are set arbitrarily. | AB26: Authoritative time and DNS sources defined and configured. | AC26: Redundant authenticated time sources with offset monitoring and alerts. | AD26: Standardise time sources and resolvers in the build baseline and monitor clock offset. | AE26: NIST SP 800-92; CIS Control 8; Microsoft Windows auditing guidance; CISA/ASD logging best-practice guidance | AF26: ISO 27001:2022 A.8.17; NIST CSF 2.0 PR.PS-04; CIS v8.1 4.9, 8.4; SOC 2 CC7.2 | AG26: 12.2
A27: SRV-HST-01 | B27: Server Security | C27: Host Protection | D27: Anti-malware or EDR is deployed, current and tamper-protected on servers | E27: All | F27: Detect and block malicious code and behaviour on servers. | G27: Servers are prime ransomware targets; endpoint protection is a baseline expectation of insurers and regulators. | H27: Malware and ransomware execution, defence tampering. | I27: Is anti-malware or EDR installed on all servers with real-time protection, current signatures and engine, tamper protection, and monitored alerts? | J27: Preventive | K27: - EDR console deployment report - coverage versus inventory - exclusion list - tamper protection setting | L27: Windows: `Get-MpComputerStatus | select AMServiceEnabled,RealTimeProtectionEnabled,AntivirusSignatureLastUpdated,IsTamperProtected` and `Get-MpPreference | select ExclusionPath,ExclusionProcess`. Linux: `mdatp health` for Defender, or the vendor equivalent. Compare EDR-reported hosts with the inventory and review exclusions for breadth and approval. | O27: ● | Q27: ● | R27: ● | T27: High | U27: EDR console API coverage report; Defender for Endpoint device inventory. | V27: 3 | W27: 5 | X27: =V27*W27 -> 15 | Y27: =INDEX(Risk_Model!$B$30:$B$33,MATCH(X27,Risk_Model!$A$30:$A$33,1)) -> High | Z27: 3 | AA27: Protection absent or unmanaged on many servers. | AB27: Deployed on all servers with updates and central alerting. | AC27: Tamper-protected EDR on all servers with reviewed exclusions and response playbooks. | AD27: Deploy EDR to every server, enable tamper protection, and review exclusions quarterly. | AE27: CIS Controls 10 and 13; Microsoft Defender documentation; vendor EDR hardening guides | AF27: ISO 27001:2022 A.8.7; NIST CSF 2.0 DE.CM-09, PR.PS-05; CIS v8.1 10.1, 10.2, 10.7; SOC 2 CC6.8 | AG27: 4.4
A28: SRV-HST-02 | B28: Server Security | C28: Host Protection | D28: A host firewall enforces default-deny inbound rules | E28: All | F28: Limit network access to each server to required services and sources. | G28: Host firewalls contain lateral movement when perimeter and segmentation controls fail. | H28: Lateral movement and service exposure. | I28: Is a host firewall enabled in default-deny inbound mode with rules limited to required services and management sources? | J28: Preventive | K28: - Firewall rule exports - GPO - nftables or firewalld configuration - rule review records | L28: Windows: `Get-NetFirewallProfile | select Name,Enabled,DefaultInboundAction` and `Get-NetFirewallRule -Enabled True -Direction Inbound -Action Allow | select DisplayName,Profile`. Linux: `firewall-cmd --list-all`, `nft list ruleset`, `ufw status verbose` or `iptables -S`. Confirm the default inbound policy is block or drop and that rules restrict source addresses. | O28: ● | Q28: ● | R28: ● | T28: High | U28: GPO, Intune or Ansible firewall policy export; OpenSCAP firewall rules. | V28: 3 | W28: 4 | X28: =V28*W28 -> 12 | Y28: =INDEX(Risk_Model!$B$30:$B$33,MATCH(X28,Risk_Model!$A$30:$A$33,1)) -> High | Z28: 3 | AA28: Host firewall disabled. | AB28: Enabled with default-deny and role-based rules. | AC28: Source-restricted rules managed as code with periodic review and drift alerts. | AD28: Enable the host firewall in default-deny mode and scope rules to required ports and sources. | AE28: CIS Controls 10 and 13; Microsoft Defender documentation; vendor EDR hardening guides | AF28: ISO 27001:2022 A.8.20, A.8.9; NIST CSF 2.0 PR.IR-01; CIS v8.1 4.4; SOC 2 CC6.6 | AG28: 4.5
A29: SRV-HST-03 | B29: Server Security | C29: Host Protection | D29: Host intrusion prevention and exploit mitigations are enabled | E29: All | F29: Block exploitation techniques and malicious behaviour at the host. | G29: Prevention-mode controls on authentication servers protect the systems that hold the keys to the whole estate. | H29: Memory-corruption exploitation and post-exploitation behaviour. | I29: Are host intrusion prevention and OS exploit mitigations enabled, and mandatory in prevention mode on authentication servers (domain controllers, identity providers, RADIUS, PAM)? | J29: Preventive | K29: - HIPS or EDR prevention policy - exploit-protection configuration - list of authentication servers with HIPS status | L29: Windows: `Get-ProcessMitigation -System` and `Get-MpPreference | select -ExpandProperty AttackSurfaceReductionRules_Ids`. Linux: `sestatus` or `aa-status`, and `sysctl kernel.randomize_va_space kernel.kptr_restrict`. Confirm authentication servers run in prevention mode, not detect-only. | O29: ● | Q29: ● | R29: ● | T29: Medium | U29: Defender ASR rule reporting; EDR policy export; OpenSCAP kernel hardening checks. | V29: 3 | W29: 4 | X29: =V29*W29 -> 12 | Y29: =INDEX(Risk_Model!$B$30:$B$33,MATCH(X29,Risk_Model!$A$30:$A$33,1)) -> High | Z29: 2 | AA29: No host prevention capability. | AB29: Prevention enabled on critical and authentication servers. | AC29: Tuned prevention on all servers with measured block events and regular tests. | AD29: Enable exploit mitigations and ASR rules, and enforce prevention mode on authentication servers. | AE29: CIS Controls 10 and 13; Microsoft Defender documentation; vendor EDR hardening guides | AF29: ISO 27001:2022 A.8.7, A.8.9; NIST CSF 2.0 PR.PS-05, DE.CM-09; CIS v8.1 10.5, 13.7; SOC 2 CC6.8, CC7.2 | AG29: 4.6
A30: SRV-HST-04 | B30: Server Security | C30: Host Protection | D30: File and configuration integrity monitoring covers critical system paths | E30: All | F30: Detect unauthorised changes to system binaries, configuration and sensitive files. | G30: Integrity monitoring detects web shells, rootkits and persistence that signature tools miss. | H30: Web shells, binary tampering, rootkits, persistence mechanisms. | I30: Is file and configuration integrity monitoring in place for critical system files, binaries, configuration and registry paths, with alerting on unauthorised change? | J30: Detective | K30: - FIM policy and monitored paths - alert samples - baseline hash database - EDR or FIM console | L30: Linux: `aide --check` or `tripwire --check`; confirm the AIDE database is stored read-only or off-host. Windows: Defender for Endpoint, Wazuh or Tripwire FIM; Sysmon events 11, 12 and 13 for file and registry activity. Make a controlled benign change to a monitored test file and confirm an alert is raised. | Q30: ● | R30: ● | T30: Medium | U30: Wazuh, AIDE, Tripwire or EDR FIM with SIEM alerting. | V30: 3 | W30: 4 | X30: =V30*W30 -> 12 | Y30: =INDEX(Risk_Model!$B$30:$B$33,MATCH(X30,Risk_Model!$A$30:$A$33,1)) -> High | Z30: 2 | AA30: No integrity monitoring. | AB30: FIM on critical servers and paths with alerts. | AC30: Comprehensive FIM with change-ticket correlation and automated triage. | AD30: Deploy FIM on critical paths, protect baselines off-host, and correlate alerts with approved changes. | AE30: CIS Controls 10 and 13; Microsoft Defender documentation; vendor EDR hardening guides | AF30: ISO 27001:2022 A.8.16, A.8.9; NIST CSF 2.0 PR.DS-06, DE.CM-09; CIS v8.1 4.1; SOC 2 CC7.1 | AG30: 4.7
A31: SRV-VUL-01 | B31: Server Security | C31: Vulnerability Assessment | D31: Servers are hardened and vulnerability-assessed before entering production | E31: All | F31: Ensure no server goes live with known exploitable weaknesses or without a retained security baseline. | G31: Fixing issues before go-live is far cheaper than after exposure, and the baseline report supports later audits and investigations. | H31: Insecure systems exposed at go-live. | I31: Is every new or rebuilt server configuration-reviewed and vulnerability-scanned before production, and are the baseline reports retained? | J31: Preventive | K31: - Go-live checklist - pre-production scan and baseline compliance report - sign-off record - retained report archive | L31: Sample 5 servers deployed in the last 12 months and locate the pre-production scan report, the open findings by severity at go-live, and the approval of any residual risk. For automated builds, confirm a scan gate exists in the pipeline. Verify reports are retained and retrievable. | N31: ● | Q31: ● | T31: High | U31: Pipeline gate calling a scanner API (Nessus, Qualys, Defender TVM, OpenVAS). | V31: 3 | W31: 4 | X31: =V31*W31 -> 12 | Y31: =INDEX(Risk_Model!$B$30:$B$33,MATCH(X31,Risk_Model!$A$30:$A$33,1)) -> High | Z31: 2 | AA31: Servers go live without assessment. | AB31: Pre-production checklist and scan completed with sign-off and retained reports. | AC31: Automated pipeline gates block deployment on policy failure with exception workflow. | AD31: Add a mandatory pre-production hardening and scanning gate with documented sign-off and report retention. | AE31: NIST SP 800-115; NIST SP 800-40 Rev.4; CVSS specification (FIRST); EPSS; CISA KEV catalog | AF31: ISO 27001:2022 A.8.29, A.8.8, A.8.9; NIST CSF 2.0 ID.RA-01, PR.PS-01; CIS v8.1 4.1, 7.5; SOC 2 CC7.1, CC8.1 | AG31: 5.1, 5.5
A32: SRV-VUL-02 | B32: Server Security | C32: Vulnerability Assessment | D32: Servers receive recurring credentialed vulnerability scans | E32: All | F32: Continuously identify missing patches and misconfigurations across all servers. | G32: Unauthenticated scans miss most local vulnerabilities; coverage gaps leave unknown risk. | H32: Unknown vulnerabilities and false negatives from unauthenticated scanning. | I32: Are all servers scanned with credentialed scans at a defined frequency (at least monthly, weekly for internet-facing), and are coverage gaps tracked? | J32: Detective | K32: - Scan schedule - coverage report versus inventory - scan credential policy - last 3 scan results - authentication failure report | L32: Export the scanner asset list and compare with the inventory (target coverage of 95% or better). Check the authentication success rate per scan and the last-scanned date per server. Confirm internet-facing assets are also scanned externally from an authorised host (`nmap -sV <public-ip>`). | N32: ● | Q32: ● | R32: ● | T32: High | U32: Scanner API coverage reports reconciled to CMDB. | V32: 4 | W32: 4 | X32: =V32*W32 -> 16 | Y32: =INDEX(Risk_Model!$B$30:$B$33,MATCH(X32,Risk_Model!$A$30:$A$33,1)) -> High | Z32: 3 | AA32: No regular scanning. | AB32: Scheduled credentialed scans with tracked coverage. | AC32: Continuous assessment (agent-based) with near-complete coverage and exposure-aware prioritisation. | AD32: Schedule credentialed scans for all servers, fix authentication failures, and scan internet-facing assets externally. | AE32: NIST SP 800-115; NIST SP 800-40 Rev.4; CVSS specification (FIRST); EPSS; CISA KEV catalog | AF32: ISO 27001:2022 A.8.8; NIST CSF 2.0 ID.RA-01; CIS v8.1 7.5, 7.6; SOC 2 CC7.1 | AG32: 5.2
A33: SRV-VUL-03 | B33: Server Security | C33: Vulnerability Assessment | D33: Vulnerability scanning is formally authorised and scanning tools are governed | E33: All | F33: Ensure scanning is permitted, unobstructed and performed only by approved people and tools. | G33: Blocked scanners create blind spots, while unmanaged scanners and their credentials are an attack path. | H33: Blind spots from blocked scanners, rogue scanning, scanner credential abuse. | I33: Is scanning formally authorised, are approved scanners excluded from blocking without blanket whitelisting, and are only approved tools and operators used? | J33: Preventive | K33: - Scanning authorisation or rules of engagement - approved-tool list - scanner service-account permissions - security-tool allow-list rationale - authorised operator list | L33: Review the authorisation and approved-tool list. Confirm scanner IPs and service accounts are inventoried, least-privilege, vaulted and monitored, and that scanner subnets are not permanently exempt across the detection stack. Hunt in the EDR for scanning tools (nmap, nessus) running outside approved hosts. | M33: ● | N33: ● | O33: ● | T33: Low | U33: EDR hunting query for unapproved scanner binaries. | V33: 2 | W33: 3 | X33: =V33*W33 -> 6 | Y33: =INDEX(Risk_Model!$B$30:$B$33,MATCH(X33,Risk_Model!$A$30:$A$33,1)) -> Medium | Z33: 1 | AA33: Scanning occurs ad hoc with no approval or governance. | AB33: Authorised scanning with approved tools and operators. | AC33: Vaulted scanner credentials with monitored use and annual authorisation review. | AD33: Document scanning authorisation, vault scanner credentials, and review exemptions in security tooling. | AE33: NIST SP 800-115; NIST SP 800-40 Rev.4; CVSS specification (FIRST); EPSS; CISA KEV catalog | AF33: ISO 27001:2022 A.8.8, A.8.34; NIST CSF 2.0 ID.RA-01; CIS v8.1 7.5; SOC 2 CC7.1 | AG33: 5.3, 5.4, 5.7
A34: SRV-VUL-04 | B34: Server Security | C34: Vulnerability Assessment | D34: Vulnerabilities are prioritised by risk, remediated within timelines and verified by rescan | E34: All | F34: Reduce exploitable exposure through risk-based prioritisation and closed-loop remediation. | G34: CVSS alone misprioritises; combining exploitability, exposure and asset criticality focuses effort where breach likelihood is highest. | H34: Backlog of exploitable issues and false closure of findings. | I34: Are vulnerabilities prioritised using severity, exploitability (CVSS, EPSS, KEV), asset criticality and exposure, with timelines enforced, exceptions approved and fixes verified by rescan? | J34: Corrective | K34: - Vulnerability management standard with timelines - aged vulnerability report - exception register - rescan evidence - time-to-remediate metrics | L34: Export open vulnerabilities and calculate the percentage within timeline by severity. Sample 10 closed items for rescan evidence and 5 exceptions for approval, compensating controls and expiry. Where no CVSS exists, confirm the vulnerability is assessed for remote exploitability. | N34: ● | Q34: ● | R34: ● | T34: High | U34: Scanner and ticketing integration; KEV and EPSS enrichment. | V34: 4 | W34: 4 | X34: =V34*W34 -> 16 | Y34: =INDEX(Risk_Model!$B$30:$B$33,MATCH(X34,Risk_Model!$A$30:$A$33,1)) -> High | Z34: 3 | AA34: Vulnerabilities are listed but not tracked to closure. | AB34: Defined timelines, tracked remediation and approved exceptions. | AC34: Risk-based prioritisation using threat data with measured, consistently met timelines and verified closure. | AD34: Adopt risk-based timelines, enrich findings with KEV and EPSS, and require rescan validation before closure. | AE34: NIST SP 800-115; NIST SP 800-40 Rev.4; CVSS specification (FIRST); EPSS; CISA KEV catalog | AF34: ISO 27001:2022 A.8.8; NIST CSF 2.0 ID.RA-05, ID.RA-06; CIS v8.1 7.1, 7.2, 7.7; SOC 2 CC7.1, CC3.2 | AG34: 5.6
A35: SRV-NET-01 | B35: Server Security | C35: Network Placement and Exposure | D35: Servers are placed in segmented zones with documented and minimised network exposure | E35: All | F35: Restrict network reachability of servers to required flows and prevent unintended exposure. | G35: Flat networks turn a single compromised host into an enterprise-wide incident. | H35: Lateral movement across flat networks and internet exposure of management or database ports. | I35: Are servers placed in zones appropriate to function and data sensitivity, with traffic limited to documented flows, no unintended internet exposure, and safeguards for specialised or shared computing (HPC, grid) environments? | J35: Preventive | K35: - Network diagrams - firewall rule exports for server zones - data-flow documentation - external attack-surface scan - segmentation test results - list of specialised-computing participants | L35: Compare the server inventory with VLAN and zone assignment. Run an authorised external scan (`nmap -Pn -sV -p- <public-ranges>`) and compare to documented exposure. From a user VLAN test reachability to admin ports (`Test-NetConnection <ip> -Port 3389` or `nc -vz <ip> 22`; also 445, 5985, 5986). Review firewall rules for any-any and unused entries, and confirm HPC or grid workloads have documented safeguards. | N35: ● | O35: ● | Q35: ● | S35: ● | T35: Medium | U35: Firewall rule analysis tools (Tufin, AlgoSec, FireMon) or exported configuration parsing; external attack-surface management. | V35: 3 | W35: 5 | X35: =V35*W35 -> 15 | Y35: =INDEX(Risk_Model!$B$30:$B$33,MATCH(X35,Risk_Model!$A$30:$A$33,1)) -> High | Z35: 3 | AA35: Flat network with servers and users together. | AB35: Defined server zones with documented flows and firewall control. | AC35: Micro-segmentation, continuous exposure monitoring and validated segmentation tests. | AD35: Segment server zones, document flows, remove unused rules, and monitor external exposure continuously. | AE35: NIST SP 800-41 Rev.1; NIST SP 800-207; CIS Control 12 | AF35: ISO 27001:2022 A.8.20, A.8.21, A.8.22; NIST CSF 2.0 PR.IR-01, ID.AM-03; CIS v8.1 4.4, 12.2, 13.4; SOC 2 CC6.6 | AG35: 1.3, 13.1
A36: SRV-IAM-01 | B36: Server Security | C36: Authentication and Access Control | D36: Default accounts and credentials are changed, renamed or disabled | E36: All | F36: Eliminate publicly known credentials on operating systems, applications and appliances. | G36: Default credentials are trivially guessed and are tested first in nearly every attack. | H36: Credential guessing with documented vendor defaults. | I36: Have all manufacturer and default accounts and passwords been changed, renamed or disabled on operating systems, applications, databases, BMCs and appliances? | J36: Preventive | K36: - Default-account review - account listings per system - default-credential scan results - BMC and appliance credential rotation records | L36: Windows: `Get-LocalUser | select Name,Enabled,PasswordLastSet`; confirm the built-in Administrator is renamed, disabled or LAPS-managed and Guest is disabled. Linux: `awk -F: '($2==""){print $1}' /etc/shadow` and `getent passwd | awk -F: '$3==0{print $1}'`; check default application accounts (tomcat, admin, postgres, sa). Run an authorised default-password scan (for example Nessus default-password plugins). | O36: ● | Q36: ● | R36: ● | T36: High | U36: Credentialed scanner default-password checks; Ansible account audit. | V36: 3 | W36: 5 | X36: =V36*W36 -> 15 | Y36: =INDEX(Risk_Model!$B$30:$B$33,MATCH(X36,Risk_Model!$A$30:$A$33,1)) -> High | Z36: 3 | AA36: Default credentials remain on some systems. | AB36: Default accounts changed at build with a verified checklist. | AC36: Automated detection of default credentials with rotation to a vault. | AD36: Change or disable default credentials during build, and scan for them regularly. | AE36: NIST SP 800-63B; NIST SP 800-53 Rev.5 AC and IA families; CIS Controls 5 and 6; Windows LAPS documentation | AF36: ISO 27001:2022 A.5.17, A.8.9; NIST CSF 2.0 PR.AA-01, PR.PS-01; CIS v8.1 4.7, 5.2; SOC 2 CC6.1 | AG36: 6.2
A37: SRV-IAM-02 | B37: Server Security | C37: Authentication and Access Control | D37: Strong authentication is enforced for all administrative and root access | E37: All | F37: Protect administrative access with phishing-resistant or multi-factor authentication. | G37: Stolen or guessed administrator passwords give full control of the server and often the domain. | H37: Password theft, brute force and reuse against privileged accounts. | I37: Is MFA or equivalent strong authentication (smart card, FIDO2, key-based SSH with passphrase) enforced for every administrator and root-level access? | J37: Preventive | K37: - PAM or jump host configuration - MFA and Conditional Access policy export - sshd configuration - admin accounts with authentication method - exception list | L37: Windows: confirm admin RDP and console logon occurs through a PAW or jump host with MFA (Conditional Access, smart card or Windows Hello for Business); `Get-ADUser -Filter {SmartcardLogonRequired -eq $true}` for smart-card-enforced admins. Linux: `sshd -T | egrep "passwordauthentication|permitrootlogin|pubkeyauthentication|authenticationmethods"` and `grep -E "pam_google_authenticator|pam_duo" /etc/pam.d/sshd`. Compare the admin list with enforcement and attempt a password-only login (expect failure). | O37: ● | Q37: ● | R37: ● | T37: High | U37: Entra sign-in logs and Conditional Access reports; sshd -T compliance scan. | V37: 4 | W37: 5 | X37: =V37*W37 -> 20 | Y37: =INDEX(Risk_Model!$B$30:$B$33,MATCH(X37,Risk_Model!$A$30:$A$33,1)) -> Critical | Z37: 3 | AA37: Passwords only for administrators. | AB37: MFA enforced for administrators with documented exceptions. | AC37: Phishing-resistant MFA everywhere with just-in-time elevation and no standing access. | AD37: Enforce MFA via jump host or PAM, move SSH to keys or certificates, and remove password-only paths. | AE37: NIST SP 800-63B; NIST SP 800-53 Rev.5 AC and IA families; CIS Controls 5 and 6; Windows LAPS documentation | AF37: ISO 27001:2022 A.8.5, A.8.2; NIST CSF 2.0 PR.AA-03; CIS v8.1 6.5; SOC 2 CC6.1 | AG37: 6.3
A38: SRV-IAM-03 | B38: Server Security | C38: Authentication and Access Control | D38: Access to the server, applications and data follows least privilege | E38: All | F38: Restrict access to authorised, authenticated users with only the rights they need. | G38: Excess privilege multiplies the damage of any single account compromise or insider misuse. | H38: Excess privilege enabling data theft, sabotage and privilege escalation. | I38: Is access limited to authorised, authenticated users through role-based groups with least privilege, and without direct user permissions on resources? | J38: Preventive | K38: - Role and group matrix - local and domain group membership exports - ACL listings for key data - last access review | L38: Windows: `Get-LocalGroupMember Administrators`, `Get-SmbShare | Get-SmbShareAccess`, `icacls <path>`; look for Everyone or Authenticated Users write access. Linux: `getent group sudo wheel`, `find / -xdev -perm -0002 -type f 2>/dev/null | head`, `find / -xdev -perm -4000 -type f`. Sample 10 users and compare their rights with job roles. | O38: ● | Q38: ● | R38: ● | T38: High | U38: AD and local group exports; access analytics tools; Ansible user audit. | V38: 4 | W38: 4 | X38: =V38*W38 -> 16 | Y38: =INDEX(Risk_Model!$B$30:$B$33,MATCH(X38,Risk_Model!$A$30:$A$33,1)) -> High | Z38: 3 | AA38: Broad shared access with many administrators. | AB38: Role-based groups and documented access matrix. | AC38: Just-in-time elevation, automated entitlement analytics and periodic recertification. | AD38: Move to role-based groups, remove direct and excessive permissions, and recertify access quarterly. | AE38: NIST SP 800-63B; NIST SP 800-53 Rev.5 AC and IA families; CIS Controls 5 and 6; Windows LAPS documentation | AF38: ISO 27001:2022 A.5.15, A.5.18, A.8.2, A.8.3; NIST CSF 2.0 PR.AA-05; CIS v8.1 3.3, 5.4, 6.8; SOC 2 CC6.1, CC6.3 | AG38: 6.4
A39: SRV-IAM-04 | B39: Server Security | C39: Authentication and Access Control | D39: Access is granted, changed and removed through a documented process with periodic review | E39: All | F39: Keep access aligned with current role and eliminate orphaned accounts. | G39: Leavers and movers retaining access are a major source of audit findings and insider breaches. | H39: Orphaned and over-provisioned access. | I39: Is there a documented process to grant, change and remove server access (joiner, mover, leaver), with periodic recertification of privileged and sensitive access? | J39: Preventive | K39: - Access procedure - approved access request sample - leaver list versus server accounts - recertification records | L39: Sample 10 leavers and 10 movers and verify revocation within the target time (for example 24 hours). Compare the HR leaver list with server and AD accounts. Windows: `Get-ADUser -Filter {Enabled -eq $true} -Properties LastLogonDate | where LastLogonDate -lt (Get-Date).AddDays(-90)`. Linux: `lastlog -b 90`. Check the date and outcome of the last recertification. | M39: ● | N39: ● | Q39: ● | T39: High | U39: HR-to-IAM leaver reconciliation; dormant account reports. | V39: 3 | W39: 4 | X39: =V39*W39 -> 12 | Y39: =INDEX(Risk_Model!$B$30:$B$33,MATCH(X39,Risk_Model!$A$30:$A$33,1)) -> High | Z39: 2 | AA39: Access removed only when someone remembers. | AB39: Documented joiner/mover/leaver process with annual reviews. | AC39: HR-driven automated provisioning and revocation with quarterly privileged recertification. | AD39: Automate leaver revocation, disable dormant accounts, and recertify privileged access at least quarterly. | AE39: NIST SP 800-63B; NIST SP 800-53 Rev.5 AC and IA families; CIS Controls 5 and 6; Windows LAPS documentation | AF39: ISO 27001:2022 A.5.16, A.5.18; NIST CSF 2.0 PR.AA-01, PR.AA-05; CIS v8.1 5.3, 6.1, 6.2; SOC 2 CC6.2, CC6.3 | AG39: 6.4
A40: SRV-IAM-05 | B40: Server Security | C40: Authentication and Access Control | D40: Generic, shared and guest interactive accounts are disabled | E40: All | F40: Ensure every interactive session is attributable to one individual. | G40: Shared accounts remove accountability and are hard to revoke when staff leave. | H40: Loss of accountability and widely known shared credentials. | I40: Are generic, shared and guest accounts that permit interactive logon disabled, with any exception approved, attributable and logged (service accounts excluded)? | J40: Preventive | K40: - Account inventory with type classification - exception approvals - PAM checkout logs | L40: Windows: `Get-LocalUser Guest`; review interactive logon events (4624 logon types 2 and 10) for non-personal accounts. Linux: `getent passwd` for UID 1000 and above and `last` for shared names. Verify exceptions use PAM checkout with session recording. | O40: ● | Q40: ● | T40: High | U40: Account inventory scripts with naming convention checks. | V40: 3 | W40: 4 | X40: =V40*W40 -> 12 | Y40: =INDEX(Risk_Model!$B$30:$B$33,MATCH(X40,Risk_Model!$A$30:$A$33,1)) -> High | Z40: 2 | AA40: Shared admin accounts are common. | AB40: Shared accounts disabled apart from approved, logged exceptions. | AC40: No shared accounts; break-glass access vaulted, alerted and reviewed after use. | AD40: Replace shared accounts with named accounts and vault break-glass credentials. | AE40: NIST SP 800-63B; NIST SP 800-53 Rev.5 AC and IA families; CIS Controls 5 and 6; Windows LAPS documentation | AF40: ISO 27001:2022 A.5.16, A.5.17; NIST CSF 2.0 PR.AA-01; CIS v8.1 5.1, 5.2; SOC 2 CC6.1 | AG40: 6.4
A41: SRV-IAM-06 | B41: Server Security | C41: Authentication and Access Control | D41: Trust relationships are identified, justified and reviewed | E41: All | F41: Know and control the implicit trust paths between systems and identities. | G41: Unreviewed trusts allow an attacker to move from a low-value system to critical ones. | H41: Lateral movement through unmonitored trust paths. | I41: Are all trust relationships (domain and forest trusts, SSH key trust, delegation, database links, service-to-service trust) identified, justified and reviewed? | J41: Preventive | K41: - Trust inventory - AD trust export - authorized_keys inventory - delegation settings - review sign-off | L41: AD: `Get-ADTrust -Filter * | select Name,Direction,TrustType,SIDFilteringQuarantined` and `Get-ADComputer -Filter {TrustedForDelegation -eq $true}`. Linux: `find /home /root -name authorized_keys`, `cat /etc/hosts.equiv ~/.rhosts 2>/dev/null`, and review `/etc/sudoers.d`. Validate business justification, SID filtering and key ownership. | N41: ● | O41: ● | Q41: ● | T41: Medium | U41: AD trust and delegation reports; SSH key inventory scripts. | V41: 3 | W41: 5 | X41: =V41*W41 -> 15 | Y41: =INDEX(Risk_Model!$B$30:$B$33,MATCH(X41,Risk_Model!$A$30:$A$33,1)) -> High | Z41: 2 | AA41: Trust relationships are unknown. | AB41: Trusts documented and reviewed annually. | AC41: Continuously monitored trust graph with automated alerts for new trusts and keys. | AD41: Inventory trusts and delegation, remove unneeded ones, enable SID filtering, and review SSH keys. | AE41: NIST SP 800-63B; NIST SP 800-53 Rev.5 AC and IA families; CIS Controls 5 and 6; Windows LAPS documentation | AF41: ISO 27001:2022 A.5.15, A.8.2, A.8.20; NIST CSF 2.0 PR.AA-05, ID.AM-03; CIS v8.1 6.8; SOC 2 CC6.1, CC6.3 | AG41: 6.1
A42: SRV-IAM-07 | B42: Server Security | C42: Authentication and Access Control | D42: Local administrator and root credentials are unique, rotated and vaulted | E42: All | F42: Stop credential reuse of local privileged accounts across servers. | G42: A shared local administrator password lets an attacker move across the whole estate from one stolen hash. | H42: Pass-the-hash and credential reuse. | I42: Are local administrator and root credentials unique per server, automatically rotated and stored in a vault or LAPS, with access audited? | J42: Preventive | K42: - Windows LAPS policy - AD attribute permissions - PAM vault configuration - rotation logs | L42: Windows: `Get-LapsADPassword -Identity <server>` (Windows LAPS) or check legacy attributes with `Get-ADComputer -Filter * -Properties ms-Mcs-AdmPwdExpirationTime`. Review who can read the password attribute (ACL review). Linux: confirm root password rotation through a vault, or that direct root login is disabled. | O42: ● | Q42: ● | R42: ● | T42: High | U42: LAPS coverage report; PAM vault API. | V42: 4 | W42: 5 | X42: =V42*W42 -> 20 | Y42: =INDEX(Risk_Model!$B$30:$B$33,MATCH(X42,Risk_Model!$A$30:$A$33,1)) -> Critical | Z42: 3 | AA42: The same local administrator password is used on many servers. | AB42: LAPS or vault deployed to most servers with controlled retrieval. | AC42: Full coverage with rotation after use and alerts on retrieval. | AD42: Deploy Windows LAPS or a PAM vault, restrict who can read passwords, and disable direct root logon. | AE42: NIST SP 800-63B; NIST SP 800-53 Rev.5 AC and IA families; CIS Controls 5 and 6; Windows LAPS documentation | AF42: ISO 27001:2022 A.8.2, A.5.17; NIST CSF 2.0 PR.AA-01, PR.AA-05; CIS v8.1 5.2, 5.4; SOC 2 CC6.1, CC6.3 | AG42: New
A43: SRV-IAM-08 | B43: Server Security | C43: Authentication and Access Control | D43: Service accounts are inventoried, owned, least-privileged and protected | E43: All | F43: Control non-human identities that run services and scheduled jobs. | G43: Service accounts are frequently over-privileged and never rotated, making them prime targets. | H43: Kerberoasting, over-privileged service credentials, secret theft. | I43: Are service accounts inventoried with owners, non-interactive, least-privileged, and using managed identities, gMSA or vaulted secrets with rotation? | J43: Preventive | K43: - Service account register - gMSA list - SPN review - password-age report - vault records | L43: AD: `Get-ADServiceAccount -Filter *` and `Get-ADUser -Filter {ServicePrincipalName -like "*"} -Properties PasswordLastSet,ServicePrincipalName`. Windows services: `Get-CimInstance Win32_Service | select Name,StartName`. Linux: review systemd units for `User=root`; `getent passwd | awk -F: '$7!~/nologin|false/'`. Verify interactive logon rights are denied and membership of privileged groups is justified. | O43: ● | Q43: ● | R43: ● | T43: High | U43: AD service account reports; PAM discovery. | V43: 4 | W43: 4 | X43: =V43*W43 -> 16 | Y43: =INDEX(Risk_Model!$B$30:$B$33,MATCH(X43,Risk_Model!$A$30:$A$33,1)) -> High | Z43: 2 | AA43: Service accounts are unknown and use shared passwords. | AB43: Register with owners and password rotation for critical accounts. | AC43: Managed identities and gMSA throughout, with anomaly detection on service account use. | AD43: Inventory service accounts, move to gMSA or managed identities, rotate secrets, and deny interactive logon. | AE43: NIST SP 800-63B; NIST SP 800-53 Rev.5 AC and IA families; CIS Controls 5 and 6; Windows LAPS documentation | AF43: ISO 27001:2022 A.5.16, A.5.18, A.8.2; NIST CSF 2.0 PR.AA-01; CIS v8.1 5.2, 5.5; SOC 2 CC6.1, CC6.2 | AG43: New
A44: SRV-IAM-09 | B44: Server Security | C44: Authentication and Access Control | D44: Root login and privilege escalation on Linux are restricted and logged | E44: Linux | F44: Control how administrators gain root so that elevated actions are limited and attributable. | G44: Unrestricted sudo or direct root login removes accountability and eases privilege escalation. | H44: Privilege escalation through sudo misconfiguration and unaccountable root activity. | I44: Is direct root login restricted, and is sudo or PAM-based escalation limited to required commands, logged and free of NOPASSWD ALL rules? | J44: Preventive | K44: - sudoers files - sshd configuration - PAM configuration - sudo logs | L44: `sshd -T | grep permitrootlogin`, `grep -R "NOPASSWD\|ALL=(ALL" /etc/sudoers /etc/sudoers.d`, `visudo -c`. Check sudo I/O logging with `grep -i "log_input\|log_output" /etc/sudoers*` and lockout with `grep pam_faillock /etc/pam.d/*`. Windows analogue: `reg query HKLM\SOFTWARE\Microsoft\Windows\CurrentVersion\Policies\System /v EnableLUA`. | O44: ● | Q44: ● | R44: ● | T44: High | U44: OpenSCAP and Ansible audits of sudoers and sshd. | V44: 3 | W44: 4 | X44: =V44*W44 -> 12 | Y44: =INDEX(Risk_Model!$B$30:$B$33,MATCH(X44,Risk_Model!$A$30:$A$33,1)) -> High | Z44: 2 | AA44: Direct root login and unrestricted sudo. | AB44: Root login disabled and sudo restricted by role. | AC44: Just-in-time privilege with session recording and command-level auditing. | AD44: Disable direct root SSH, scope sudo rules, require authentication, and log all elevated commands. | AE44: NIST SP 800-63B; NIST SP 800-53 Rev.5 AC and IA families; CIS Controls 5 and 6; Windows LAPS documentation | AF44: ISO 27001:2022 A.8.2, A.8.18; NIST CSF 2.0 PR.AA-05; CIS v8.1 5.4, 6.8; SOC 2 CC6.3 | AG44: New
A45: SRV-ADM-01 | B45: Server Security | C45: Secure Administration | D45: Only secure protocols are used for administration and credential transmission | E45: All | F45: Protect administrative sessions and credentials from interception and downgrade. | G45: Cleartext or weak administrative protocols expose credentials to anyone on the network path. | H45: Credential interception, adversary-in-the-middle, protocol downgrade (telnet, FTP, SMBv1, NTLMv1, HTTP). | I45: Are only encrypted, authenticated protocols used for administration (SSH, RDP with NLA/TLS, WinRM over HTTPS, HTTPS consoles), with legacy protocols disabled? | J45: Preventive | K45: - Protocol configuration - listening-service inventory - firewall rules for admin ports - scan results showing no cleartext admin protocols | L45: Windows: RDP NLA via `(Get-ItemProperty "HKLM:\SYSTEM\CurrentControlSet\Control\Terminal Server\WinStations\RDP-Tcp").UserAuthentication`; `winrm enumerate winrm/config/listener`; `Get-SmbServerConfiguration | select RequireSecuritySignature,EnableSMB1Protocol`; LmCompatibilityLevel under `HKLM\SYSTEM\CurrentControlSet\Control\Lsa`. Linux: `sshd -T | egrep "ciphers|macs|kexalgorithms"` and `ss -tlnp | egrep ":23 |:21 |:80 "`. Authorised scan: `nmap -sV -p 21,23,80,445,3389,5985,5986 <ip>`. | O45: ● | Q45: ● | R45: ● | T45: High | U45: Nmap and credentialed scanner checks; OpenSCAP and CIS-CAT. | V45: 3 | W45: 4 | X45: =V45*W45 -> 12 | Y45: =INDEX(Risk_Model!$B$30:$B$33,MATCH(X45,Risk_Model!$A$30:$A$33,1)) -> High | Z45: 3 | AA45: Cleartext and legacy protocols in use. | AB45: Secure protocols mandated and legacy disabled on most servers. | AC45: Enforced by baseline with continuous verification and alerts on cleartext admin traffic. | AD45: Disable legacy protocols, require NLA/TLS and SSH with modern ciphers, and enforce SMB signing. | AE45: NIST SP 800-53 Rev.5 AC-17; Microsoft privileged access (enterprise access model); CIS Controls 4 and 12 | AF45: ISO 27001:2022 A.8.5, A.8.21, A.8.24; NIST CSF 2.0 PR.DS-02, PR.AA-03; CIS v8.1 3.10, 4.6; SOC 2 CC6.1, CC6.7 | AG45: 12.2
A46: SRV-ADM-02 | B46: Server Security | C46: Secure Administration | D46: Servers are administered only from hardened administrative workstations or jump hosts | E46: All | F46: Keep administrator credentials off general-purpose, internet-exposed workstations. | G46: Admin credentials typed on a compromised daily-use machine hand attackers the keys to the servers. | H46: Theft of administrator credentials from compromised workstations. | I46: Are servers administered only from dedicated, hardened workstations or jump hosts that meet endpoint security requirements, with direct administration from standard workstations blocked? | J46: Preventive | K46: - PAW or bastion standard - firewall rules allowing admin protocols only from jump hosts - PAW compliance reports - session logs | L46: Review firewall and host-firewall rules for source restrictions on 22, 3389, 5985 and 5986. Attempt administrative logon from a standard workstation (expect failure). Verify the PAW build baseline, no email or browsing, MFA and EDR, and sample session recordings. | O46: ● | P46: ● | Q46: ● | T46: Medium | U46: Firewall rule analysis; PAW compliance via Intune or Defender. | V46: 3 | W46: 5 | X46: =V46*W46 -> 15 | Y46: =INDEX(Risk_Model!$B$30:$B$33,MATCH(X46,Risk_Model!$A$30:$A$33,1)) -> High | Z46: 3 | AA46: Administration from any workstation. | AB46: Jump hosts or PAWs required for administration of critical servers. | AC46: Tiered administration with enforced PAWs, session recording and just-in-time access. | AD46: Introduce a tiered admin model with PAWs or bastions and block admin protocols from other sources. | AE46: NIST SP 800-53 Rev.5 AC-17; Microsoft privileged access (enterprise access model); CIS Controls 4 and 12 | AF46: ISO 27001:2022 A.8.2, A.8.20; NIST CSF 2.0 PR.AA-05, PR.IR-01; CIS v8.1 4.6, 12.8; SOC 2 CC6.1, CC6.6 | AG46: 12.1
A47: SRV-BCK-01 | B47: Server Security | C47: Backup, Restore and Recovery | D47: Operationally critical servers are covered by a defined backup scope with RPO and RTO | E47: All | F47: Ensure critical data, configuration and system state can be recovered to agreed objectives. | G47: Unrecoverable data loss or prolonged outage is an existential risk for many organisations, particularly under ransomware. | H47: Permanent data loss and unrecoverable ransomware outage. | I47: Are all servers holding operationally critical data or services included in a documented backup scope with defined recovery point and recovery time objectives? | J47: Corrective | K47: - Critical-system register with RPO/RTO - backup job list versus server inventory - backup success reports (30 days) | L47: Reconcile backup console assets with the server inventory and business-critical list. Check the last successful backup per server and the follow-up of failures. Windows: `vssadmin list shadows`, `Get-WBSummary`. Linux: `systemctl list-timers | grep -i backup`. Confirm system state and configuration are backed up, not just data. | N47: ● | Q47: ● | R47: ● | T47: High | U47: Backup platform API reconciled with CMDB; failure alerts to ticketing. | V47: 3 | W47: 5 | X47: =V47*W47 -> 15 | Y47: =INDEX(Risk_Model!$B$30:$B$33,MATCH(X47,Risk_Model!$A$30:$A$33,1)) -> High | Z47: 3 | AA47: Backups are informal and incomplete. | AB47: Documented scope with RPO/RTO and monitored backup jobs. | AC47: Scope driven by business impact analysis, with automated coverage assurance. | AD47: Define RPO/RTO from the business impact analysis, onboard all critical servers, and alert on missed or failed jobs. | AE47: NIST SP 800-34 Rev.1; 3-2-1-1-0 backup practice; CIS Control 11 | AF47: ISO 27001:2022 A.8.13, A.5.29, A.5.30; NIST CSF 2.0 PR.DS-11, ID.AM-05; CIS v8.1 11.1, 11.2; SOC 2 A1.2, CC9.1 | AG47: 7.1
A48: SRV-BCK-02 | B48: Server Security | C48: Backup, Restore and Recovery | D48: System, application and data restoration procedures are documented and accessible | E48: All | F48: Ensure recovery can be executed under pressure by someone other than the original author. | G48: Slow or failed recovery extends outage costs; plans stored only on affected systems are unusable. | H48: Delayed or failed recovery during incidents. | I48: Are system, application, configuration and data restoration procedures documented, current, available offline, and aligned to BCP and DR plans? | J48: Corrective | K48: - Restoration runbooks - DR plan - offline copy location - last review date - dependency map | L48: Review runbooks for restoration order, credential escrow, licence keys and dependencies (DNS, AD, certificates). Confirm copies are accessible without production services (offline or printed). Ask an engineer to walk through a bare-metal restore of a critical server. | M48: ● | N48: ● | T48: Low | U48: Runbook review reminders in the document system. | V48: 3 | W48: 4 | X48: =V48*W48 -> 12 | Y48: =INDEX(Risk_Model!$B$30:$B$33,MATCH(X48,Risk_Model!$A$30:$A$33,1)) -> High | Z48: 2 | AA48: No documented recovery procedures. | AB48: Documented runbooks reviewed annually and available offline. | AC48: Runbooks tested in exercises and updated after every change or test. | AD48: Write and test runbooks including dependencies, and keep an offline copy. | AE48: NIST SP 800-34 Rev.1; 3-2-1-1-0 backup practice; CIS Control 11 | AF48: ISO 27001:2022 A.5.30, A.5.29; NIST CSF 2.0 RC.RP-01; CIS v8.1 11.1; SOC 2 A1.3, CC9.1 | AG48: 7.1
A49: SRV-BCK-03 | B49: Server Security | C49: Backup, Restore and Recovery | D49: Backups are verified and restores are tested on a defined schedule | E49: All | F49: Prove that backups are usable and that recovery meets objectives. | G49: Untested backups frequently fail when needed; testing converts assumption into assurance. | H49: Silent backup failure or corruption discovered during a crisis. | I49: Are backups integrity-verified and restore-tested at least monthly for critical systems and at least annually for full DR, with results recorded? | J49: Detective | K49: - Restore test reports - backup verification logs - DR exercise results with achieved RTO and RPO - remediation actions | L49: Select 3 critical servers and obtain the latest restore-test evidence (date, scope, success, time versus RTO). If none exists, perform a supervised test restore to an isolated network. Review failures and corrective actions. | N49: ● | P49: ● | Q49: ● | T49: Medium | U49: Backup platform automated recovery verification (for example sandbox restore testing). | V49: 3 | W49: 5 | X49: =V49*W49 -> 15 | Y49: =INDEX(Risk_Model!$B$30:$B$33,MATCH(X49,Risk_Model!$A$30:$A$33,1)) -> High | Z49: 3 | AA49: Restores are never tested. | AB49: Monthly verification and annual DR test with documented results. | AC49: Automated recovery verification with measured RTO/RPO against targets. | AD49: Schedule monthly verification and annual DR tests, record results, and fix failures. | AE49: NIST SP 800-34 Rev.1; 3-2-1-1-0 backup practice; CIS Control 11 | AF49: ISO 27001:2022 A.8.13, A.5.30; NIST CSF 2.0 PR.DS-11, RC.RP-03; CIS v8.1 11.5; SOC 2 A1.3, CC7.5 | AG49: 7.1
A50: SRV-BCK-04 | B50: Server Security | C50: Backup, Restore and Recovery | D50: An off-site and offline or immutable backup copy exists | E50: All | F50: Ensure at least one recovery copy survives site loss and attacker deletion. | G50: Ransomware operators target backups first; immutable and offline copies determine whether recovery is possible without paying. | H50: Ransomware encrypting or deleting online backups, and same-site disaster. | I50: Does the backup strategy include at least one off-site copy and one offline or immutable copy protected from deletion by compromised administrator credentials? | J50: Corrective | K50: - Backup architecture diagram - immutability and retention-lock settings - off-site location contract - deletion-protection configuration | L50: In a test scope, attempt deletion of a restore point using a production backup-admin account (expect denial). Cloud checks: `aws s3api get-object-lock-configuration --bucket <bucket>`; Azure immutable storage policy; Veeam hardened repository settings. Confirm geographic separation of the off-site copy. | O50: ● | P50: ● | Q50: ● | T50: Medium | U50: Cloud storage policy queries; backup platform configuration export. | V50: 4 | W50: 5 | X50: =V50*W50 -> 20 | Y50: =INDEX(Risk_Model!$B$30:$B$33,MATCH(X50,Risk_Model!$A$30:$A$33,1)) -> Critical | Z50: 3 | AA50: All backups are online in the same site. | AB50: Off-site copy exists and a separate offline or immutable copy is maintained. | AC50: Immutable, geographically separated copies with verified deletion protection and regular tests. | AD50: Implement immutable or offline copies off-site and require dual authorisation for deletion. | AE50: NIST SP 800-34 Rev.1; 3-2-1-1-0 backup practice; CIS Control 11 | AF50: ISO 27001:2022 A.8.13, A.8.14; NIST CSF 2.0 PR.DS-11, PR.IR-03; CIS v8.1 11.3, 11.4; SOC 2 A1.2 | AG50: 7.1
A51: SRV-BCK-05 | B51: Server Security | C51: Backup, Restore and Recovery | D51: Backups are encrypted in transit and at rest and media is handled securely | E51: All | F51: Protect confidentiality of backup data wherever it is stored or transmitted. | G51: Backups contain the full data set; their compromise is equivalent to a breach of the source systems. | H51: Theft or exposure of backup copies and interception in transit. | I51: Are backups encrypted in transit and at rest, with keys managed separately from the backup data, and is backup media handled per a media security standard? | J51: Preventive | K51: - Backup job encryption settings - key management records - transport protocol configuration - media handling standard - courier and vault logs | L51: Inspect job settings for encryption and TLS. Confirm key escrow is separate from the backup server. Sample tape or media chain-of-custody records. Confirm via capture or scan that backup traffic is encrypted. | N51: ● | O51: ● | Q51: ● | T51: Medium | U51: Backup platform configuration export; network protocol scan. | V51: 3 | W51: 4 | X51: =V51*W51 -> 12 | Y51: =INDEX(Risk_Model!$B$30:$B$33,MATCH(X51,Risk_Model!$A$30:$A$33,1)) -> High | Z51: 2 | AA51: Backups are unencrypted and media handling is informal. | AB51: Encryption enabled with documented key management and media standard. | AC51: End-to-end encryption with HSM or KMS-managed keys and audited media handling. | AD51: Enable backup encryption, separate key management, and adopt a media handling standard. | AE51: NIST SP 800-34 Rev.1; 3-2-1-1-0 backup practice; CIS Control 11 | AF51: ISO 27001:2022 A.8.24, A.8.13, A.7.10; NIST CSF 2.0 PR.DS-01, PR.DS-02; CIS v8.1 3.10, 3.11, 11.3; SOC 2 CC6.7 | AG51: 7.1
A52: SRV-BCK-06 | B52: Server Security | C52: Backup, Restore and Recovery | D52: Backup infrastructure and credentials are segregated from production administration | E52: All | F52: Prevent a single compromised administrator or domain from destroying both production and backups. | G52: Backup systems joined to the production domain are routinely compromised and wiped in ransomware attacks. | H52: Compromised domain administrator deleting production data and backups. | I52: Are backup servers, consoles and credentials separated from production administration through separate identities, MFA, network isolation and restricted console access? | J52: Preventive | K52: - Backup server domain status - admin role assignments - MFA configuration - firewall rules - backup console audit logs | L52: Windows: `(Get-CimInstance Win32_ComputerSystem).PartOfDomain` to determine whether the backup server is domain-joined. Review membership of backup administrator groups and MFA on the console. Check that deletion and retention-change actions are audited and alerted. | M52: ● | O52: ● | Q52: ● | T52: Medium | U52: Backup platform audit log export; AD group membership reports. | V52: 4 | W52: 5 | X52: =V52*W52 -> 20 | Y52: =INDEX(Risk_Model!$B$30:$B$33,MATCH(X52,Risk_Model!$A$30:$A$33,1)) -> Critical | Z52: 3 | AA52: Backup servers are domain-joined and managed by domain administrators. | AB52: Dedicated backup administrators with MFA and restricted network access. | AC52: Isolated backup domain or workgroup, dual authorisation for destructive actions and alerts. | AD52: Separate backup identities and network from production, require MFA, and alert on destructive actions. | AE52: NIST SP 800-34 Rev.1; 3-2-1-1-0 backup practice; CIS Control 11 | AF52: ISO 27001:2022 A.8.13, A.8.2, A.8.22; NIST CSF 2.0 PR.AA-05, PR.IR-01; CIS v8.1 5.4, 6.5, 11.3; SOC 2 CC6.1, CC6.3 | AG52: New
A53: SRV-DAT-01 | B53: Server Security | C53: Data Protection | D53: Sensitive data on servers is encrypted at rest | E53: All | F53: Protect data on disks, volumes and databases from exposure through theft or improper access to storage. | G53: Encryption at rest limits the impact of lost drives, snapshots and storage-level access. | H53: Data exposure from stolen disks, backups and snapshots. | I53: Is sensitive data encrypted at rest through full-disk, volume or database encryption, with keys protected and recoverable? | J53: Preventive | K53: - BitLocker or LUKS status - key escrow records (AD, Entra, KMS) - database TDE settings - virtual disk encryption | L53: Windows: `manage-bde -status` and `Get-BitLockerVolume`. Linux: `lsblk -f` (look for crypto_LUKS) and `cryptsetup status <name>`. SQL Server: `SELECT name,is_encrypted FROM sys.databases`. Verify recovery key escrow and who can retrieve keys. | O53: ● | Q53: ● | R53: ● | T53: High | U53: BitLocker reports through Intune or MBAM; configuration management queries. | V53: 3 | W53: 4 | X53: =V53*W53 -> 12 | Y53: =INDEX(Risk_Model!$B$30:$B$33,MATCH(X53,Risk_Model!$A$30:$A$33,1)) -> High | Z53: 2 | AA53: No encryption at rest. | AB53: Encryption on servers holding sensitive data with escrowed keys. | AC53: Encryption everywhere with managed rotation and monitoring of key access. | AD53: Enable disk and database encryption, escrow recovery keys, and restrict retrieval. | AE53: NIST SP 800-111; NIST SP 800-52 Rev.2; CIS Control 3 | AF53: ISO 27001:2022 A.8.24; NIST CSF 2.0 PR.DS-01; CIS v8.1 3.11; SOC 2 CC6.1, CC6.7 | AG53: New
A54: SRV-DAT-02 | B54: Server Security | C54: Data Protection | D54: Server services use current TLS versions, strong ciphers and managed certificates | E54: All | F54: Ensure encrypted channels are actually strong and certificates are valid and managed. | G54: Weak protocols enable decryption and downgrade; expired certificates cause outages. | H54: Downgrade and adversary-in-the-middle attacks, weak cipher decryption, expired certificates. | I54: Do services use TLS 1.2 or higher with strong cipher suites and valid, managed certificates, with SSLv3 and TLS 1.0/1.1 disabled? | J54: Preventive | K54: - TLS scan results - certificate inventory with expiry dates - SChannel or OpenSSL configuration - cryptographic standard | L54: `nmap --script ssl-enum-ciphers -p 443,636,3389 <ip>` or `testssl.sh <host>:443`. Windows: `Get-TlsCipherSuite` and the SCHANNEL registry keys under `HKLM\SYSTEM\CurrentControlSet\Control\SecurityProviders\SCHANNEL\Protocols`. Linux: `openssl ciphers -v`; certificate expiry via `openssl s_client -connect <host>:443 | openssl x509 -noout -dates`. | Q54: ● | R54: ● | T54: High | U54: testssl.sh or SSL Labs-style scanning; certificate lifecycle management tools. | V54: 3 | W54: 4 | X54: =V54*W54 -> 12 | Y54: =INDEX(Risk_Model!$B$30:$B$33,MATCH(X54,Risk_Model!$A$30:$A$33,1)) -> High | Z54: 2 | AA54: Legacy protocols and unmanaged certificates. | AB54: Cryptographic standard enforced on most services with certificate inventory. | AC54: Automated crypto compliance scanning and certificate renewal. | AD54: Disable legacy protocols and weak ciphers, inventory certificates, and automate renewal. | AE54: NIST SP 800-111; NIST SP 800-52 Rev.2; CIS Control 3 | AF54: ISO 27001:2022 A.8.24; NIST CSF 2.0 PR.DS-02; CIS v8.1 3.10; SOC 2 CC6.7 | AG54: 12.2
A55: SRV-DAT-03 | B55: Server Security | C55: Data Protection | D55: File systems enforce access control and permissions on sensitive data | E55: All | F55: Ensure storage uses file systems capable of enforcing permissions and that permissions are appropriate. | G55: Without enforceable permissions, any local or network user can read or alter sensitive data. | H55: Unauthorised data access or modification on file systems without permission enforcement. | I55: Are non-removable media formatted with access-control-capable file systems (NTFS, ReFS, ext4/XFS with ACLs), with appropriate permissions and no FAT file systems for sensitive volumes? | J55: Preventive | K55: - File system listing - permission baselines - ACL exports for sensitive paths | L55: Windows: `Get-Volume | select DriveLetter,FileSystem` and `icacls D:\Data`. Linux: `lsblk -f`, `mount | grep -E "vfat|ntfs-3g"`, `getfacl -R /srv/data | head`, and `findmnt` to check nodev, nosuid and noexec options where appropriate. | O55: ● | Q55: ● | R55: ● | T55: High | U55: Configuration management file system and ACL reports. | V55: 2 | W55: 4 | X55: =V55*W55 -> 8 | Y55: =INDEX(Risk_Model!$B$30:$B$33,MATCH(X55,Risk_Model!$A$30:$A$33,1)) -> Medium | Z55: 1 | AA55: Sensitive data on file systems without permission support. | AB55: Access-control file systems with documented permission standards. | AC55: Permissions baselined and monitored with automated drift detection. | AD55: Migrate sensitive volumes to ACL-capable file systems and apply least-privilege permissions. | AE55: NIST SP 800-111; NIST SP 800-52 Rev.2; CIS Control 3 | AF55: ISO 27001:2022 A.8.3, A.5.15; NIST CSF 2.0 PR.AA-05, PR.DS-01; CIS v8.1 3.3; SOC 2 CC6.1, CC6.3 | AG55: 1.2
A56: SRV-GOV-01 | B56: Server Security | C56: Governance, Ownership and Risk | D56: Every server is registered in an authoritative inventory reconciled with discovery | E56: All | F56: Maintain an accurate record of all servers, their role, owner and lifecycle. | G56: Unknown servers are unpatched, unmonitored and unowned, and are favoured footholds for attackers. | H56: Shadow or forgotten servers. | I56: Is every server registered in an authoritative inventory or CMDB (owner, role, OS, criticality, location, network address, lifecycle), and is it reconciled with network discovery? | J56: Detective | K56: - CMDB export - network discovery results - reconciliation report - registration procedure | L56: Obtain discovery data (`nmap -sn <subnets>`, DHCP, DNS and ARP exports, hypervisor inventory, cloud APIs) and compare it with the CMDB. Quantify unmatched hosts in both directions and check mandatory fields for completeness. | N56: ● | Q56: ● | R56: ● | T56: High | U56: Scheduled discovery reconciled with CMDB via API. | V56: 3 | W56: 4 | X56: =V56*W56 -> 12 | Y56: =INDEX(Risk_Model!$B$30:$B$33,MATCH(X56,Risk_Model!$A$30:$A$33,1)) -> High | Z56: 3 | AA56: No reliable server inventory. | AB56: Maintained CMDB with a registration step in provisioning. | AC56: Automated discovery and reconciliation with exceptions closed within defined time. | AD56: Make registration part of provisioning and reconcile discovery with the CMDB at least monthly. | AE56: ISO/IEC 27005; NIST SP 800-30 Rev.1; NIST SP 800-53 Rev.5 RA and SA families; ISO/IEC 27036 (supplier relationships) | AF56: ISO 27001:2022 A.5.9; NIST CSF 2.0 ID.AM-01, ID.AM-02; CIS v8.1 1.1, 1.2; SOC 2 CC6.1 | AG56: 10.1
A57: SRV-GOV-02 | B57: Server Security | C57: Governance, Ownership and Risk | D57: Every server has accountable owners, a criticality rating and a data classification | E57: All | F57: Ensure clear accountability and risk-based treatment of each server. | G57: Unclear ownership delays response and leaves patching, backup and monitoring unprioritised. | H57: Unmanaged systems and misprioritised protection. | I57: Does every server have a named business owner, system administrator and application administrator approved by management, with criticality and data classification recorded and responsibilities for server-standard compliance documented? | J57: Preventive | K57: - Owner and administrator register - management approval - criticality and classification ratings - RACI - list of applications with administrators | L57: Sample 10 servers and verify named owners and administrators are current employees and approved. Confirm criticality and classification drive patching, backup and monitoring tiers. Verify application administrators are accountable for application-level compliance with the server standard. | M57: ● | N57: ● | T57: Medium | U57: CMDB mandatory fields; HR-to-CMDB owner validation. | V57: 3 | W57: 3 | X57: =V57*W57 -> 9 | Y57: =INDEX(Risk_Model!$B$30:$B$33,MATCH(X57,Risk_Model!$A$30:$A$33,1)) -> Medium | Z57: 2 | AA57: Ownership is unknown or informal. | AB57: Named owners and administrators recorded with criticality. | AC57: Automated owner validation and risk-based service tiers driving controls. | AD57: Make owner, administrators, criticality and classification mandatory CMDB fields with periodic validation. | AE57: ISO/IEC 27005; NIST SP 800-30 Rev.1; NIST SP 800-53 Rev.5 RA and SA families; ISO/IEC 27036 (supplier relationships) | AF57: ISO 27001:2022 A.5.2, A.5.9, A.5.12, A.5.13; NIST CSF 2.0 GV.RR-02, ID.AM-05; CIS v8.1 1.1, 3.2; SOC 2 CC1.3 | AG57: 8.1, 8.2
A58: SRV-GOV-03 | B58: Server Security | C58: Governance, Ownership and Risk | D58: A security review and risk assessment is completed before production and on significant change | E58: All | F58: Ensure risk is understood and formally accepted before a server enters service. | G58: Risk assessed after go-live is difficult to remediate and leaves leadership accepting unknown exposure. | H58: Unassessed systems deployed with unmanaged risk. | I58: Is a security review and risk assessment completed for new servers and significant changes before production by an approved assessor, with residual risk accepted by the owner? | J58: Preventive | K58: - Risk assessment reports - reviewer qualification - risk acceptance forms - review schedule | L58: Sample 5 new servers and verify the risk assessment date precedes go-live, the assessor, findings and the owner's risk acceptance. Confirm re-assessment triggers and scheduled review dates exist. | M58: ● | N58: ● | T58: Low | U58: Workflow gate in provisioning requiring an attached assessment ID. | V58: 3 | W58: 4 | X58: =V58*W58 -> 12 | Y58: =INDEX(Risk_Model!$B$30:$B$33,MATCH(X58,Risk_Model!$A$30:$A$33,1)) -> High | Z58: 2 | AA58: No pre-production risk assessment. | AB58: Standard assessment completed with owner acceptance for new servers. | AC58: Threat-informed assessments integrated into provisioning with periodic reassessment. | AD58: Introduce a mandatory pre-production risk assessment and risk acceptance step, and reassess on change. | AE58: ISO/IEC 27005; NIST SP 800-30 Rev.1; NIST SP 800-53 Rev.5 RA and SA families; ISO/IEC 27036 (supplier relationships) | AF58: ISO 27001:2022 A.5.8, A.8.29; NIST CSF 2.0 ID.RA-05, ID.RA-06; CIS v8.1 N/A; SOC 2 CC3.2, CC8.1 | AG58: 9.1, 9.2
A59: SRV-GOV-04 | B59: Server Security | C59: Governance, Ownership and Risk | D59: Third-party system administration and hosting are governed through contracts and access controls | E59: All | F59: Manage risk introduced by vendors who administer, host or support servers. | G59: Third parties with privileged access are a leading supply-chain breach vector. | H59: Third-party compromise and unmanaged vendor access. | I59: Are contracts for outsourced administration, hosting and support reviewed for security and risk clauses (access, audit rights, breach notification, subcontractors), and is third-party access controlled? | J59: Preventive | K59: - Contracts and security schedules - vendor risk assessments - third-party access list - SOC 2 or ISO reports - vendor remote-access logs | L59: Sample 3 contracts for required clauses. Review vendor accounts and remote access methods (MFA, session recording, time-bound access). Obtain assurance reports and map complementary user entity controls to internal controls. | M59: ● | N59: ● | Q59: ● | T59: Low | U59: Vendor access reports from PAM; vendor risk platform integration. | V59: 3 | W59: 4 | X59: =V59*W59 -> 12 | Y59: =INDEX(Risk_Model!$B$30:$B$33,MATCH(X59,Risk_Model!$A$30:$A$33,1)) -> High | Z59: 2 | AA59: Vendors have standing access with no security terms. | AB59: Contracts include security clauses and vendor access is controlled. | AC59: Continuous vendor monitoring, just-in-time recorded access, and annual assurance review. | AD59: Add security clauses and audit rights, enforce MFA and recorded just-in-time vendor access, and review assurance reports. | AE59: ISO/IEC 27005; NIST SP 800-30 Rev.1; NIST SP 800-53 Rev.5 RA and SA families; ISO/IEC 27036 (supplier relationships) | AF59: ISO 27001:2022 A.5.19, A.5.20, A.5.21, A.5.22; NIST CSF 2.0 GV.SC-05, GV.SC-06; CIS v8.1 15.1, 15.4; SOC 2 CC9.2 | AG59: 9.5
